Workbook

Sheet Jan_2024_FinancialReport
D2: OUR LADY OF THE MOST HOLY ROSARY
D3: Sub-Parish
D4: Diamond Crest Village
D5: Bgy. San Manuel, City of San Jose del Monte
G8: FINANCIAL REPORT
G9: January 2024
B12: Beginning balance as of January 01, 2024\\ | O12: 12090
I13: Less : Add'l | K13: Net
B14: Mass Collections for: | G14: Sunday | I14: Stipend | K14: Amount
D15: January | F15: 01 | G15: 1276 | I15: 0 | K15: 1276
F16: 07 | G16: (no mass)
F17: 14 | G17: 1860 | K17: 1860
F18: 21 | G18: 2590 | I18: 1000 | K18: 1590
F19: 28 | G19: 2376 | I19: 1000 | K19: 1376
D20: Sub-total | G20: =SUM(G15:G19) -> 8102 | I20: 2000 | K20: =SUM(K14:K19) -> 6102 | M20: 6102
B21: Add: Donations/Thanksgiving:
B22: Date | F22: Donor | I22: Rcpt. # | K22: Amount
F23: Donations / Pamisa | K23: 2200
B25: TOTAL COLLECTION FOR January …………… | O25: 8302
B27: TOTAL CASH AVAILABLE ……………. | O27: =SUM(O12:O25) -> 20392
B29: Less: | D29: Expenses for January:
B30: Date | D30: PCV # | G30: P A R T I C U L A R S | M30: Amount
B31: 01/04/24 | F31: Desk Fan repair | M31: 300
B32: 01/10/24 | F32: Wire screen for back door | M32: 540
B33: 01/13/24 | F33: Michael - labor: removed x'mas lights | M33: 500
B34: 01/18/24 | F34: Office supplies | M34: 122
B35: 01/16/24 | F35: Meralco/Water Bills (2 mos.) | M35: 2457.45
B36: 01/21/24 | F36: SLRP Anniversary | M36: 3500
B37: TOTAL EXPENSES FOR JANUARY ……………………………………… | O37: =SUM(M31:M36) -> 7419.45
D39: Cash Balance as of January 31, 2024 …………………… | O39: 12972.55
D41: Cash in Bank as of December 31, 2024 | M41: 47848.34
D42: Add: | F42: Interest (net of w/holding tax) | M42: 4.12
D43: Cash in Bank as of January 31, 2024 | M43: =SUM(M41:M42) -> 47852.46
B46: Prepared by | F46: Checked by | I46: Audited by: | M46: Noted by:
F49: Fely Rabano | I49: Tina Murla | M49: Lucky Tiu
B50: Asst. Treasurer | F50: Treasurer | I50: Auditor | M50: President

Sheet Jan. 2024_AckReceipt
G2: Our Lady of the Most Holy Rosary (Sub-Parish)
A3: Control File - Receipts
A4: Month of January 2024
G6: Pamisa & | L6: from mass | M6: Total
A7: Date | D7: Rcpt. # | F7: Donor | G7: Thanksgiving | I7: Donation | J7: Stipend | L7: collection | M7: Stipend | N7: Date
A8: Jan.
A9: 01 | D9: 2563 | F9: F. Rabano | G9: 100
A10: 01 | D10: 2564 | F10: Jane Pasamba | G10: 100
A11: 01 | D11: 2565 | F11: Elmer Buere | G11: 100
A12: 01 | D12: 2566 | F12: Leony Aviles | G12: 200
A13: 01 | D13: 2567 | F13: Beng Grafil | G13: 300
A14: 01 | D14: 2568 | F14: Tina Murla | G14: 500 | J14: =SUM(G9:G14) -> 1300 | L14: 200 | M14: 1500 | N14: Jan. 04
A15: 14 | D15: 2569 | F15: Imelda | G15: 100
A16: 14 | D16: 2570 | F16: Gina Albarido | G16: 100
A17: 14 | D17: 2572 | F17: Lucy Saramosing | G17: 100
A18: 14 | D18: 2573 | F18: Jane Pasamba | G18: 100
A19: 14 | D19: 2574 | F19: Art de Leon | G19: 500
A20: 14 | D20: 2575 | F20: Elmer Buere | G20: 100
A21: 14 | D21: 2576 | F21: Leo Grafil | G21: 100
A22: 14 | D22: 2577 | F22: Nida Alberto | G22: 1000
A23: 14 | D23: 2578 | F23: Baby Boris | G23: 100 | I23: 1100 | M23: 1000 | N23: Jan. 15
A24: 21 | D24: 2579 | F24: Thin Tapaon | G24: 100 | I24: 100 | L24: 1000 | M24: 1000 | N24: Jan. 21
A25: 28 | D25: 2571 | F25: Art de Leon | G25: 200
A26: 28 | D26: 2580 | F26: Gina Albarido | G26: 100
A27: 28 | D27: 2581 | F27: Art de Leon | G27: 200
A28: 28 | D28: 2582 | F28: Perla | G28: 100
A29: 28 | D29: 2583 | F29: Nanie Domingo | G29: 100
A30: 28 | D30: 2584 | F30: Elmer Buere | G30: 100
A31: 28 | D31: 2585 | F31: Susan | G31: 100
A32: 28 | D32: 2586 | F32: Thin Tapaon | G32: 100 | I32: =SUM(G25:G32) -> 1000 | L32: 1000 | M32: 1000 | N32: Jan. 28
I33: =SUM(I22:I32) -> 2200
D35: Prepared by:
A38: Date | J38: Stipend
A39: January | D39: 01 | F39: (New Year) | J39: 1500
D40: 07 | F40: No Mass)
D41: 14 | J41: 1000
D42: 21 | J42: 1000
D43: 28 | J43: 1000
J44: 4500

Sheet FEB_2024_Sched A
B2: Schedule A
B7: Our Lady of the Most Holy Rosary (Sub-Parish)
G8: Control File - Receipts
F9: For the month of February 2024
G11: DONATIONS (Mass Intentions:Thanksgiving, Souls, others) | H11: DONATIONS | I11: Net of Donations | J11: STIPEND from | L11: Total Stipend
B12: Date | D12: OR Number | F12: Donor | J12: Donations | K12: Mass Collections
B13: February
B14: 04 | D14: 2587 | F14: Art de Leon | G14: 100
B15: 04 | D15: 2588 | F15: Elmer Buere | G15: 100
B16: 04 | D16: 2589 | F16: Annie | G16: 20
B17: 04 | F17: No Offical Receipt | G17: 80
B18: Sub-Total | G18: =SUM(G14:G17) -> 300 | I18: =G18-J18 -> 0 | J18: 300 | K18: 700 | L18: =J18+K18 -> 1000
B19: 11 | D19: 2590 | F19: Fely Rabano | G19: 100
B20: 11 | D20: 2591 | F20: Gina Albarido | G20: 100
B21: 11 | D21: 2592 | F21: Jane P. | G21: 100
B22: 11 | D22: 2593 | F22: Imelda | G22: 100
B23: Sub-Total | G23: =SUM(G19:G22) -> 400 | I23: =G23-J23 -> 0 | J23: 400 | K23: 600 | L23: =J23+K23 -> 1000
B24: 18 | D24: 2594 | F24: Annie | G24: 50
B25: 18 | D25: 2595 | F25: Art de Leon | G25: 200
B26: 18 | D26: 2596 | F26: Elmer Buere | G26: 100
B27: 18 | D27: 2597 | F27: Hilda | G27: 200
B28: 18 | D28: 2598 | F28: Irene Masong | G28: 100
B29: 18 | D29: 2599 | F29: Aviles Family | G29: 150
B30: 18 | D30: 2600 | F30: Beng Grafil | G30: 100
B31: Sub-Total | G31: =SUM(G24:G30) -> 900 | I31: =G31-J31 -> 0 | J31: 900 | K31: 100 | L31: =J31+K31 -> 1000
B32: 25 | D32: 2601 | F32: Lourdes Galang | G32: 50
B33: 25 | D33: 2602 | F33: Annie | G33: 20
B34: 25 | D34: 2603 | F34: Art de Leon | G34: 200
B35: 25 | D35: 2604 | F35: Jane P. | G35: 100
B36: 25 | D36: 2605 | F36: Unused OR | G36: 0
B37: 25 | D37: 2606 | F37: Aviles Family | G37: 150
B38: Sub-Total | G38: =SUM(G32:G37) -> 520 | I38: =G38-J38 -> 50 | J38: 470 | K38: 530 | L38: =J38+K38 -> 1000
B39: TOTAL | G39: =G38+G31+G23+G18 -> 2120 | I39: =I38+I31+I23+I18 -> 50 | J39: =J38+J31+J23+J18 -> 2070 | K39: =K38+K31+K23+K18 -> 1930 | L39: =L38+L31+L23+L18 -> 4000
B48: Stipend for the month of February 2024
B50: Period covered | F50: Amount
B51: February | C51: 04 | F51: 1000
B52: February | C52: 11 | F52: 1000
B53: February | C53: 18 | F53: 1000
B54: February | C54: 25 | F54: 1000
B56: Total Stipend | F56: =SUM(F51:F54) -> 4000

Sheet FEB_2024_FR
C4: Our Lady of the Most Holy Rosary (Sub-Parish)
C5: Diamond Crest Village ,Brgy, San Manuel, San Jose DelMonte City, Bulacan
C7: FINANCIAL REPORT
C8: As of FEBRUARY 29, 2024
C10: Cash Balance as of February 01, 2024 | K10: P | L10: 12972.55
C12: Add: Receipts for the month of February
C14: Mass Collections: | G14: (Net of Stipend)
H16: Collections | I16: Stipend | J16: Net Amount
E18: February | G18: 04 | H18: =881 -> 881 | I18: 700 | J18: =H18-I18 -> 181
E19: February | G19: 11 | H19: 2340 | I19: 600 | J19: =H19-I19 -> 1740
E20: February | G20: 18 | H20: 1807 | I20: 100 | J20: =H20-I20 -> 1707
E21: February | G21: 25 | H21: 2225 | I21: 530 | J21: =H21-I21 -> 1695
E23: Total | H23: =SUM(H18:H21) -> 7253 | I23: =SUM(I18:I21) -> 1930 | J23: =SUM(J18:J21) -> 5323
C26: Donations from Mass Intentions : ( Schedule A)
E28: Donations (Net of Stipend) | J28: 50 | L28: =J23+J28 -> 5373 | N28: =L28-3915 -> 1458
C30: Total Cash Available | K30: P | L30: =L28+L10 -> 18345.55
C32: Less: Expenses for the month of February
C34: Date | E34: PCV # | G34: P articulars | J34: Amount
C36: 45506 | G36: Utility Expenses (Meralco/Water Bills ) | J36: 1206.8
C37: 45567 | G37: Electrical/Labor expenses -(c/o Jaime ) | J37: =575 -> 575
C38: 45598 | G38: SPPC Share for Annual Planning | J38: 1000
C39: 02/16/2024 | G39: Food Expenses ( Daan ng Krus ) | J39: 1134.5
C40: 02/22/2024 | G40: Repairs of cabinet | J40: 200 | L40: =SUM(J36:J40) -> 4116.3
C42: Net of Expenses | L42: =L30-L40 -> 14229.25
C44: Less: Deposits for the month of February | L44: 12090
C46: Cash Balance as of February 29, 2024 | K46: P | L46: =L42-L44 -> 2139.25
C50: Cash in Bank as of January 31, 2024 | K50: P | L50: 47852.46
C52: Add: Deposits - February 2024 | L52: 12090
C53: Interest ( Net of witholding tax ) | L53: =5.75-1.15 -> 4.6
C54: Cash in Bank as of February 29, 2024 | K54: P | L54: =SUM(L50:L53) -> 59947.06
C59: Prepared by: | G59: Checked by: | I59: Audited by: | L59: Noted by:
C61: Elvira Grafil | G61: Fely Rabano | I61: Tina Murla | L61: Lucky Tiu
C62: Asst. Treasurer | G62: Treasurer | I62: Auditor | L62: President

Sheet Mar_2024_FR
C4: Our Lady of the Most Holy Rosary (Sub-Parish)
C5: Diamond Crest Village ,Brgy, San Manuel, San Jose DelMonte City, Bulacan
C7: FINANCIAL REPORT
C8: As of MARCH 31, 2024
C10: Cash Balance as of March 01, 2024 | K10: P | L10: 2139.25
C12: Add: Receipts for the month of March
C14: Mass Collections: | G14: (Net of Stipend)
H16: Collections | I16: Stipend | J16: Net Amount
E18: March | G18: 03 | H18: 2320 | I18: 150 | J18: =H18-I18 -> 2170
E19: March | G19: 10 | H19: 0 | I19: 0 | J19: =H19-I19 -> 0 | N19: No mass
E20: March | G20: 17 | H20: 1288 | I20: 0 | J20: =H20-I20 -> 1288
E21: March | G21: 31 | H21: =930 -> 930 | I21: 900 | J21: =H21-I21 -> 30
E23: Total | H23: =SUM(H18:H21) -> 4538 | I23: =SUM(I18:I21) -> 1050 | J23: =SUM(J18:J21) -> 3488
C25: Alay Kapwa Collections | J25: 10400
C27: Donations from Mass Intentions : (see Schedule A) | J27: 0
E29: Donations ( net of Stipend ) | J29: ='Mar_2024_Sched A'!I37 -> 700 | L29: =J23+J25+J29 -> 14588 | N29: 14438 | O29: =550-J29 -> -150
C31: Total Cash Available | K31: P | L31: =L29+L10 -> 16727.25
C33: Less: Expenses for the month of March
C35: Date | E35: PCV # | G35: Particulars | J35: Amount
C37: 03/06/2024 | G37: Utility Expenses (Meralco & Water Bills ) | J37: 1326.6
C38: 03/06/2024 | G38: Candles | J38: 141.1
C39: 03/23/2024 | G39: Battery Charger | J39: 699
C40: 03/24/2024 | G40: Dry Clean Services ( Sto. Entiero clothes) | J40: 400
C41: 03/26/2024 | G41: Food Expenses ( PABASA & VIGIL) | J41: 559.75
C42: 03/26/2024 | G42: Repairs of Hot and Cold Dispenser | J42: 250
C43: 03/30/2024 | G43: Food Sharing ( for SLR Parish ) | J43: =1300+200 -> 1500 | L43: =SUM(J37:J43) -> 4876.45
C45: Net of Expenses | L45: =L31-L43 -> 11850.8
C47: Less: Deposits for the month of March 2024 | L47: 882.55
C49: Cash Balance as of March 31, 2024 | K49: P | L49: =L45-L47 -> 10968.25 | N49: =L45-L47 -> 10968.25
C53: Cash in Bank as of February 29, 2024 | K53: P | L53: 59947.06
C55: Add: Deposits - March 2024 | L55: 882.55
C56: Interest ( Net of witholding tax ) | L56: =6.53-1.31 -> 5.22
C57: Cash in Bank as of March 31, 2024 | K57: P | L57: =SUM(L53:L56) -> 60834.83
C62: Prepared by: | G62: Checked by: | I62: Audited by: | L62: Noted by:
C64: Elvira Grafil | G64: Fely Rabano | I64: Tina Murla | L64: Lucky Tiu
C65: Asst. Treasurer | G65: Treasurer | I65: Auditor | L65: President

Sheet Mar_2024_Sched A
B2: Schedule A
B7: Our Lady of the Most Holy Rosary (Sub-Parish)
G8: Control File - Receipts
F9: For the month of March 2024
G11: DONATIONS (Mass Intentions:Thanksgiving, Souls, others) | H11: DONATIONS | I11: Net of Donations | J11: STIPEND from | L11: Total Stipend
B12: Date | D12: OR Number | F12: Donor | J12: Donations | K12: Mass Collections
B13: March
B14: 03 | D14: 2607 | F14: Chris Levi | G14: 100
B15: 03 | D15: 2608 | F15: Elmer Buere | G15: 100
B16: 03 | D16: 2609 | F16: Art de Leon | G16: 200
B17: 03 | D17: 2610 | F17: Emeld Torres | G17: 100
B18: 03 | D18: 2611 | F18: Gina | G18: 100
B19: 03 | D19: 2612 | F19: Fely Rabano | G19: 100
B20: 03 | D20: 2613 | F20: Abeles | G20: 150
B21: Sub-Total | G21: =SUM(G14:G20) -> 850 | I21: =G21-J21 -> 0 | J21: 850 | K21: 150 | L21: =J21+K21 -> 1000
B22: 17 | D22: 2605 | F22: Art de Leon & Family | G22: 200
B23: 17 | D23: 2614 | F23: Elmer Buere | G23: 100
B24: 17 | D24: 2615 | F24: Jane Pasamba | G24: 100
B25: 17 | D25: 2616 | F25: Thin | G25: 100
B26: 17 | D26: 2617 | F26: R. Calonge | G26: 100
B27: 17 | D27: 2618 | F27: Hilda | G27: 100
B28: 17 | D28: 2619 | F28: Abeles | G28: 150
B29: 17 | D29: 2620 | F29: Belma | G29: 100
B30: 17 | D30: 2621 | F30: Emelda | G30: 100
B31: Sub-Total | G31: =SUM(G22:G30) -> 1050 | I31: =G31-J31 -> 50 | J31: 1000 | K31: 0 | L31: =J31+K31 -> 1000
B32: 31 | D32: 2622 | F32: Calonge Family | G32: 100
B33: 31 | D33: 2623 | F33: Gina | G33: 100
B34: 31 | D34: No OR | F34: Terrie | G34: 500
B35: 31 | D35: No OR | F35: Abeles | G35: 50 | K35: 0
B36: Sub-Total | G36: =SUM(G32:G35) -> 750 | I36: =G36-J36 -> 650 | J36: 100 | K36: 900 | L36: =J36+K36 -> 1000
B37: TOTAL | G37: =G21+G31+G36 -> 2650 | I37: =I21+I31+I36 -> 700 | J37: =J21+J31+J36 -> 1950 | K37: =K21+K31+K36 -> 1050 | L37: =L21+L31+L36 -> 3000
I38: =G37-J37 -> 700
B46: Stipend for the month of March 2024
B48: Period covered | F48: Amount
B49: March | C49: 03 | F49: 1000
B50: March | C50: 10 | D50: No mass | F50: 0
B51: March | C51: 17 | F51: 1000
B52: March | C52: 31 | F52: 1000
B54: Total Stipend | F54: =SUM(F49:F52) -> 3000

Sheet April_2024_FR
C4: Our Lady of the Most Holy Rosary (Sub-Parish)
C5: Diamond Crest Village ,Brgy, San Manuel, San Jose DelMonte City, Bulacan
C7: FINANCIAL REPORT
C8: As of APRIL 30, 2024
C10: Cash Balance as of April 01, 2024 | K10: P | L10: 10968.25
C12: Add: Receipts for the month of April 2024
C14: Mass Collections: | G14: (Net of Stipend)
H16: Collections | I16: Stipend | J16: Net Amount
E18: April | G18: 07 | H18: 1265 | I18: 150 | J18: =H18-I18 -> 1115
E19: April | G19: 14 | H19: 881 | I19: 300 | J19: =H19-I19 -> 581
E20: April | G20: 21 | H20: 884 | I20: 50 | J20: =H20-I20 -> 834
E21: April | G21: 28 | H21: 795 | I21: 300 | J21: =H21-I21 -> 495
E23: Total | H23: =SUM(H18:H21) -> 3825 | I23: =SUM(I18:I21) -> 800 | J23: =SUM(J18:J21) -> 3025
C27: Donations from Mass Intentions : (see Schedule A)
E29: Donations ( net of Stipend ) | J29: ='April_2024_Sched A'!I45 -> 0 | L29: =J29+J23 -> 3025
C31: Total Cash Available | K31: P | L31: =L10+L29 -> 13993.25
C34: Less: Expenses for the month of April
C36: Date | E36: PCV # | G36: Particulars | J36: Amount
C38: April 14, 2024 | G38: Donations (Abuloy to Leah's sister -Mindanao) | J38: 500
C39: April 16, 2024 | G39: Utility Expenses (Meralco & Water Bills ) | J39: 1112.85 | L39: =J38+J39 -> 1612.85
C41: Net of Expenses | L41: =L31-L39 -> 12380.4
C43: Less: Deposits for the month of April 2024 | L43: 1256.7
C45: Cash Balance as of April 30, 2024 | K45: P | L45: =L41-L43 -> 11123.7
C49: Cash in Bank as of March 31, 2024 | K49: P | L49: 60834.83
C51: Add: Deposits - April 2024 | L51: 1256.7
C52: Interest ( Net of witholding tax ) | L52: =6.42-1.28 -> 5.14
C53: Cash in Bank as of April 30, 2024 | K53: P | L53: =SUM(L49:L52) -> 62096.67
C58: Prepared by: | G58: Checked by: | I58: Audited by: | L58: Noted by:
C60: Elvira Grafil | G60: Fely Rabano | I60: Tina Murla | L60: Lucky Tiu
C61: Asst. Treasurer | G61: Treasurer | I61: Auditor | L61: President

Sheet April_2024_Sched A
B2: Schedule A
B7: Our Lady of the Most Holy Rosary (Sub-Parish)
G8: Control File - Receipts
F9: For the month of April 2024
G11: DONATIONS (Mass Intentions:Thanksgiving, Souls, others) | H11: DONATIONS | I11: Net of Donations | J11: STIPEND from | L11: Total Stipend
B12: Date | D12: OR Number | F12: Donor | J12: Donations | K12: Mass Collections
B13: April
B14: 07 | D14: 2623 | F14: Gina | G14: 100
B15: 07 | D15: 2624 | F15: Imelda | G15: 100
B16: 07 | D16: 2625 | F16: Art de Leon | G16: 200
B17: 07 | D17: 2626 | F17: Hilda | G17: 150
B18: 07 | D18: 2627 | F18: Beng Grafil | G18: 100
B19: 07 | D19: 2628 | F19: Elmer Buere | G19: 100
B20: 07 | D20: 2629 | F20: Baby | G20: 100
B21: Sub-Total | G21: =SUM(G14:G20) -> 850 | I21: =G21-J21 -> 0 | J21: 850 | K21: 150 | L21: =J21+K21 -> 1000
B22: 14 | D22: 2630 | F22: Jane Pasamba | G22: 100
B23: 14 | D23: 2631 | F23: Beng Grafil | G23: 100
B24: 14 | D24: 2632 | F24: Juvy | G24: 100
B25: 14 | D25: 2633 | F25: Abeles | G25: 150
B26: 14 | D26: 2634 | F26: Lea | G26: 50
B27: 14 | D27: 2635 | F27: Irene | G27: 100
B28: 14 | D28: - | F28: No Official Receipt | G28: 100
B29: Sub-Total | G29: =SUM(G22:G28) -> 700 | I29: =G29-J29 -> 0 | J29: 700 | K29: 300 | L29: =J29+K29 -> 1000
B30: 21 | D30: 2636 | F30: Beng Grafil | G30: 100
B31: 21 | D31: 2637 | F31: Gina | G31: 100
B32: 21 | D32: 2638 | F32: Galang Store | G32: 50
B33: 21 | D33: 2639 | F33: Art de Leon & Family | G33: 500
B34: 21 | D34: 2640 | F34: Elmer Buere | G34: 100
B35: 21 | D35: 2641 | F35: Irene | G35: 100
B36: Sub-Total | G36: =SUM(G30:G35) -> 950 | I36: =G36-J36 -> 0 | J36: 950 | K36: 50 | L36: =J36+K36 -> 1000
B37: 28 | D37: 2642 | F37: Fely Rabano | G37: 100
B38: 28 | D38: 2643 | F38: Thelma Lara | G38: 50
B39: 28 | D39: 2644 | F39: Art de Leon & Family | G39: 200
B40: 28 | D40: 2645 | F40: Loira | G40: 100
B41: 28 | D41: 2646 | F41: Jane | G41: 100
B42: 28 | D42: 2647 | F42: Elmer Buere | G42: 100
B43: 28 | D43: 2648 | F43: Susan | G43: 50 | K43: 0
B44: Sub-Total | G44: =SUM(G37:G43) -> 700 | I44: =G44-J44 -> 0 | J44: 700 | K44: 300 | L44: =J44+K44 -> 1000
B45: TOTAL | G45: =G21+G29+G36+G44 -> 3200 | I45: =I21+I36+I44 -> 0 | J45: =J21+J29+J36+J44 -> 3200 | K45: =K21+K29+K36+K44 -> 800 | L45: =L21+L29+L36+L44 -> 4000
B54: Stipend for the month of April 2024
B56: Period covered | F56: Amount
B57: April | C57: 07 | F57: 1000
B58: April | C58: 14 | F58: 1000
B59: April | C59: 21 | F59: 1000
B60: April | C60: 28 | F60: 1000
B62: Total Stipend | F62: =SUM(F57:F60) -> 4000

Sheet May-2024_FR
C4: Our Lady of the Most Holy Rosary (Sub-Parish)
C5: Diamond Crest Village ,Brgy, San Manuel, San Jose DelMonte City, Bulacan
C7: FINANCIAL REPORT
C8: As of MAY 31, 2024
C10: Cash Balance as of May 01, 2024 | L10: P | M10: 11123.7
C12: Add: Receipts for the month of May 2024
C14: Mass Collections: | G14: (Net of Stipend)
H16: Collections | I16: Stipend | J16: Others | K16: Net Amount
E18: May | G18: 05 | H18: 1158 | I18: 200 | J18: 300 | K18: =H18-I18-J18 -> 658
E19: May | G19: 12 | H19: 909 | I19: 0 | J19: 0 | K19: =H19-I19 -> 909
E20: May | G20: 19 | H20: 892 | I20: 500 | J20: 0 | K20: =H20-I20 -> 392
E21: May | G21: 26 | H21: 806 | I21: 400 | J21: 0 | K21: =H21-I21 -> 406
E23: Total | H23: =SUM(H18:H21) -> 3765 | I23: =SUM(I18:I21) -> 1100 | J23: =SUM(J18:J21) -> 300 | K23: =SUM(K18:K21) -> 2365
C27: Donations from Mass Intentions : (see Schedule A)
E29: Donations ( net of Stipend ) | K29: ='May-2024-Sched A'!I49 -> 600 | M29: =K29+K23 -> 2965 | O29: 2915 | P29: =O29-M29 -> -50
C31: Add: Cash withdrawal - May 24, 2024 | M31: 9000
C33: Total Cash Available | L33: P | M33: =M10+M29+M31 -> 23088.7
C38: Less: Expenses for the month of May
C40: Date | E40: PCV # | G40: Particulars | K40: Amount
C42: May 9, 2024 | G42: Dry Clean Expenses ( Mama Mary Gowns) | K42: 400
C43: May 21, 2024 | G43: Utility Expenses (Meralco & Water Bills ) | K43: =976.8+168.8 -> 1145.6
C44: May 21, 2024 | G44: Materials for "Luhuran" | K44: 115
C45: May 24,2024 | G45: Labor/Materials and Repairs Expenses | K45: 3000
C46: May 28, 2024 | G46: Candles | K46: 212.25
C47: May 29, 2024 | G47: Stipend for Novenario (Flores de Maria) | K47: 3000 | M47: =SUM(K42:K47) -> 7872.85
C49: Net of Expenses | M49: =M33-M47 -> 15215.85
C51: Less: Deposits for the month of May 2024 | M51: 9711.55
C53: Cash Balance as of May31, 2024 | L53: P | M53: =M49-M51 -> 5504.3 | O53: =M49-M51 -> 5504.3
C57: Cash in Bank as of April 30, 2024 | L57: P | M57: 62096.67
C59: Add: Deposits - May 21, 2024 | M59: 9711.55
C60: Interest ( Net of witholding tax ) | M60: =6.8-1.36 -> 5.44
C61: Less: Withdrawal - May 24, 2024 | M61: -9000
C62: Cash in Bank as of Mayl 31, 2024 | L62: P | M62: =SUM(M57:M61) -> 62813.66
C67: Prepared by: | G67: Checked by: | I67: Audited by: | M67: Noted by:
C69: Elvira Grafil | G69: Fely Rabano | I69: Tina Murla | M69: Lucky Tiu
C70: Asst. Treasurer | G70: Treasurer | I70: Auditor | M70: President

Sheet May-2024-Sched A
B2: Schedule A
B7: Our Lady of the Most Holy Rosary (Sub-Parish)
G8: Control File - Receipts
F9: For the month of May 2024
G11: DONATIONS (Mass Intentions:Thanksgiving, Souls, others) | H11: DONATIONS | I11: Net of Donations | J11: STIPEND from | L11: Total Stipend
B12: Date | D12: OR Number | F12: Donor | J12: Donations | K12: Mass Collections
B13: May
B14: 05 | D14: 2649 | F14: Lucy | G14: 50
B15: 05 | D15: 2650 | F15: Ebony | G15: 100
B16: 05 | D16: 2651 | F16: Art de Leon & Family | G16: 100
B17: 05 | D17: 2652 | F17: Calonge Family | G17: 100
B18: 05 | D18: 2653 | F18: Eloisa | G18: 100
B19: 05 | D19: 2654 | F19: Beng Grafil | G19: 100
B20: 05 | D20: 2655 | F20: Helen | G20: 100
B21: 05 | D21: 2656 | F21: Helen | G21: 100
B22: 05 | D22: 2657 | F22: Elmer Buere | G22: 100
B23: Sub-Total | G23: =SUM(G14:G22) -> 850 | I23: =G23-J23 -> 50 | J23: 800 | K23: 200 | L23: =J23+K23 -> 1000
B24: 12 | D24: 2658 | F24: Tina Murla | G24: 500
B25: 12 | D25: 2659 | F25: Galang Family | G25: 50
B26: 12 | D26: 2660 | F26: Beng Grafil | G26: 150
B27: 12 | D27: 2661 | F27: Jane Pasamba | G27: 100
B28: 12 | D28: 2662 | F28: Lucy Sararosing Family | G28: 100
B29: 12 | D29: 2663 | F29: Gina | G29: 100
B30: 12 | D30: 2664 | F30: Ebony | G30: 100
B31: 12 | D31: 2665 | F31: Banog Family | G31: 100
B32: 12 | D32: 2666 | F32: Elmer Buere | G32: 100
B33: 12 | D33: 2667 | F33: Irene Masong | G33: 100
B34: 12 | D34: 2668 | F34: Aveles Family | G34: 150
B35: Sub-Total | G35: =SUM(G24:G34) -> 1550 | I35: =G35-J35 -> 550 | J35: 1000 | K35: 0 | L35: =J35+K35 -> 1000
B36: 19 | D36: 2669 | F36: Art de Leon | G36: 100
B37: 19 | D37: 2670 | F37: Beng Grafil | G37: 100
B38: 19 | D38: 2671 | F38: Eloisa | G38: 100
B39: 19 | D39: 2672 | F39: Susan | G39: 100
B40: 19 | D40: 2673 | F40: Rose | G40: 100
B41: Sub-Total | G41: =SUM(G36:G40) -> 500 | I41: =G41-J41 -> 0 | J41: 500 | K41: 500 | L41: =J41+K41 -> 1000
B42: 26 | D42: 2674 | F42: Calonge Family | G42: 100
B43: 26 | D43: 2675 | F43: Jane Pasamba | G43: 100
B44: 26 | D44: 2676 | F44: Susan | G44: 100
B45: 26 | D45: 2677 | F45: Elmer Buere | G45: 100
B46: 26 | D46: 2678 | F46: Hilda | G46: 100
B47: 26 | D47: 2679 | F47: Jun Cales | G47: 100
B48: Sub-Total | G48: =SUM(G42:G47) -> 600 | I48: =G48-J48 -> 0 | J48: 600 | K48: 400 | L48: =J48+K48 -> 1000
B49: TOTAL | G49: =G23+G35+G41+G48 -> 3500 | I49: =I23+I41+I35+I48 -> 600 | J49: =J23+J35+J41+J48 -> 2900 | K49: =K23+K35+K41+K48 -> 1100 | L49: =L23+L35+L41+L48 -> 4000
B58: Stipend for the month of May 2024
B60: Period covered | F60: Amount
B61: May | C61: 05 | F61: 1000
B62: May | C62: 12 | F62: 1000
B63: May | C63: 19 | F63: 1000
B64: May | C64: 26 | F64: 1000
B66: Total Stipend | F66: =SUM(F61:F64) -> 4000

Sheet June-2024-FR
C4: Our Lady of the Most Holy Rosary (Sub-Parish)
C5: Diamond Crest Village ,Brgy, San Manuel, San Jose DelMonte City, Bulacan
C7: FINANCIAL REPORT
C8: As of JUNE 30, 2024
C10: Cash Balance as of June 01, 2024 | L10: P | M10: 5504.3
C12: Add: Receipts for the month of June 2024
C14: Mass Collections: | G14: (Net of Stipend)
H16: Collections | I16: Stipend | J16: Others | K16: Net Amount
E18: June | G18: 09 | H18: 3258 | I18: 0 | J18: 0 | K18: =H18-I18-J18 -> 3258
E19: June | G19: 16 | H19: 903 | I19: 150 | J19: 0 | K19: =H19-I19 -> 753
E20: June | G20: 23 | H20: 1125 | I20: 300 | J20: 0 | K20: =H20-I20 -> 825
E21: June | G21: 30 | H21: 1024 | I21: 0 | J21: 0 | K21: =H21-I21 -> 1024
E23: Total | H23: =SUM(H18:H21) -> 6310 | I23: =SUM(I18:I21) -> 450 | J23: =SUM(J18:J21) -> 0 | K23: =SUM(K18:K21) -> 5860
C27: Donations from Mass Intentions : (see Schedule A)
E29: Donations ( net of Stipend ) | K29: ='June-2024-SchedA'!I50 -> 120 | M29: =K29+K23 -> 5980 | O29: 5960 | P29: =M29-O29 -> 20
C31: Add: Cash withdrawal | M31: 0
C33: Total Cash Available | L33: P | M33: =M10+M29+M31 -> 11484.3
C38: Less: Expenses for the month of June 2024
C40: Date | E40: PCV # | G40: Particulars | K40: Amount
C42: June 01, 2024 | G42: Tarpaulin ( Signage for No Mass ) | K42: 150
C43: June 16, 2024 | G43: Father's Day gift ( for Father Von ) | K43: 1000
C44: June 18, 2024 | G44: Utility Expenses ( Water Bills share for 2 months ) | K44: =300+300 -> 600
C45: June 20, 2024 | G45: Battery for Laptop used at Chapel | K45: 239
C46: June 29, 2024 | G46: Candles | K46: 210.15
C47: June 30, 2024 | G47: Flowers at SLR Parish for the month of June 2024 | K47: 700 | M47: =SUM(K42:K47) -> 2899.15
C49: Net of Expenses | M49: =M33-M47 -> 8585.15
C51: Less: Deposits for the month of June 2024 | M51: 1412.15
C53: Cash Balance as of June 30, 2024 | L53: P | M53: =M49-M51 -> 7173 | O53: =M49-M51 -> 7173
C57: Cash in Bank as of May 31, 2024 | L57: P | M57: 62813.66
C59: Add: Deposits - June 18, 2024 | M59: 1412.15
C60: Interest ( Net of witholding tax ) | M60: =6.61-1.32 -> 5.29
C61: Less: Withdrawal | M61: 0
C62: Cash in Bank as of June 30, 2024 | L62: P | M62: =SUM(M57:M61) -> 64231.1
C67: Prepared by: | G67: Checked by: | I67: Audited by: | M67: Noted by:
C69: Elvira Grafil | G69: Fely Rabano | I69: Tina Murla | M69: Lucky Tiu
C70: Asst. Treasurer | G70: Treasurer | I70: Auditor | M70: President

Sheet June-2024-SchedA
B2: Schedule A
B7: Our Lady of the Most Holy Rosary (Sub-Parish)
G8: Control File - Receipts
F9: For the month of June 2024
G11: DONATIONS (Mass Intentions:Thanksgiving, Souls, others) | H11: DONATIONS | I11: Net of Donations | J11: STIPEND from | L11: Total Stipend
B12: Date | D12: OR Number | F12: Donor | J12: Donations | K12: Mass Collections
B13: June
B14: 09 | D14: 2680 | F14: Neri | G14: 100
B15: 09 | D15: 2681 | F15: Gina | G15: 100
B16: 09 | D16: 2682 | F16: Elmer Buere | G16: 100
B17: 09 | D17: 2683 | F17: Beng Grafil | G17: 100
B18: 09 | D18: 2684 | F18: Eloisa | G18: 100
B19: 09 | D19: 2685 | F19: Art De Leon | G19: 200
B20: 09 | D20: 2686 | F20: Jane Pasamba | G20: 100
B21: 09 | D21: 2687 | F21: Sola | G21: 100
B22: 09 | D22: 2688 | F22: Annie | G22: 20
B23: 09 | D23: 2689 | F23: Helen | G23: 150
B24: 09 | D24: 2690 | F24: Hilda | G24: 50
B25: Sub-Total | G25: =SUM(G14:G24) -> 1120 | I25: =G25-J25 -> 120 | J25: 1000 | K25: 0 | L25: =J25+K25 -> 1000
B26: 16 | D26: 2691 | F26: Fely Rabano | G26: 100
B27: 16 | D27: 2692 | F27: Gina | G27: 100
B28: 16 | D28: 2693 | F28: Art De Leon | G28: 200
B29: 16 | D29: 2694 | F29: Lucy Sararosing Family | G29: 100
B30: 16 | D30: 2695 | F30: Eloisa | G30: 100
B31: 16 | D31: 2696 | F31: Irene | G31: 100
B32: 16 | D32: 2697 | F32: Susan | G32: 50
B33: 16 | D33: 2698 | F33: Juvy | G33: 100
B34: Sub-Total | G34: =SUM(G26:G33) -> 850 | I34: =G34-J34 -> 0 | J34: 850 | K34: 150 | L34: =J34+K34 -> 1000
B35: 23 | D35: 2699 | F35: Art De Leon | G35: 200
B36: 23 | D36: 2700 | F36: Jane Pasamba | G36: 100
B37: 23 | D37: 2701 | F37: Helen | G37: 100
B38: 23 | D38: 2702 | F38: Eloisa | G38: 100
B39: 23 | D39: - | F39: No Official Receipt | G39: 200
B40: Sub-Total | G40: =SUM(G35:G39) -> 700 | I40: =G40-J40 -> 0 | J40: 700 | K40: 300 | L40: =J40+K40 -> 1000
B41: 30 | D41: 2703 | F41: Lucia Gacomo | G41: 100
B42: 30 | D42: 2704 | F42: Beng Grafil | G42: 100
B43: 30 | D43: 2705 | F43: Reylyn Calonge | G43: 100
B44: 30 | D44: 2706 | F44: Elmer Buere | G44: 100
B45: 30 | D45: 2707 | F45: Banog Family | G45: 100
B46: 30 | D46: 2708 | F46: Unused OR(see July 7) | G46: 0
B47: 30 | D47: 2709 | F47: Art De Leon | G47: 200
B48: 30 | D48: 2710 | F48: Tess Sabado | G48: 300
B49: Sub-Total | G49: =SUM(G41:G48) -> 1000 | I49: =G49-J49 -> 0 | J49: 1000 | K49: 0 | L49: =J49+K49 -> 1000
B50: TOTAL | G50: =G25+G34+G40+G49 -> 3670 | I50: =I25+I40+I34+I49 -> 120 | J50: =J25+J34+J40+J49 -> 3550 | K50: =K25+K34+K40+K49 -> 450 | L50: =L25+L34+L40+L49 -> 4000
B59: Stipend for the month of June 2024
B61: Period covered | F61: Amount
B62: June | C62: 09 | F62: 1000
B63: June | C63: 16 | F63: 1000
B64: June | C64: 23 | F64: 1000
B65: June | C65: 30 | F65: 1000
B67: Total Stipend | F67: =SUM(F62:F65) -> 4000

Sheet July-2024-FR
C4: Our Lady of the Most Holy Rosary (Sub-Parish)
C5: Diamond Crest Village ,Brgy, San Manuel, San Jose DelMonte City, Bulacan
C7: FINANCIAL REPORT
C8: As of JULY 31, 2024
C10: Cash Balance as of July 01, 2024 | L10: P | M10: 7173
C12: Add: Receipts for the month of July 2024
C14: Mass Collections: | G14: (Net of Stipend)
H16: Collections | I16: Stipend | J16: Others | K16: Net Amount
E18: July | G18: 07 | H18: 1495 | I18: 700 | J18: 0 | K18: =H18-I18-J18 -> 795
E19: July | G19: 14 | H19: 1130 | I19: 100 | J19: 0 | K19: =H19-I19 -> 1030
E20: July | G20: 21 | H20: 1385 | I20: 400 | J20: 0 | K20: =H20-I20 -> 985
E21: July | G21: 28 | H21: 1004 | I21: 150 | J21: 0 | K21: =H21-I21 -> 854
E23: Total | H23: =SUM(H18:H21) -> 5014 | I23: =SUM(I18:I21) -> 1350 | J23: =SUM(J18:J21) -> 0 | K23: =SUM(K18:K21) -> 3664
C27: Donations from Mass Intentions : (see Schedule A)
E29: Donations ( net of Stipend ) | K29: ='July-2024-Sched A'!I42 -> 0 | M29: =K29+K23 -> 3664
C31: Add: Cash withdrawal | M31: 0
C33: Total Cash Available | L33: P | M33: =M10+M29+M31 -> 10837
C38: Less: Expenses for the month of July 2024
C40: Date | E40: PCV # | G40: Particulars | K40: Amount
C42: July 17, 2024 | G42: Utility Expenses ( Meralco Bill - May 21-June 20 ) | K42: 783.38
C43: July 27, 2024 | G43: Labor/Materials and Repairs Expenses ( repair of ceiling ) | K43: 635 | M43: =K42+K43 -> 1418.38
C44: June 18, 2024 | G44: Utility Expenses ( Water Bills share for 2 months ) | K44: 0
C45: June 20, 2024 | G45: Battery for Laptop used at Chapel | K45: 0
C46: June 29, 2024 | G46: Candles | K46: 0
C47: June 30, 2024 | G47: Flowers at SLR Parish for the month of June 2024 | K47: 0 | M47: =SUM(K42:K47) -> 1418.38
C49: Net of Expenses | M49: =M33-M43 -> 9418.62
C51: Less: Deposits for the month of July 2024 | M51: =1193+2899.15 -> 4092.15
C53: Cash Balance as of July 31, 2024 | L53: P | M53: =M49-M51 -> 5326.47
C57: Cash in Bank as of June 30, 2024 | L57: P | M57: 64231.1
C59: Add: Deposits - July 17, 2024 | M59: 1193
C60: Deposits - July 22, 2024 | M60: 2899.15
C61: Interest ( Net of witholding tax ) | M61: =7.08-1.42 -> 5.66
C62: Less: Withdrawal | M62: 0
C63: Cash in Bank as of July 31, 2024 | L63: P | M63: =SUM(M57:M62) -> 68328.91
C68: Prepared by: | G68: Checked by: | I68: Audited by: | M68: Noted by:
C70: Elvira Grafil | G70: Fely Rabano | I70: Tina Murla | M70: Lucky Tiu
C71: Asst. Treasurer | G71: Treasurer | I71: Auditor | M71: President

Sheet July-2024-Sched A
B2: Schedule A
B7: Our Lady of the Most Holy Rosary (Sub-Parish)
G8: Control File - Receipts
F9: For the month of July 2024
G11: DONATIONS (Mass Intentions:Thanksgiving, Souls, others) | H11: DONATIONS | I11: Net of Donations | J11: STIPEND from | L11: Total Stipend
B12: Date | D12: OR Number | F12: Donor | J12: Donations | K12: Mass Collections
B13: July
B14: 07 | D14: 2708 | F14: Jane Pasamba | G14: 100
B15: 07 | D15: 2711 | F15: Elmer Buere | G15: 100
B16: 07 | D16: =1+D15 -> 2712 | F16: Maricel | G16: 100
B17: Sub-Total | G17: =SUM(G14:G16) -> 300 | I17: =G17-J17 -> 0 | J17: 300 | K17: 700 | L17: =J17+K17 -> 1000
B18: 14 | D18: 2713 | F18: Josefina Avila | G18: 100
B19: 14 | D19: =1+D18 -> 2714 | F19: Elmer Buere | G19: 100
B20: 14 | D20: =1+D19 -> 2715 | F20: Thelma | G20: 100
B21: 14 | D21: =1+D20 -> 2716 | F21: Thin Tapaoan | G21: 100
B22: 14 | D22: =1+D21 -> 2717 | F22: Eloisa | G22: 100
B23: 14 | D23: =1+D22 -> 2718 | F23: Beng Grafil | G23: 100
B24: 14 | D24: =1+D23 -> 2719 | F24: Baby Boris | G24: 200
B25: 14 | D25: =1+D24 -> 2720 | F25: Irene | G25: 100
B26: Sub-Total | G26: =SUM(G18:G25) -> 900 | I26: =G26-J26 -> 0 | J26: 900 | K26: 100 | L26: =J26+K26 -> 1000
B27: 21 | D27: 2721 | F27: Hilda | G27: 200
B28: 21 | D28: =1+D27 -> 2722 | F28: Elmer Buere | G28: 100
B29: 21 | D29: =1+D28 -> 2723 | F29: Jane Pasamba | G29: 100
B30: 21 | D30: =1+D29 -> 2724 | F30: Thin Tapaoan | G30: 100
B31: 21 | D31: =1+D30 -> 2725 | F31: Eloisa | G31: 100
B32: Sub-Total | G32: =SUM(G27:G31) -> 600 | I32: =G32-J32 -> 0 | J32: 600 | K32: 400 | L32: =J32+K32 -> 1000
B33: 28 | D33: 2726 | F33: Beng Grafil | G33: 100
B34: 28 | D34: =1+D33 -> 2727 | F34: Lucy S, & Atienza family | G34: 150
B35: 28 | D35: =1+D34 -> 2728 | F35: Billy Lara | G35: 100
B36: 28 | D36: =1+D35 -> 2729 | F36: Thin Tapaoan | G36: 100
B37: 28 | D37: =1+D36 -> 2730 | F37: Lucia Gacuma | G37: 100
B38: 28 | D38: =1+D37 -> 2731 | F38: Banog family | G38: 100
B39: 28 | D39: =1+D38 -> 2732 | F39: Baby Boris | G39: 100
B40: 28 | D40: =1+D39 -> 2733 | F40: Elmer Buere & family | G40: 100
B41: Sub-Total | G41: =SUM(G33:G40) -> 850 | I41: =G41-J41 -> 0 | J41: 850 | K41: 150 | L41: =J41+K41 -> 1000
B42: TOTAL | G42: =G17+G26+G32+G41 -> 2650 | I42: =I17+I32+I26+I41 -> 0 | J42: =J17+J26+J32+J41 -> 2650 | K42: =K17+K26+K32+K41 -> 1350 | L42: =L17+L26+L32+L41 -> 4000
B51: Stipend for the month of July 2024
B53: Period covered | F53: Amount
B54: July | C54: 07 | F54: 1000
B55: July | C55: 14 | F55: 1000
B56: July | C56: 21 | F56: 1000
B57: July | C57: 28 | F57: 1000
B59: Total Stipend | F59: =SUM(F54:F57) -> 4000

Sheet Aug-2024-FR
C4: Our Lady of the Most Holy Rosary (Sub-Parish)
C5: Diamond Crest Village ,Brgy, San Manuel, San Jose DelMonte City, Bulacan
C7: FINANCIAL REPORT
C8: As of AUGUST 31, 2024
C10: Cash Balance as of August 01, 2024 | L10: P | M10: 5326.47
C12: Add: Receipts for the month of August 2024
C14: Mass Collections: | G14: (Net of Stipend)
H16: Collections | I16: Stipend | J16: Others | K16: Net Amount
E18: August | G18: 04 | H18: 950 | I18: 500 | J18: 0 | K18: =H18-I18-J18 -> 450
E19: August | G19: 11 | H19: 1276 | I19: 800 | J19: 0 | K19: =H19-I19 -> 476
E20: August | G20: 18 | H20: 2122 | I20: 250 | J20: 0 | K20: =H20-I20 -> 1872
E21: August | G21: 25 | H21: 1182 | I21: 450 | J21: 0 | K21: =H21-I21 -> 732
E23: Total | H23: =SUM(H18:H21) -> 5530 | I23: =SUM(I18:I21) -> 2000 | J23: =SUM(J18:J21) -> 0 | K23: =SUM(K18:K21) -> 3530
C27: Donations from Mass Intentions : (see Schedule A)
E29: Donations ( net of Stipend ) | K29: ='[1]July-2024-Sched A'!I42 -> 0 | M29: =K29+K23 -> 3530
C31: Add: Cash withdrawal | M31: 0
C33: Total Cash Available | L33: P | M33: =M10+M29+M31 -> 8856.47
C38: Less: Expenses for the month of August 2024
C40: Date | E40: PCV # | G40: Particulars | K40: Amount
C42: August 4 | G42: Parol ( partial payment ) | K42: 1000
C43: August 8 | G43: Utility Expenses ( Meralco Bill - June 21 to July 20 ) | K43: 800
C44: August 9 | G44: Laundry Expenses ( Dry Clean - Santo clothes ) | K44: 200
C45: August 10 | G45: Labor expenses ( Sub-meter removal ) | K45: 500
C46: August 11 | G46: Labor expenses ( Fabrication of metal cabinet ) | K46: 500
C47: August 23 | G47: Food expenses ( Food share for Father Von's anniversary ) | K47: 1250
C48: August 25 | G48: Donation ( Abuloy to former SPPC Choir) | K48: 1500 | M48: =SUM(K42:K48) -> 5750
C49: June 18, 2024 | G49: Utility Expenses ( Water Bills share for 2 months ) | K49: 0
C50: June 20, 2024 | G50: Battery for Laptop used at Chapel | K50: 0
C51: June 29, 2024 | G51: Candles | K51: 0
C52: June 30, 2024 | G52: Flowers at SLR Parish for the month of June 2024 | K52: 0 | M52: =SUM(K42:K52) -> 5750
C54: Net of Expenses | M54: =M33-M48 -> 3106.47
C56: Less: Deposits for the month of August 2024 | M56: 3080.85
C58: Cash Balance as of August 31, 2024 | L58: P | M58: =M54-M56 -> 25.62
C62: Cash in Bank as of July 31, 2024 | L62: P | M62: 68328.91
C64: Add: Deposits - August 28, 2024 | M64: 3080.85
C65: Interest ( Net of witholding tax ) | M65: =7.39-1.48 -> 5.91
C66: Less: Withdrawal | M66: 0
C67: Cash in Bank as of August 31, 2024 | L67: P | M67: =SUM(M62:M66) -> 71415.67
C72: Prepared by: | G72: Checked by: | I72: Audited by: | M72: Noted by:
C74: Elvira Grafil | G74: Fely Rabano | I74: Tina Murla | M74: Lucky Tiu
C75: Asst. Treasurer | G75: Treasurer | I75: Auditor | M75: President

Sheet Aug-2024-Sched A
B2: Schedule A
B7: Our Lady of the Most Holy Rosary (Sub-Parish)
G8: Control File - Receipts
F9: For the month of August 2024
G11: DONATIONS (Mass Intentions:Thanksgiving, Souls, others) | H11: DONATIONS | I11: Net of Donations | J11: STIPEND from | L11: Total Stipend
B12: Date | D12: OR Number | F12: Donor | J12: Donations | K12: Mass Collections
B13: August
B14: 04 | D14: 2734 | F14: Jane Pasamba | G14: 100
B15: 04 | D15: 2735 | F15: Elmer Buere | G15: 100
B16: 04 | D16: 2736 | F16: Beng Grafil | G16: 100
B17: 04 | D17: 2737 | F17: Eloisa | G17: 100
B18: 04 | D18: 2738 | F18: Relyne Calonge | G18: 100
B19: Sub-Total | G19: =SUM(G14:G18) -> 500 | I19: 0 | J19: 500 | K19: 500 | L19: =J19+K19 -> 1000
B20: 11 | D20: 2739 | F20: Meldie | G20: 100
B21: 11 | D21: =1+D20 -> 2740 | F21: Eloisa | G21: 100
B22: Sub-Total | G22: =SUM(G20:G21) -> 200 | I22: =G22-J22 -> 0 | J22: 200 | K22: 800 | L22: =J22+K22 -> 1000
B23: 18 | D23: 2741 | F23: Gina | G23: 100
B24: 18 | D24: =1+D23 -> 2742 | F24: Jane Pasamba | G24: 200
B25: 18 | D25: =1+D24 -> 2743 | F25: Susan | G25: 50
B26: 18 | D26: =1+D25 -> 2744 | F26: Elmer Buere | G26: 100
B27: 18 | D27: =1+D26 -> 2745 | F27: Rani | G27: 200
B28: 18 | D28: =1+D27 -> 2746 | F28: Eloisa | G28: 100
B29: Sub-Total | G29: =SUM(G23:G28) -> 750 | I29: =G29-J29 -> 0 | J29: 750 | K29: 250 | L29: =J29+K29 -> 1000
B30: 25 | D30: 2747 | F30: Mrs. Salas | G30: 100
B31: 25 | D31: =1+D30 -> 2748 | F31: Elmer Buere | G31: 100
B32: 25 | D32: =1+D31 -> 2749 | F32: Susan | G32: 50
B33: 25 | D33: =1+D32 -> 2750 | F33: Beng Grafil | G33: 100
B34: 25 | D34: =1+D33 -> 2751 | F34: Eloisa | G34: 100
B35: 28 | D35: =1+D34 -> 2752 | F35: Baby Boris | G35: 100
B36: Sub-Total | G36: =SUM(G30:G35) -> 550 | I36: =G36-J36 -> 0 | J36: 550 | K36: 450 | L36: =J36+K36 -> 1000
B37: TOTAL | G37: =G19+G22+G29+G36 -> 2000 | I37: =I19+I29+I22+I36 -> 0 | J37: =J19+J22+J29+J36 -> 2000 | K37: =K19+K22+K29+K36 -> 2000 | L37: =L19+L22+L29+L36 -> 4000
B46: Stipend for the month of August 2024
B48: Period covered | F48: Amount
B49: August | C49: 04 | F49: 1000
B50: August | C50: 11 | F50: 1000
B51: August | C51: 18 | F51: 1000
B52: August | C52: 25 | F52: 1000
B54: Total Stipend | F54: =SUM(F49:F52) -> 4000

Sheet Sept-2024-FR
C4: Our Lady of the Most Holy Rosary (Sub-Parish)
C5: Diamond Crest Village ,Brgy, San Manuel, San Jose DelMonte City, Bulacan
C7: FINANCIAL REPORT
C8: As of September 30, 2024
C10: Cash Balance as of September 01, 2024 | L10: P | M10: 25.62
C12: Add: Receipts for the month of September 2024
C14: Mass Collections: | G14: (Net of Stipend)
H16: Collections | I16: Stipend | J16: Others | K16: Net Amount
E18: September | G18: 01 | H18: 1881 | I18: 700 | J18: 0 | K18: =H18-I18-J18 -> 1181
E19: September | G19: 08 | H19: 2214 | I19: 450 | J19: 0 | K19: =H19-I19 -> 1764
E20: September | G20: 15 | H20: 1200 | I20: 600 | J20: 0 | K20: =H20-I20 -> 600
E21: September | G21: 22 | H21: 1210 | I21: 0 | J21: 0 | K21: =H21-I21 -> 1210
E23: Total | H23: =SUM(H18:H21) -> 6505 | I23: =SUM(I18:I21) -> 1750 | J23: =SUM(J18:J21) -> 0 | K23: =SUM(K18:K21) -> 4755 | O23: =H23-I23 -> 4755
C27: Donations from Mass Intentions : (see Schedule A)
E29: Donations ( net of Stipend ) | K29: ='Sept-2024-Sched A'!I41 -> 950 | M29: =K29+K23 -> 5705
C31: Add: Cash withdrawal | M31: 0
C33: Total Cash Available | L33: P | M33: =M10+M29+M31 -> 5730.62
C38: Less: Expenses for the month of September 2024
C40: Date | E40: PCV # | G40: Particulars | K40: Amount
C42: September 7 | G42: Battery for wireless microphones | K42: 119
C43: September 13 | G43: Cleaning materials ( brooms and walis ting-ting) | K43: 170
C44: September 14 | G44: Tarpaulin for Fiesta at SLRP | K44: 500
C45: September 17 | G45: Electricity Expenses ( Meralco Bill - July21 to August 20 ) | K45: 668.6
C46: September 17 | G46: Water Expenses ( Billing period - July 12-August 11 ) | K46: 632.85
C47: September 20 | G47: Transporation Expenses ( Convention Center re: Gabi ng Parokya) | K47: 1000
C48: September 22 | G48: Expenses for the Cleaning of Chapel's lectric fans | K48: 500
C49: September 24 | G49: Purchase of chlorine used outside the chapel | K49: 200
C50: September 24 | G50: Mass Stipend ( Novena mass - SPPC sponsor ) | K50: 2500
C51: September 20 | G51: Food share for the guest Priest ( Novena mass ) | K51: 900 | M51: =SUM(K42:K51) -> 7190.45
C52: June 18, 2024 | G52: Utility Expenses ( Water Bills share for 2 months ) | K52: 0
C53: June 20, 2024 | G53: Battery for Laptop used at Chapel | K53: 0
C54: June 29, 2024 | G54: Candles | K54: 0
C55: June 30, 2024 | G55: Flowers at SLR Parish for the month of June 2024 | K55: 0 | M55: =SUM(K46:K55) -> 5732.85
C57: Net of Expenses | M57: =M33-M51 -> -1459.83
C59: Less: Deposits for the month of September 2024 | M59: 0
C61: Cash Balance as of September 30, 2024 | L61: P | M61: =M57-M59 -> -1459.83
C65: Cash in Bank as of August 31, 2024 | L65: P | M65: 71415.67
C67: Add: Deposits - | M67: 0
C68: Interest ( Net of witholding tax ) | M68: =7.44-1.49 -> 5.95
C69: Less: Withdrawal | M69: 0
C70: Cash in Bank as of September 30, 2024 | L70: P | M70: =SUM(M65:M69) -> 71421.62
C75: Prepared by: | G75: Checked by: | I75: Audited by: | M75: Noted by:
C77: Elvira Grafil | G77: Fely Rabano | I77: Tina Murla | M77: Lucky Tiu
C78: Asst. Treasurer | G78: Treasurer | I78: Auditor | M78: President

Sheet Sept-2024-Sched A
B2: Schedule A
B7: Our Lady of the Most Holy Rosary (Sub-Parish)
G8: Control File - Receipts
F9: For the month of September 2024
G11: DONATIONS (Mass Intentions:Thanksgiving, Souls, others) | H11: DONATIONS | I11: Net of Donations | J11: STIPEND from | L11: Total Stipend
B12: Date | D12: OR Number | F12: Donor | J12: Donations | K12: Mass Collections
B13: September
B14: 01 | D14: 2753 | F14: Jane Pasamba | G14: 100
B15: 01 | D15: =1+D14 -> 2754 | F15: Elmer Buere | G15: 100
B16: 01 | D16: =1+D15 -> 2755 | F16: Eloisa | G16: 100
B17: Sub-Total | G17: =SUM(G14:G16) -> 300 | I17: =G17-J17 -> 0 | J17: 300 | K17: 700 | L17: =J17+K17 -> 1000
B18: 08 | D18: 2756 | F18: Lucy Saramosing | G18: 150
B19: 08 | D19: =1+D18 -> 2757 | F19: Elmer Buere | G19: 100
B20: 08 | D20: =1+D19 -> 2758 | F20: Gina | G20: 100
B21: 08 | D21: =1+D20 -> 2759 | F21: Eloisa | G21: 100
B22: 08 | D22: =1+D21 -> 2760 | F22: Meldie Torres | G22: 100
B23: 08 | D23: =1+D22 -> 2761 | F23: Regine Estrada | G23: 100
B24: Sub-Total | G24: =SUM(G18:G23) -> 650 | I24: =G24-J24 -> 100 | J24: 550 | K24: 450 | L24: =J24+K24 -> 1000
B25: 15 | D25: 2762 | F25: cancelled | G25: 0
B26: 15 | D26: =1+D25 -> 2763 | F26: Lucy Saramosing | G26: 100
B27: 15 | D27: =1+D26 -> 2764 | F27: Jane Pasamba | G27: 100
B28: 15 | D28: =1+D27 -> 2765 | F28: Eloisa | G28: 100
B29: Sub-Total | G29: =SUM(G25:G28) -> 300 | I29: =G29-J29 -> -100 | J29: 400 | K29: 600 | L29: =J29+K29 -> 1000
B30: 22 | D30: 2766 | F30: Regide Meneses | G30: 100
B31: 22 | D31: =1+D30 -> 2767 | F31: Nida Angels | G31: 100
B32: 22 | D32: =1+D31 -> 2768 | F32: Gina Albarido | G32: 200
B33: 22 | D33: =1+D32 -> 2769 | F33: Annie Alejandia | G33: 50
B34: 22 | D34: =1+D33 -> 2770 | F34: Lucy Saramosing | G34: 100
B35: 22 | D35: =1+D34 -> 2771 | F35: Meldy Torres | G35: 100
B36: 22 | D36: =1+D35 -> 2772 | F36: Irene Masong | G36: 100
B37: 22 | D37: =1+D36 -> 2773 | F37: Elmer Buere | G37: 100
B38: 22 | D38: =1+D37 -> 2774 | F38: Susan Chua Uy | G38: 100
B39: 22 | D39: =1+D38 -> 2775 | F39: Helen C. & J. Pasamba | G39: =500+500 -> 1000
B40: Sub-Total | G40: =SUM(G30:G39) -> 1950 | I40: =G40-J40 -> 950 | J40: 1000 | K40: 0 | L40: =J40+K40 -> 1000
B41: TOTAL | G41: =G17+G24+G29+G40 -> 3200 | I41: =I17+I29+I24+I40 -> 950 | J41: =J17+J24+J29+J40 -> 2250 | K41: =K17+K24+K29+K40 -> 1750 | L41: =L17+L24+L29+L40 -> 4000
B50: Stipend for the month of September 2024
B52: Period covered | F52: Amount
B53: September | C53: 01 | F53: 1000
B54: September | C54: 08 | F54: 1000
B55: September | C55: 15 | F55: 1000
B56: September | C56: 22 | F56: 1000
B58: Total Stipend | F58: =SUM(F53:F56) -> 4000

Sheet Oct-2024-FR
C4: Our Lady of the Most Holy Rosary (Sub-Parish)
C5: Diamond Crest Village ,Brgy, San Manuel, San Jose DelMonte City, Bulacan
C7: FINANCIAL REPORT
C8: As of October 31, 2024
C10: Cash Balance as of October 01, 2024 | L10: P | M10: -1459.83
C12: Add: Receipts for the month of October 2024
C14: Mass Collections: | G14: (Net of Stipend)
H16: Collections | I16: Stipend | J16: Others | K16: Net Amount
E18: October | G18: 06 | H18: 1400 | I18: 300 | J18: 0 | K18: =H18-I18-J18 -> 1100
E19: October | G19: 13 | H19: 1331 | I19: 600 | J19: 0 | K19: =H19-I19 -> 731
E20: October | G20: 17 | H20: 310 | I20: 0 | J20: 0 | K20: =H20-I20 -> 310
E21: October | G21: 18 | H21: 584 | I21: 0 | J21: 0 | K21: =H21-I21 -> 584
E22: October | G22: 19 | H22: 680 | I22: 0 | J22: 0 | K22: =H22-I22 -> 680
E23: October | G23: 20 | H23: 3382 | I23: 0 | J23: 0 | K23: =H23-I23 -> 3382
E24: October | G24: 27 | H24: 0 | I24: 0 | J24: 0 | K24: =H24-I24 -> 0 | P24: No mass
E26: Total | H26: =SUM(H18:H24) -> 7687 | I26: =SUM(I18:I24) -> 900 | J26: =SUM(J18:J24) -> 0 | K26: =SUM(K18:K24) -> 6787 | P26: =H26-I26 -> 6787
C30: Donations from Mass Intentions /Fiesta Collections/Pledges: (see Schedule A)
E32: Donations ( net of Stipend ) including Collections/donations from Fiesta Pledges | K32: ='Oct-2024-Sched A'!I55 -> 39750 | M32: =K32+K26 -> 46537
C34: Add: Cash withdrawal
E35: 39356 | K35: 20000
E36: 43009 | K36: 10000 | M36: =SUM(K35:K36) -> 30000
C38: Total Cash Available | L38: P | M38: =M32+M36+M10 -> 75077.17
C43: Less: Expenses for the month of October 2024
C45: Date | E45: PCV # | G45: Particulars | K45: Amount
C47: October 6 | G47: Banderitas | K47: 500
C48: October 6 | G48: Flowers Share at SLR Parish | K48: 1000 | P48: =K48+SUM(K50:K54) -> 5888.3 | Q48: 5288.3 | R48: =P48-Q48 -> 600
C49: October 7 | G49: Repair of ceiling (kitchen) | K49: 8900
C50: October 9 | G50: Dry Clean ( Santo Clothes ) | K50: 400
C51: October 10 | G51: Labor expenses ( for Banderitas ) | K51: 550
C52: October 11 | G52: Gift and Food Share ( Father Von's birthday ) | K52: 3000
C53: October 22 | G53: Electricity Expenses ( Meralco Bill - August 211 to September 20 ) | K53: 638.3
C54: October 22 | G54: Water Expenses ( Billing period - August 12-September 11 ) | K54: 300 | P54: =SUM(K47:K54) -> 15288.3 | Q54: 5288.3 | R54: =Q54-P54 -> -10000
C55: October 31 | G55: Fiesta Expenses (attached sched ) | K55: 47093.4 | M55: =SUM(K47:K55) -> 62381.7
C56: June 18, 2024 | G56: Utility Expenses ( Water Bills share for 2 months ) | K56: 0
C57: June 20, 2024 | G57: Battery for Laptop used at Chapel | K57: 0
C58: June 29, 2024 | G58: Candles | K58: 0
C59: June 30, 2024 | G59: Flowers at SLR Parish for the month of June 2024 | K59: 0 | M59: =SUM(K53:K59) -> 48031.7
C61: Net of Expenses | M61: =M38-M55 -> 12695.47 | P61: 11506.6 | Q61: 11506.6
P62: =2750+38.87 -> 2788.87 | Q62: 38.87
C63: Less: Deposits for the month of October 2024 | M63: 0 | P63: =P62+P61 -> 14295.47 | Q63: 1150 | R63: =SUM(Q62:Q63) -> 1188.87
Q64: =SUM(Q61:Q63) -> 12695.47
C65: Cash Balance as of October 31, 2024 | L65: P | M65: =M61-M63 -> 12695.47 | Q65: 14295.47 | R65: =Q64-Q65 -> -1600
C69: Cash in Bank as of September 30, 2024 | L69: P | M69: 71421.62
C71: Add: Deposits - | M71: 0
C72: Interest ( Net of witholding tax ) | M72: =5.78-1.16 -> 4.62
C73: Less: Withdrawals ( Oct. 7 & 17) | M73: =20000+10000 -> 30000
C74: Cash in Bank as of October 31, 2024 | L74: P | M74: =SUM(M69:M72)-M73 -> 41426.24
C79: Prepared by: | G79: Checked by: | I79: Audited by: | M79: Noted by:
C81: Elvira Grafil | G81: Fely Rabano | I81: Tina Murla | M81: Lucky Tiu
C82: Asst. Treasurer | G82: Treasurer | I82: Auditor | M82: President

Sheet Oct-2024-Sched A
B2: Schedule A
B7: Our Lady of the Most Holy Rosary (Sub-Parish)
G8: Control File - Receipts
F9: For the month of October 2024
G11: DONATIONS (Mass Intentions:Thanksgiving, Souls, others) | H11: DONATIONS | I11: Net of Donations | J11: STIPEND from | L11: Total Stipend
B12: Date | D12: OR Number | F12: Donor | J12: Donations | K12: Mass Collections
B13: October
B14: 06 | D14: 2776 | F14: Beng Grafil | G14: 100
B15: 06 | D15: =1+D14 -> 2777 | F15: Jerry | G15: 100
B16: 06 | D16: =1+D15 -> 2778 | F16: Elmer Buere | G16: 100
B17: 06 | D17: =1+D16 -> 2779 | F17: Jane Pasamba | G17: 100
B18: 06 | D18: =1+D16 -> 2779 | F18: Eloisa | G18: 100
B19: 06 | F19: No Official Receipt | G19: 200
B20: Sub-Total | G20: =SUM(G14:G19) -> 700 | I20: =G20-J20 -> 0 | J20: 700 | K20: 300 | L20: =J20+K20 -> 1000
B21: 13 | D21: 2781 | F21: Elmer Buere | G21: 200
B22: 13 | D22: =1+D21 -> 2782 | F22: Gina | G22: 100
B23: 13 | D23: =1+D22 -> 2783 | F23: Eloisa | G23: 100
B24: 13 | D24: =1+D23 -> 2784 | F24: Madel Belino | G24: 1500 | M24: env # 13
B25: Sub-Total | G25: =SUM(G21:G24) -> 1900 | I25: =G25-J25 -> 1500 | J25: 400 | K25: 600 | L25: =J25+K25 -> 1000
B26: 18 | D26: 2785 | F26: Elmer Buere | G26: 100
B27: 18 | D27: =1+D26 -> 2786 | F27: Elmer Buere | G27: 100
B28: 18 | D28: =1+D27 -> 2787 | F28: Belma | G28: 400
B29: 18 | D29: =1+D28 -> 2788 | F29: Pres SaraNanette | G29: 500
B30: 18 | D30: =1+D29 -> 2789 | F30: Ebony | G30: 500 | M30: env #14
B31: 18 | D31: =1+D30 -> 2790 | F31: Edna Mejia | G31: 500 | M31: env #24
B32: 18 | D32: =1+D31 -> 2791 | F32: Aviles Family | G32: 500 | M32: env #21
B33: Sub-Total | G33: =SUM(G26:G32) -> 2600 | I33: =G33-J33 -> 1100 | J33: 1500 | K33: 0 | L33: =J33+K33 -> 1500
B34: 19 | D34: 2792 | F34: Regine Estrada | G34: 200
B35: 19 | D35: =1+D34 -> 2793 | F35: Elmer Buere | G35: 100
B36: Sub-Total | G36: =SUM(G34:G35) -> 300 | I36: =G36-J36 -> 300
B37: 20 | D37: 2794 | F37: Imelda Torres | G37: 100
B38: 20 | D38: =1+D37 -> 2795 | F38: Gary Mariano | G38: 100
B39: 20 | D39: =1+D38 -> 2796 | F39: Damian Family | G39: 100
B40: 20 | D40: =1+D39 -> 2797 | F40: Jane Pasamba | G40: 100
B41: 20 | D41: =1+D40 -> 2798 | F41: Basilia Family | G41: 50
B42: 20 | D42: =1+D41 -> 2799 | F42: blank | G42: 0
B43: 20 | D43: =1+D42 -> 2800 | F43: Rose Riambon | G43: 1500 | M43: env #7
B44: Sub-Total | G44: =SUM(G37:G43) -> 1950 | I44: =G44-J44 -> 450 | J44: 1500 | L44: =J44+K44 -> 1500
B45: 12 | D45: 2801 | F45: Art De Leon | G45: 5000
B46: 13 | D46: =1+D45 -> 2802 | F46: Nida Albato | G46: 4000
B47: 14 | D47: =1+D46 -> 2803 | F47: Hilda Villena | G47: 3000
B48: 15 | D48: =1+D47 -> 2804 | F48: Melanie Tabuena | G48: 1000
B49: 17 | D49: =1+D48 -> 2805 | F49: Fely Rabano | G49: 3000
B50: 20 | D50: =1+D49 -> 2806 | F50: Grace Villaresco | G50: 5000
B51: 25 | D51: =1+D50 -> 2807 | F51: Rad Saringan | G51: 1000
F52: No Official Receipt/Donations from envelopes | G52: =19000-1000-600 -> 17400 | M52: 19000-1000-600 | O52: =19000-1000-600 -> 17400
B53: Sub-Total | G53: =SUM(G45:G52) -> 39400 | I53: =G53-J53 -> 36400 | J53: 3000 | L53: =J53+K53 -> 3000 | M53: Stipend - Oct 17 & 19
G54: 0 | I54: =G54-J54 -> 0
B55: TOTAL | G55: =G20+G25+G33+G36+G44+G53+G54 -> 46850 | I55: =I20+I25+I33+I36+I44+I53+I54 -> 39750 | J55: =J20+J25+J33+J36+J44+J53+J54 -> 7100 | K55: =K20+K25+K33+K36+K44+K53+K54 -> 900 | L55: =L20+L25+L33+L36+L44+L53+L54 -> 8000
M57: =41150-1600 -> 39550
M58: =M55-39550 -> -39550
M59: 1150
M60: 11506.6
M61: 38.87
M62: =SUM(M59:M61) -> 12695.47
B65: Stipend for the month of October 2024 | M65: =14295.47 -> 14295.47
B67: Period covered | F67: Amount | M67: =M62-M65 -> -1600
B68: October | C68: 06 | F68: 1000
B69: October | C69: 13 | F69: 1000
B70: October | C70: 17 | F70: 1500
B71: October | C71: 18 | F71: 1500
B72: October | C72: 19 | F72: 1500
B73: October | C73: 20 | F73: 1500
B75: Total Stipend | F75: =SUM(F68:F73) -> 8000

Sheet Oct - Fiesta-details
A2: FIESTA COLLECTION from Envelopes:
A3: Total as counted by Lucy, Gina & Lucky ……………
B4: Env. No. | D4: Amount | F4: Rcpt. # | H4: Stipend
A5: Luz Damian | B5: 01 | D5: 1000
A6: Merly Pagayon | B6: 04 | D6: 500
A7: Nanie Domingo | B7: 05 | D7: 200
A8: Rose Riambon | B8: 07 | C8: 1500 | D8: 1500 | F8: 2800 | H8: 1500 | I8: (10/19) | J8: =H8 -> 1500
A9: Emma Ortega | B9: 08 | D9: 100
A10: M. Tabuena | B10: 09 | C10: 1000 | D10: 1000 | F10: 2804
A11: Art de Leon | B11: 10 | C11: =D11 -> 5000 | D11: 5000 | F11: 2801
A12: Lara Fam. | B12: 11 | D12: 200
A13: Jane Pasamba | B13: 12 | D13: 500
A14: Madel Belino | B14: 13 | C14: =D14 -> 1500 | D14: 1500 | F14: 2784 | H14: 1500 | I14: (10/17) | J14: =H14 -> 1500
A15: Ebon Andres | B15: 14 | C15: =D15 -> 500 | D15: 500 | F15: 2789 | H15: 0
A16: Emily Silva | B16: 15 | D16: 1000
A17: Beng Grafil | B17: 17 | D17: 1000
A18: Baby Boris | B18: 20 | D18: 1000
A19: Leony Aviles | B19: 21 | C19: =D19 -> 500 | D19: 500 | F19: 2791 | H19: 500
A20: Eloisa Banog | B20: 22 | D20: 250
A21: Bautro Fam. | B21: 23 | D21: 200
A22: Edna Mejia | B22: 24 | C22: =D22 -> 500 | D22: 500 | F22: 2790 | H22: 0
A23: Masong Fam. | B23: 26 | C23: =D23 -> 1000 | D23: 1000 | F23: 2790
A24: Chua-Uy & Padua Fam. | B24: 29 | D24: 150
A25: Tess Sabado | B25: 31 | D25: 500
A26: Helen Caballero | B26: 32 | D26: 200
A27: Grace Conseja | B27: 33 | D27: 300
A28: Gina Singun | B28: 34 | D28: 500
A29: Ellen Mendoza | B29: 37 | D29: 500
A30: Lorena Bianzon | B30: 40 | D30: 3000
A31: Grace Villarisco | B31: 44 | C31: =D31 -> 5000 | D31: 5000 | F31: 2806
A32: Nanette Sara | B32: 46 | C32: =D32 -> 500 | D32: 500 | F32: 2788 | H32: 500 | I32: (10/18) | J32: =SUM(H19:H32) -> 1000
A33: Saringan Fam. | B33: 48 | C33: =D33 -> 1000 | D33: 1000 | F33: 2807
A34: Regine Estrada | B34: 49 | C34: =D34 -> 1000 | D34: 1000 | F34: 2787
A35: Tina Murla | D35: 2000
A36: Howie | D36: 500
D37: =SUM(D5:D36) -> 32600 | H37: =SUM(H5:H36) -> 4000
D38: =D37-H37 -> 28600
A39: No OR | C39: =SUM(C5:C34) -> 19000 | D39: =D36+D35+SUM(D24:D30)+D21+D20+D18+D17+D16+D13+D12+D9+D7+D6+D5 -> 13600
A40: With OR | D40: =C39 -> 19000
A41: Collections from Envelopes | D41: =D40+D39 -> 32600
A42: Stipend | D42: =H37 -> 4000
D43: =D41-D42 -> 28600
A45: DONORS: | B45: Rcpt. No. | D45: Amount
A47: Nida Alberto | B47: 2802 | D47: 4000 | F47: 2802
A48: Hilda Villena | B48: 2803 | D48: 3000 | F48: 2803
A49: Fely Rabano | B49: 2805 | D49: 3000 | F49: 2805
D50: 10000
A52: TOTAL COLLECTION …………… | D52: 38600
A57: FIESTA EXPENSES:
A58: Catering …………………. | D58: 30000
A59: Extra fee for catering crew | D59: 1000
A60: Food for drum & lyre | D60: 4000
A61: Flowers for altar | D61: 2000
A62: Additional flowers for caroza | D62: 1000
A63: Drum & Lyre Fee | D63: 4000 | F63: =SUM(D58:D63) -> 42000
A66: Other Expenses:
A67: Caroza bulbs | D67: 640
A68: Misc.(paper cup, plastic tubs) | D68: 205
A69: Fiesta Tarpaulin | D69: 160
A70: Bulbs for altar | D70: 202
A71: Bottled water /snack for prosisyon | D71: 643.15
A72: Bioman services 10/17-20 - see attached | D72: 1284
A73: Bottled water for Drum & Lyre | D73: 420
A74: Bibingka & puto for Fr. Von, (SLRP staff) | D74: 1310
A75: Misc.: d.washing liquied, sponge, soap | D75: 229.25 | F75: =SUM(D67:D75) -> 5093.4
A76: TOTAL EXPENSES ………………………………………… | F76: 47093.4
A78: TOTAL COLLECTION …………………………………………. | F78: 38600
A79: Cash withdrawal from NOC ………………. | F79: 20000
F80: 58600
A81: Less: Total Expenses ………… | F81: -47093.4
A82: NET CASH BALANCE ……………………………….. | F82: =SUM(F80:F81) -> 11506.6
A87: Prepared by: | D87: Checked by:
A89: Tina Murla | D89: Beng Grafil

Sheet Nov-2024-FR
C4: Our Lady of the Most Holy Rosary (Sub-Parish)
C5: Diamond Crest Village ,Brgy, San Manuel, San Jose DelMonte City, Bulacan
C7: FINANCIAL REPORT
C8: As of November 30, 2024
C10: Cash Balance as of November 01, 2024 | L10: P | M10: ='Oct-2024-FR'!M65 -> 12695.47 | O10: 11506.6 | P10: =O10-M10 -> -1188.87
C12: Add: Receipts for the month of November 2024
C14: Mass Collections: | G14: (Net of Stipend)
H16: Collections | I16: Stipend | J16: Others | K16: Net Amount
E18: November | G18: 03 | H18: 603 | I18: 0 | J18: 0 | K18: =H18-I18-J18 -> 603
E19: November | G19: 10 | H19: 1609 | I19: 450 | J19: 0 | K19: =H19-I19 -> 1159
E20: November | G20: 17 | H20: 833 | I20: 400 | J20: 0 | K20: =H20-I20 -> 433
E21: October | G21: 18 | H21: 0 | I21: 0 | J21: 0 | K21: =H21-I21 -> 0
E22: October | G22: 19 | H22: 0 | I22: 0 | J22: 0 | K22: =H22-I22 -> 0
E23: October | G23: 20 | H23: 0 | I23: 0 | J23: 0 | K23: =H23-I23 -> 0
E24: October | G24: 27 | H24: 0 | I24: 0 | J24: 0 | K24: =H24-I24 -> 0 | O24: No mass
E26: Total | H26: =SUM(H18:H24) -> 3045 | I26: =SUM(I18:I24) -> 850 | J26: =SUM(J18:J24) -> 0 | K26: =SUM(K18:K24) -> 2195 | O26: =H26-I26 -> 2195
C30: Donations from Mass Intentions (see Schedule A)
E32: Donations ( net of Stipend ) | K32: ='Nov-2024-Sched A'!I55 -> 1000 | M32: =K32+K26 -> 3195
C34: Add: Cash withdrawal
E35: 39356 | K35: 0
E36: 43009 | K36: 0 | M36: =SUM(K35:K36) -> 0
C38: Total Cash Available | L38: P | M38: =M32+M36+M10 -> 15890.47
C43: Less: Expenses for the month of November 2024
C45: Date | E45: PCV # | G45: Particulars | K45: Amount
C47: November 3 | G47: Parol ( partial payment ) | K47: 1000
C48: November 16 | G48: Financial Assistance to DLC IV (Feast of Christ the King) | K48: 1000
C49: November 17 | G49: Stipend - DCV mass sponsor on Novenario Masses | K49: 500
C50: November 26 | G50: Purchase of christmas lights ( chapel décor ) | K50: 693.1
C51: November 29 | G51: Labor expenses ( Bioman 's assistance in the decoration and cleaning of the chapel | K51: 471.5
C52: November 29 | G52: Candles | K52: 141.5 | M52: =SUM(K47:K52) -> 3806.1
C53: November 29 | G53: Electricity Expenses ( Meralco Bill - August 211 to September 20 ) | K53: 0
C54: November 29 | G54: Water Expenses ( Billing period - August 12-September 11 ) | K54: 0
C55: November 29 | K55: 0 | M55: 0
C56: June 18, 2024 | G56: Utility Expenses ( Water Bills share for 2 months ) | K56: 0
C57: June 20, 2024 | G57: Battery for Laptop used at Chapel | K57: 0
C58: June 29, 2024 | G58: Candles | K58: 0
C59: June 30, 2024 | G59: Flowers at SLR Parish for the month of June 2024 | K59: 0 | M59: =SUM(K53:K59) -> 0
C61: Net of Expenses | M61: =M38-M52 -> 12084.37
C63: Less: Deposits for the month of November 2024 | M63: 11506.6
C65: Cash Balance as of November 30, 2024 | L65: P | M65: =M61-M63 -> 577.77
C69: Cash in Bank as of October 31, 2024 | L69: P | M69: 41426.24
C71: Add: Deposits - November 22, 2024 | M71: 11506.6
C72: Interest ( Net of witholding tax ) | M72: =4.68-0.94 -> 3.74
C73: Less: Withdrawals ( Oct. 7 & 17) | M73: 0
C74: Cash in Bank as of November 30, 2024 | L74: P | M74: =SUM(M69:M72)-M73 -> 52936.58
C79: Prepared by: | G79: Checked by: | I79: Audited by: | M79: Noted by:
C81: Elvira Grafil | G81: Fely Rabano | I81: Tina Murla | M81: Lucky Tiu
C82: Asst. Treasurer | G82: Treasurer | I82: Auditor | M82: President

Sheet Nov-2024-Sched A
B2: Schedule A
B7: Our Lady of the Most Holy Rosary (Sub-Parish)
G8: Control File - Receipts
F9: For the month of November 2024
G11: DONATIONS (Mass Intentions:Thanksgiving, Souls, others) | H11: DONATIONS | I11: Net of Donations | J11: STIPEND from | L11: Total Stipend
B12: Date | D12: OR Number | F12: Donor | J12: Donations | K12: Mass Collections
B13: November
B14: 03 | D14: 2808 | F14: Art De Leon | G14: 500
B15: 03 | D15: =1+D14 -> 2809 | F15: Elmer Buere | G15: 100
B16: 03 | D16: =1+D15 -> 2810 | F16: Beng Grafil | G16: 100
B17: 03 | D17: =1+D16 -> 2811 | F17: Banog Family | G17: 100
B18: 03 | D18: =1+D17 -> 2812 | F18: Ebony | G18: 100
B19: 03 | D19: =1+D18 -> 2813 | F19: Grafil Family | G19: 1000 | M19: env # 17
B20: Sub-Total | G20: =SUM(G14:G19) -> 1900 | I20: =G20-J20 -> 900 | J20: 1000 | K20: 0 | L20: =J20+K20 -> 1000
B21: 10 | D21: 2814 | F21: Lucy | G21: 100
B22: 10 | D22: =1+D21 -> 2815 | F22: Lucy | G22: 50
B23: 10 | D23: =1+D22 -> 2816 | F23: Gina | G23: 100
B24: 10 | D24: =1+D23 -> 2817 | F24: Imelda | G24: 100
B25: 10 | D25: =1+D24 -> 2818 | F25: Juvy | G25: 100
B26: 10 | D26: =1+D25 -> 2819 | F26: Eloisa | G26: 100
B27: Sub-Total | G27: =SUM(G21:G26) -> 550 | I27: =G27-J27 -> 0 | J27: 550 | K27: 450 | L27: =J27+K27 -> 1000
B28: 17 | D28: 2820 | F28: Gina | G28: 100
B29: 17 | D29: =1+D28 -> 2821 | F29: Art De Leon | G29: 200
B30: 17 | D30: =1+D29 -> 2822 | F30: Jane Pasamba | G30: 100
B31: 17 | D31: =1+D30 -> 2823 | F31: Jonie | G31: 100
B32: 17 | D32: =1+D31 -> 2824 | F32: Beng Grafil | G32: 100
B33: 17 | D33: =1+D32 -> 2825 | F33: Elmer Buere | G33: 100
B34: Sub-Total | G34: =SUM(G28:G33) -> 700 | I34: =G34-J34 -> 100 | J34: 600 | K34: 400 | L34: =J34+K34 -> 1000
B35: 19 | D35: 2792 | F35: Regine Estrada
B36: 19 | D36: =1+D35 -> 2793 | F36: Elmer Buere
B37: Sub-Total | G37: =SUM(G35:G36) -> 0 | I37: =G37-J37 -> 0
B38: 20 | D38: 2794 | F38: Imelda Torres
B39: 20 | D39: =1+D38 -> 2795 | F39: Gary Mariano
B40: 20 | D40: =1+D39 -> 2796 | F40: Damian Family
B41: 20 | D41: =1+D40 -> 2797 | F41: Jane Pasamba
B42: 20 | D42: =1+D41 -> 2798 | F42: Basilia Family
B43: 20 | D43: =1+D42 -> 2799 | F43: blank | G43: 0
B44: 20 | D44: =1+D43 -> 2800 | F44: Rose Riambon
B45: Sub-Total | G45: =SUM(G38:G44) -> 0 | I45: =G45-J45 -> 0 | J45: 0 | L45: =J45+K45 -> 0
B46: 12 | D46: 2801 | F46: Art De Leon
B47: 13 | D47: =1+D46 -> 2802 | F47: Nida Albato
B48: 14 | D48: =1+D47 -> 2803 | F48: Hilda Villena
B49: 15 | D49: =1+D48 -> 2804 | F49: Melanie Tabuena
B50: 17 | D50: =1+D49 -> 2805 | F50: Fely Rabano
B51: 20 | D51: =1+D50 -> 2806 | F51: Grace Villaresco
B52: 25 | D52: =1+D51 -> 2807 | F52: Rad Saringan
B53: Sub-Total | G53: =SUM(G46:G52) -> 0 | I53: =G53-J53 -> 0 | J53: 0 | L53: =J53+K53 -> 0 | M53: Stipend - Oct 17 & 19
B54: Sub-Total | F54: No Official Receipt/Donations from envelopes | I54: =G54-J54 -> 0
B55: TOTAL | G55: =G20+G27+G34+G37+G45+G53+G54 -> 3150 | I55: =I20+I27+I34+I37+I45+I53+I54 -> 1000 | J55: =J20+J27+J34+J37+J45+J53+J54 -> 2150 | K55: =K20+K27+K34+K37+K45+K53+K54 -> 850 | L55: =L20+L27+L34+L37+L45+L53+L54 -> 3000
B64: Stipend for the month of November 2024
B66: Period covered | F66: Amount
B67: November | C67: 03 | F67: 1000
B68: November | C68: 10 | F68: 1000
B69: November | C69: 17 | F69: 1000
B71: Total Stipend | F71: =SUM(F67:F69) -> 3000

Sheet Dec-2024-FR
C4: Our Lady of the Most Holy Rosary (Sub-Parish)
C5: Diamond Crest Village ,Brgy, San Manuel, San Jose DelMonte City, Bulacan
C7: FINANCIAL REPORT
C8: As of December 31, 2024
C12: Cash Balance as of December 01, 2024 | L12: P | M12: 577.77
C14: Add: Receipts for the month of December 2024
C16: Mass Collections: | G16: (Net of Stipend)
H18: Collections | I18: Stipend | J18: Others | K18: Net Amount
E20: December | G20: 01 | H20: 2139 | I20: 300 | J20: 0 | K20: =H20-I20-J20 -> 1839
E21: December | G21: 08 | H21: 2021 | I21: 300 | J21: 0 | K21: =H21-I21-J21 -> 1721
E22: December | G22: 15 | H22: 3157 | J22: 0 | K22: =H22-I22-J22 -> 3157
E23: December | G23: =1+G22 -> 16 | H23: 1513 | J23: 0 | K23: =H23-I23-J23 -> 1513
E24: December | G24: =1+G23 -> 17 | H24: 1731 | J24: 0 | K24: =H24-I24-J24 -> 1731
E25: December | G25: =1+G24 -> 18 | H25: 1063 | I25: 500 | J25: 0 | K25: =H25-I25-J25 -> 563
E26: December | G26: =1+G25 -> 19 | H26: 1759 | J26: 0 | K26: =H26-I26-J26 -> 1759
E27: December | G27: =1+G26 -> 20 | H27: 1774 | J27: 0 | K27: =H27-I27-J27 -> 1774
E28: December | G28: =1+G27 -> 21 | H28: 1447 | J28: 0 | K28: =H28-I28-J28 -> 1447
E29: December | G29: =1+G28 -> 22 | H29: 3316 | J29: 0 | K29: =H29-I29-J29 -> 3316
E30: December | G30: =1+G29 -> 23 | H30: 1806 | J30: 0 | K30: =H30-I30-J30 -> 1806
E31: December | G31: 25 | H31: 1631 | J31: 0 | K31: =H31-I31-J31 -> 1631
E32: December | G32: 29 | H32: 1104 | I32: 600 | J32: 0 | K32: =H32-I32-J32 -> 504
E33: October | G33: 18 | H33: 0 | I33: 0 | J33: 0 | K33: =H33-I33 -> 0
E34: October | G34: 19 | H34: 0 | I34: 0 | J34: 0 | K34: =H34-I34 -> 0
E35: October | G35: 20 | H35: 0 | I35: 0 | J35: 0 | K35: =H35-I35 -> 0
E36: October | G36: 27 | H36: 0 | I36: 0 | J36: 0 | K36: =H36-I36 -> 0 | O36: No mass
E38: Total | H38: =SUM(H20:H36) -> 24461 | I38: =SUM(I20:I36) -> 1700 | J38: =SUM(J20:J36) -> 0 | K38: =SUM(K20:K36) -> 22761 | O38: =H38-I38 -> 22761
C42: Donations from Mass Intentions /Pledges: (see Schedule A)
E44: Donations ( net of Stipend ) | K44: ='Dec-2024-Sched A'!I102 -> 4450 | M44: =K44+K38 -> 27211
C46: Add: Cash withdrawal | M46: 5500
E47: 39356 | K47: 0
E48: 43009 | K48: 0 | M48: =SUM(K47:K48) -> 0
C50: Total Cash Available | L50: P | M50: =M46+M44+M12 -> 33288.77
C55: Less: Expenses for the month of December 2024
C57: Date | E57: PCV # | G57: Particulars | K57: Amount
C59: December 1 | G59: Ordo | K59: 300
C60: December 1 | G60: Gel Candles | K60: 690
C61: December 1 | G61: Parol (last payment) | K61: 1000
C62: December 3 | G62: SPPC share ( Angels-SLR Parish ) | K62: 3000
C63: December 4 | G63: Repair of 2 outlets (Chapel) | K63: 260
C64: December 6 | G64: Installation of christmas decors | K64: 768.6
C65: December 7 | G65: Food for SLRP carolers | K65: 3350
C66: December 11 | G66: Purchase of colored bulbs | K66: 704
C67: December 11 | G67: Christmas Tarpaulin (Simbang Gabi) | K67: 1000
C68: December 12 | G68: Purchase of small envelopes | K68: 309
C69: December 12 | G69: Candles for Chapel | K69: 198
C70: December 12 | G70: Spray paint/bulb | K70: 175
C71: December 13 | G71: Electricity Expenses ( Meralco Bill - Sept 21 to Nov 20 ) | K71: =650+730 -> 1380
C72: December 13 | G72: Water Expenses ( Billing period - Sept 11-Nov 11 ) | K72: =300+300 -> 600
C73: December 17 | G73: Battery for microphone used at Chapel | K73: 88
C74: December 17 | G74: Christmas goods for 3 Bioman | K74: 2680
C75: December 19 | G75: Take-out food for Father Von ( Dec 18 & 19) | K75: 1650
C76: December 20 | G76: SPPC - Sponsor for Simbang Gabi | K76: 1500
C77: December 21 | G77: Take-out food for Father Von | K77: 860
C78: December 22 | G78: Purchase of Monde mamon and candies for SLR Parish | K78: 3099.75
C79: December 25 | G79: Gift Check for Fr. Von | K79: 1500
C80: December 29 | G80: Food Share for SLR Parish christmas party | K80: 2550
C81: December 30 | G81: Grace Conseja - Food for Dec 21 & Dec 25 | K81: 1095 | M81: =SUM(K59:K81) -> 28757.35 | O81: 25152.35 | P81: =M81-O81 -> 3605
C83: Net of Expenses | M83: =M50-M81 -> 4531.42
C85: Less: Deposits for the month of December 2024 | M85: 0
C87: Cash Balance as of December 31, 2024 | L87: P | M87: =M83-M85 -> 4531.42
C91: Cash in Bank as of November 30, 2024 | L91: P | M91: 52936.58
C93: Add: Deposits - | M93: 0
C94: Interest ( Net of witholding tax ) | M94: =5.18-1.04 -> 4.14
C95: Less: Withdrawals ( Dec 5) | M95: 5500
C96: Cash in Bank as of December 31, 2024 | L96: P | M96: =SUM(M91:M94)-M95 -> 47440.72
O97: 47440.72 | P97: =M96-O97 -> 0
C101: Prepared by: | G101: Checked by: | I101: Audited by: | M101: Noted by:
C103: Elvira Grafil | G103: Fely Rabano | I103: Tina Murla | M103: Lucky Tiu
C104: Asst. Treasurer | G104: Treasurer | I104: Auditor | M104: President

Sheet Dec-2024-Sched A
B2: Schedule A
B5: Our Lady of the Most Holy Rosary (Sub-Parish)
G6: Control File - Receipts
F7: For the month of December 2024
G9: DONATIONS (Mass Intentions:Thanksgiving, Souls, others) | H9: DONATIONS | I9: Net of Donations | J9: STIPEND from | L9: Total Stipend
B10: Date | D10: OR Number | F10: Donor | J10: Donations | K10: Mass Collections
B11: December
B12: 01 | D12: 2826 | F12: Beng Grafil & Family | G12: 100
B13: 01 | D13: =1+D12 -> 2827 | F13: Jane Pasamba & Family | G13: 100
B14: 01 | D14: =1+D13 -> 2828 | F14: Lucy & Family | G14: 100
B15: 01 | D15: =1+D14 -> 2829 | F15: Elmer Buere | G15: 100
B16: 01 | D16: =1+D15 -> 2830 | F16: Irene Masong | G16: 100
B17: 01 | D17: =1+D16 -> 2831 | F17: Lucy Salas | G17: 100
B18: 01 | D18: =1+D17 -> 2832 | F18: Juvy Mateo | G18: 100
B19: Sub-Total | G19: =SUM(G12:G18) -> 700 | I19: =G19-J19 -> 0 | J19: 700 | K19: 300 | L19: =J19+K19 -> 1000
B20: 08 | D20: 2833 | F20: Beng Grafil & Family | G20: 100
B21: 08 | D21: =1+D20 -> 2834 | F21: Eloisa | G21: 100
B22: 08 | D22: =1+D21 -> 2835 | F22: Ebony | G22: 100
B23: 08 | D23: =1+D22 -> 2836 | F23: Susan Chua | G23: 100
B24: 08 | D24: =1+D22 -> 2836 | F24: Susan Chua | G24: 100
F25: No Official Receipt | G25: 0
B26: Sub-Total | G26: =SUM(G20:G25) -> 500 | I26: =G26-J26 -> -200 | J26: 700 | K26: 300 | L26: =J26+K26 -> 1000
B27: 15 | D27: 2838 | F27: Art De Leon | G27: 200 | L27: =J27+K27 -> 0
B28: 15 | D28: =1+D27 -> 2839 | F28: Freddie Damian | G28: 100 | L28: =J28+K28 -> 0
B29: 15 | D29: =1+D28 -> 2840 | F29: Lucy | G29: 100 | L29: =J29+K29 -> 0
B30: 15 | D30: =1+D29 -> 2841 | F30: Gina | G30: 100 | L30: =J30+K30 -> 0
B31: 15 | D31: =1+D30 -> 2842 | F31: Beng Grafil & Family | G31: 1500 | J31: 0 | L31: =J31+K31 -> 0 | M31: stipend-Dec 15 | P31: 1500
B32: 15 | D32: =1+D31 -> 2843 | F32: Fely Rabano | G32: 1500 | J32: 0 | L32: =J32+K32 -> 0 | M32: stipend-Dec 16 | P32: 1500
B33: 15 | D33: =1+D32 -> 2844 | F33: Terrie Pisalbon | G33: 3000 | L33: =J33+K33 -> 0 | M33: stipend-Dec 16
B34: 15 | D34: =1+D33 -> 2845 | F34: Belma | G34: 600 | J34: 0 | L34: =J34+K34 -> 0
B35: Sub-Total | G35: =SUM(G27:G34) -> 7100 | I35: =G35-J31-J32-J35 -> 2600 | J35: 4500 | L35: =J35+K35 -> 4500 | M35: stipend-Dec 15, 16 &17
B36: 16 | D36: 2846 | F36: Molina Family | G36: 200 | L36: =J36+K36 -> 0
B37: Sub-Total | G37: =G36 -> 200 | I37: =G37-J33-J34-J37 -> 200 | L37: =J37+K37 -> 0
B38: 17 | D38: 2847 | F38: Molina Family | G38: 100 | L38: =J38+K38 -> 0
B39: 17 | D39: 2848 | F39: Elmer Buere | G39: 100 | L39: =J39+K39 -> 0
B40: 17 | D40: 2849 | F40: Leaticia | G40: 200 | L40: =J40+K40 -> 0
B41: Sub-Total | G41: =SUM(G38:G40) -> 400 | I41: =G41-J37-J38-J41 -> 400 | L41: =J41+K41 -> 0
B42: 18 | D42: =1+D40 -> 2850 | F42: Elmer Buere | G42: 100 | L42: =J42+K42 -> 0
B43: 18 | D43: =1+D42 -> 2851 | F43: Gina | G43: 100 | L43: =J43+K43 -> 0
B44: 18 | D44: =1+D43 -> 2852 | F44: Art De Leon | G44: 200 | L44: =J44+K44 -> 0
B45: 18 | D45: =1+D44 -> 2853 | F45: Reylyn Calonge | G45: 750 | P45: 750
B46: Sub-Total | G46: =SUM(G42:G45) -> 1150 | I46: =G46-J46 -> 150 | J46: 1000 | K46: 500 | L46: =J46+K46 -> 1500 | M46: stipend - Dec 18
B47: 19 | D47: =1+D45 -> 2854 | F47: Lerma | G47: 1500 | J47: 0 | L47: =J47+K47 -> 0 | P47: 1500
B48: 19 | D48: =1+D47 -> 2855 | F48: Gina | G48: 100 | L48: =J48+K48 -> 0
B49: 19 | D49: =1+D48 -> 2856 | F49: Art De Leon | G49: 200 | L49: =J49+K49 -> 0
B50: Sub-Total | G50: =SUM(G47:G49) -> 1800 | I50: =G50-J50 -> 300 | J50: 1500 | L50: =J50+K50 -> 1500 | M50: stipend - Dec 19
B51: 20 | D51: =1+D49 -> 2857 | F51: Helen Caballero | G51: 100 | L51: =J51+K51 -> 0
B52: 20 | D52: =1+D51 -> 2858 | F52: Elmer Buere | G52: 100 | L52: =J52+K52 -> 0
B53: 20 | D53: =1+D52 -> 2859 | F53: Luz Damian | G53: 100 | L53: =J53+K53 -> 0
B54: 20 | D54: =1+D53 -> 2860 | F54: Riz Damian | G54: 100 | L54: =J54+K54 -> 0
B55: Sub-Total | G55: =SUM(G51:G54) -> 400 | I55: =G55-J51-J52-J55 -> 400 | L55: =J55+K55 -> 0
B56: 21 | D56: =1+D54 -> 2861 | F56: Irene Masong | G56: 50 | L56: =J56+K56 -> 0
B57: 21 | D57: =1+D56 -> 2862 | F57: Lea Tamayo | G57: 150 | L57: =J57+K57 -> 0
B58: Sub-Total | G58: =SUM(G56:G57) -> 200 | I58: =G58-J54-J55-J58 -> 200 | L58: =J58+K58 -> 0
B59: 22 | D59: =1+D57 -> 2863 | F59: Erlinda | G59: 100 | L59: =J59+K59 -> 0
B60: 22 | D60: =1+D59 -> 2864 | F60: Henry Ortega | G60: 100 | L60: =J60+K60 -> 0
B61: 22 | D61: =1+D60 -> 2865 | F61: Eloisa | G61: 100 | L61: =J61+K61 -> 0
B62: 22 | D62: =1+D61 -> 2866 | F62: Irene Masong | G62: 1500 | J62: 0 | L62: =J62+K62 -> 0 | M62: stipend | P62: 1500
B63: 22 | D63: =1+D62 -> 2867 | F63: Madel/Helen/Jane | G63: 1500 | L63: =J63+K63 -> 0 | M63: stipend | P63: 1500
B64: 22 | D64: =1+D63 -> 2868 | F64: Ris Centeno | G64: 1000 | L64: =J64+K64 -> 0 | M64: stipend | P64: 1000
B65: 22 | D65: =1+D64 -> 2869 | F65: Roger & Emma Belino | G65: 500 | L65: =J65+K65 -> 0 | M65: stipend
B66: Sub-Total | G66: =SUM(G59:G65) -> 4800 | I66: =G66-J66 -> 300 | J66: =1500+1500+1500 -> 4500 | L66: =J66+K66 -> 4500 | M66: stipend - Dec 20, 21, & 22
B67: 23 | D67: =1+D65 -> 2870 | F67: Erlinda | G67: 100 | L67: =J67+K67 -> 0
B68: 23 | D68: =1+D67 -> 2871 | F68: Elmer Buere | G68: 100 | L68: =J68+K68 -> 0
B69: 23 | D69: =1+D68 -> 2872 | F69: Ebony | G69: 100 | L69: =J69+K69 -> 0
B70: 23 | D70: =1+D69 -> 2873 | F70: Liwayway Molina | G70: 100 | L70: =J70+K70 -> 0
B71: 23 | D71: =1+D70 -> 2874 | F71: Bel | G71: 100 | L71: =J71+K71 -> 0
B72: 23 | D72: =1+D71 -> 2875 | F72: Helen | G72: 1000 | L72: =J72+K72 -> 0 | P72: 1000
B73: Sub-Total | G73: =SUM(G67:G72) -> 1500 | I73: =G73-J73 -> 0 | J73: 1500 | L73: =J73+K73 -> 1500 | M73: stipend - Dec 23
B74: 25 | D74: =2876 -> 2876 | F74: Lucy | G74: 100 | L74: =J74+K74 -> 0
B75: 25 | D75: =1+D74 -> 2877 | F75: Baby Borris | G75: 1500 | L75: =J75+K75 -> 0
B76: Sub-Total | G76: =SUM(G74:G75) -> 1600 | I76: =G76-J76 -> 100 | J76: 1500 | L76: =J76+K76 -> 1500 | M76: stipend - Dec 25 | P76: 1500
B77: 29 | D77: =1+D75 -> 2878 | F77: Reylyn Calonge | G77: 100 | L77: =J77+K77 -> 0
B78: 29 | D78: =1+D77 -> 2879 | F78: Lucy | G78: 100 | L78: =J78+K78 -> 0
B79: 29 | D79: =1+D78 -> 2880 | F79: Elmer Buere | G79: 100 | L79: =J79+K79 -> 0
B80: 29 | D80: =1+D79 -> 2881 | F80: Centeno Family | G80: 100 | L80: =J80+K80 -> 0
B81: Sub-Total | G81: =SUM(G77:G80) -> 400 | I81: =G81-J81 -> 0 | J81: 400 | K81: 600 | L81: =J81+K81 -> 1000
B82: 19 | D82: 2792 | F82: Regine Estrada
B83: 19 | D83: =1+D82 -> 2793 | F83: Elmer Buere
B84: Sub-Total | G84: =SUM(G82:G83) -> 0 | I84: =G84-J84 -> 0
B85: 20 | D85: 2794 | F85: Imelda Torres
B86: 20 | D86: =1+D85 -> 2795 | F86: Gary Mariano
B87: 20 | D87: =1+D86 -> 2796 | F87: Damian Family
B88: 20 | D88: =1+D87 -> 2797 | F88: Jane Pasamba
B89: 20 | D89: =1+D88 -> 2798 | F89: Basilia Family
B90: 20 | D90: =1+D89 -> 2799 | F90: blank | G90: 0
B91: 20 | D91: =1+D90 -> 2800 | F91: Rose Riambon
B92: Sub-Total | G92: =SUM(G85:G91) -> 0 | I92: =G92-J92 -> 0 | J92: 0 | L92: =J92+K92 -> 0
B93: 12 | D93: 2801 | F93: Art De Leon
B94: 13 | D94: =1+D93 -> 2802 | F94: Nida Albato
B95: 14 | D95: =1+D94 -> 2803 | F95: Hilda Villena
B96: 15 | D96: =1+D95 -> 2804 | F96: Melanie Tabuena
B97: 17 | D97: =1+D96 -> 2805 | F97: Fely Rabano
B98: 20 | D98: =1+D97 -> 2806 | F98: Grace Villaresco
B99: 25 | D99: =1+D98 -> 2807 | F99: Rad Saringan
B100: Sub-Total | G100: =SUM(G93:G99) -> 0 | I100: =G100-J100 -> 0 | J100: 0 | L100: =J100+K100 -> 0 | M100: Stipend - Oct 17 & 19
B101: Sub-Total | F101: No Official Receipt/Donations from envelopes | I101: =G101-J101 -> 0
B102: TOTAL | G102: =G81+G76+G73+G66+G58+G55+G50+G46+G41+G37+G35+G26+G19 -> 20750 | I102: =I81+I76+I73+I66+I58+I55+I50+I46+I41+I37+I35+I26+I19 -> 4450 | J102: =J81+J76+J73+J66+J58+J55+J50+J46+J41+J37+J35+J26+J19 -> 16300 | K102: =K81+K76+K73+K66+K58+K55+K50+K46+K41+K37+K35+K26+K19 -> 1700 | L102: =L81+L76+L73+L66+L58+L55+L50+L46+L41+L37+L35+L26+L19 -> 18000 | P102: =SUM(P12:P81) -> 11750
P103: 10950
B106: Stipend for the month of December 2024
...

Sheet Jan-2025-FR
C2: Our Lady of the Most Holy Rosary (Sub-Parish)
C3: Diamond Crest Village ,Brgy, San Manuel, San Jose DelMonte City, Bulacan
C5: FINANCIAL REPORT
C6: As of January 31, 2025
C8: Cash Balance as of January 01, 2021 | L8: P | M8: 4531.42
C10: Add: Receipts for the month of January 2025
C12: Mass Collections: | G12: (Net of Stipend)
H14: Collections | I14: Stipend | J14: Others | K14: Net Amount
E16: January | G16: 01 | H16: 1188 | I16: 0 | J16: 0 | K16: =H16-I16-J16 -> 1188
E17: January | G17: 05 | H17: 1748 | I17: 350 | J17: 0 | K17: =H17-I17-J17 -> 1398
E18: January | G18: 12 | H18: 2334 | J18: 0 | K18: =H18-I18-J18 -> 2334
E19: January | G19: 19 | H19: 1791 | J19: 0 | K19: =H19-I19-J19 -> 1791
E20: January | G20: 26 | H20: 1751 | I20: 200 | J20: 0 | K20: =H20-I20-J20 -> 1551
E21: October | G21: 18 | H21: 0 | I21: 0 | J21: 0 | K21: =H21-I21 -> 0
E22: October | G22: 19 | H22: 0 | I22: 0 | J22: 0 | K22: =H22-I22 -> 0
E23: October | G23: 20 | H23: 0 | I23: 0 | J23: 0 | K23: =H23-I23 -> 0
E24: October | G24: 27 | H24: 0 | I24: 0 | J24: 0 | K24: =H24-I24 -> 0 | O24: No mass
E26: Total | H26: =SUM(H16:H24) -> 8812 | I26: =SUM(I16:I24) -> 550 | J26: =SUM(J16:J24) -> 0 | K26: =SUM(K16:K24) -> 8262 | O26: 8897 | P26: =O26-K26 -> 635
C28: Donations from Mass Intentions /Pledges: (see Schedule A)
E30: Donations ( net of Stipend ) | K30: ='Jan-2025-Sched A'!I73 -> 12985 | M30: =K30+K26 -> 21247 | O30: 12450 | P30: =O30-K30 -> -535
C32: Add: Cash withdrawal
E33: 27 January 2025 | K33: 20000
E34: 30 January 2025 | K34: 20000 | M34: =SUM(K33:K34) -> 40000
C36: Total Cash Available | L36: P | M36: =+M30+M8+M34 -> 65778.42
C39: Less: Expenses for the month of January 2025
C41: Date | E41: PCV # | G41: Particulars | K41: Amount
C43: January 4 | G43: Funeral Flower for the late Lorena Bianzon | K43: 1500
C44: January 16 | G44: Electricity Expenses ( Meralco Bill - Nov 21 to Dec 20 ) | K44: 813.2
C45: January 16 | G45: Water Expenses ( Billing period - Nov 11 to Dec 11 ) | K45: 150
C46: January 17 | G46: Repair Expenses of Electric Fan | K46: 250 | M46: =SUM(K43:K46) -> 2713.2
C48: Net of Expenses | M48: =M36-M46 -> 63065.22
C50: Less: Deposits for the month of January 2025
E51: 06 January 2025 | K51: 4534
E52: 06 January 2025 | K52: 10950 | M52: =SUM(K51:K52) -> 15484 | O52: 12450 | P52: =K52-O52 -> -1500
C54: Cash Balance as of January 31, 2025 | L54: P | M54: =M48-M52 -> 47581.22 | O54: 52681.17 | P54: =M54-O54 -> -5099.95
C57: Cash in Bank as of December 31, 2024 | L57: P | M57: 47440.72
C59: Add: Deposits - Jan 6, 2025 | M59: =4534+10950 -> 15484
C60: Interest ( Net of witholding tax ) | M60: =6.02-1.2 -> 4.82
C61: Less: Withdrawals ( Jan 27 & 30 ) | M61: 40000
C62: Cash in Bank as of January 31, 2025 | L62: P | M62: =SUM(M57:M60)-M61 -> 22929.54
O63: 22929.54 | P63: =M62-O63 -> 0
C66: Prepared by: | G66: Checked by: | I66: Audited by: | M66: Noted by:
C68: Elvira Grafil | G68: Fely Rabano | I68: Tina Murla | M68: Lucky Tiu
C69: Asst. Treasurer | G69: Treasurer | I69: Auditor | M69: President

Sheet Jan-2025-Sched A
B2: Schedule A
B5: Our Lady of the Most Holy Rosary (Sub-Parish)
G6: Control File - Receipts
F7: For the month of January 2025
G9: DONATIONS (Mass Intentions:Thanksgiving, Souls, others) | H9: DONATIONS | I9: Net of Donations | J9: STIPEND from | L9: Total Stipend
B10: Date | D10: OR Number | F10: Donor | J10: Donations | K10: Mass Collections
B11: January
B12: 01 | D12: 2882 | F12: Jane Pasamba | G12: 100
B13: 01 | D13: =1+D12 -> 2883 | F13: Irene Masong | G13: 100
B14: 01 | D14: =1+D13 -> 2884 | F14: Lucy | G14: 100
B15: 01 | D15: =1+D14 -> 2885 | F15: Ris Centeno | G15: 100
B16: 01 | D16: =1+D15 -> 2886 | F16: Aveles family | G16: 150
F17: No Official Receipt | G17: =950+635 -> 1585 | O17: 0
B18: 01 | F18: No Official Receipts | G18: 0
B19: Sub-Total | G19: =SUM(G12:G18) -> 2135 | I19: =G19-J19 -> 635 | J19: 1500 | K19: 0 | L19: =J19+K19 -> 1500
B20: 05 | D20: 2887 | F20: Beng Grafil & Family | G20: 100
B21: 05 | D21: =1+D20 -> 2888 | F21: Grace Villarisco | G21: 5000 | M21: christmas envelope | O21: 5000
B22: 05 | D22: =1+D21 -> 2889 | F22: Nida Angeles | G22: 100
B23: 05 | D23: =1+D22 -> 2890 | F23: Elmer Buere | G23: 100
B24: 05 | D24: =1+D23 -> 2891 | F24: Aveles family | G24: 150
B25: 05 | D25: =1+D24 -> 2892 | F25: Juvy | G25: 100
B26: 05 | D26: =1+D25 -> 2893 | F26: Eloisa Banog | G26: 100
B27: 05 | D27: =1+D26 -> 2894 | F27: Nani | G27: 100
B28: Sub-Total | G28: =SUM(G20:G27) -> 5750 | I28: =G28-J28 -> 5100 | J28: 650 | K28: 350 | L28: =J28+K28 -> 1000
B29: 12 | D29: 2895 | F29: Dr. Gonzalo | G29: 500 | L29: =J29+K29 -> 0 | M29: christmas envelope | O29: 500
B30: 12 | D30: =1+D29 -> 2896 | F30: Art De Leon | G30: 2000 | L30: =J30+K30 -> 0 | M30: christmas envelope | O30: 2000
B31: 12 | D31: =1+D30 -> 2897 | F31: Mary Ann | G31: 50 | L31: =J31+K31 -> 0
B32: 12 | D32: =1+D31 -> 2898 | F32: Mary Ann | G32: 250 | L32: =J32+K32 -> 0
B33: 12 | D33: =1+D32 -> 2899 | F33: Beng Grafil | G33: 100 | J33: 0 | L33: =J33+K33 -> 0
B34: 15 | D34: =1+D33 -> 2900 | F34: Elmer Buere | G34: 100 | J34: 0 | L34: =J34+K34 -> 0
B35: 15 | D35: =1+D34 -> 2901 | F35: Baby Boris | G35: 200 | L35: =J35+K35 -> 0
B36: 15 | D36: =1+D35 -> 2902 | F36: Eloisa Banog | G36: 100
B37: 15 | D37: =1+D36 -> 2903 | F37: Juvy Mateo | G37: 100 | J37: 0 | L37: =J37+K37 -> 0
B38: Sub-Total | G38: =SUM(G29:G37) -> 3400 | I38: =G38-J38 -> 2400 | J38: 1000 | L38: =J38+K38 -> 1000
B39: 19 | D39: 2904 | F39: Art De Leon & family | G39: 500 | L39: =J39+K39 -> 0
B40: 19 | D40: =1+D39 -> 2905 | F40: Jane Pasamba | G40: 100
B41: 19 | D41: =1+D40 -> 2906 | F41: Lucy | G41: 100
B42: 19 | D42: =1+D41 -> 2907 | F42: Reylyn | G42: 100
B43: 19 | D43: =1+D42 -> 2908 | F43: Beng Grafil | G43: 100
B44: 19 | D44: =1+D43 -> 2909 | F44: Elmer Buere | G44: 100
B45: 19 | D45: =1+D44 -> 2910 | F45: Aveles family | G45: 100
B46: Sub-Total | G46: =SUM(G39:G45) -> 1100 | I46: =G46-J46 -> 100 | J46: 1000 | L46: =J46+K46 -> 1000
B47: 26 | D47: 2911 | F47: Beng Grafil | G47: 100 | L47: =J47+K47 -> 0
B48: 26 | D48: =1+D47 -> 2912 | F48: Irene Masong | G48: 100 | L48: =J48+K48 -> 0
B49: 26 | D49: =1+D48 -> 2913 | F49: Mary Ann | G49: 300
B50: 26 | D50: =1+D49 -> 2914 | F50: Aveles family | G50: 100 | M50: No amount
B51: 26 | F51: No Official Receipt | G51: =4950 -> 4950 | L51: =J51+K51 -> 0 | M51: christmas envelope | O51: 4950
B52: Sub-Total | G52: =SUM(G47:G51) -> 5550 | I52: =G52-J52 -> 4750 | J52: 800 | K52: 200 | L52: =J52+K52 -> 1000
B53: 19 | D53: 2792 | F53: Regine Estrada
B54: 19 | D54: =1+D53 -> 2793 | F54: Elmer Buere
B55: Sub-Total | G55: =SUM(G53:G54) -> 0 | I55: =G55-J55 -> 0
B56: 20 | D56: 2794 | F56: Imelda Torres
B57: 20 | D57: =1+D56 -> 2795 | F57: Gary Mariano
B58: 20 | D58: =1+D57 -> 2796 | F58: Damian Family
B59: 20 | D59: =1+D58 -> 2797 | F59: Jane Pasamba
B60: 20 | D60: =1+D59 -> 2798 | F60: Basilia Family
B61: 20 | D61: =1+D60 -> 2799 | F61: blank | G61: 0
B62: 20 | D62: =1+D61 -> 2800 | F62: Rose Riambon
B63: Sub-Total | G63: =SUM(G56:G62) -> 0 | I63: =G63-J63 -> 0 | J63: 0 | L63: =J63+K63 -> 0
B64: 12 | D64: 2801 | F64: Art De Leon
B65: 13 | D65: =1+D64 -> 2802 | F65: Nida Albato
B66: 14 | D66: =1+D65 -> 2803 | F66: Hilda Villena
B67: 15 | D67: =1+D66 -> 2804 | F67: Melanie Tabuena
B68: 17 | D68: =1+D67 -> 2805 | F68: Fely Rabano
B69: 20 | D69: =1+D68 -> 2806 | F69: Grace Villaresco
B70: 25 | D70: =1+D69 -> 2807 | F70: Rad Saringan
B71: Sub-Total | G71: =SUM(G64:G70) -> 0 | I71: =G71-J71 -> 0 | J71: 0 | L71: =J71+K71 -> 0
B72: Sub-Total | F72: No Official Receipt/Donations from envelopes | I72: =G72-J72 -> 0
B73: TOTAL | G73: =G19+G28+G38+G46+G52 -> 17935 | I73: =I19+I28+I38+I46+I52 -> 12985 | J73: =J19+J28+J38+J46+J52 -> 4950 | K73: =K19+K28+K38+K46+K52 -> 550 | L73: =L19+L28+L38+L46+L52 -> 5500 | O73: =SUM(O11:O52) -> 12450
O74: 12450
B76: Stipend for the month of January 2025
B78: Period covered | F78: Amount
B79: January | C79: 01 | F79: 1500
B80: January | C80: 05 | F80: 1000
B81: January | C81: 12 | F81: 1000
B82: January | C82: 19 | F82: 1000
B83: January | C83: 26 | F83: 1000
B85: Total Stipend | F85: =SUM(F79:F83) -> 5500

Sheet Feb- 2025-FR
C4: Our Lady of the Most Holy Rosary (Sub-Parish)
C5: Diamond Crest Village ,Brgy, San Manuel, San Jose DelMonte City, Bulacan
C7: FINANCIAL REPORT
C8: As of February 28, 2025
C10: Cash Balance as of February 01, 2025 | L10: P | M10: ='Jan-2025-FR'!M54 -> 47581.22
C12: Add: Receipts for the month of February 2025
C14: Mass Collections: | G14: (Net of Stipend)
H16: Collections | I16: Stipend | J16: Others | K16: Net Amount
E18: February | G18: 02 | H18: 1913 | I18: 0 | J18: 0 | K18: =H18-I18-J18 -> 1913
E19: February | G19: 09 | H19: 1671 | I19: 400 | J19: 0 | K19: =H19-I19-J19 -> 1271
E20: February | G20: 16 | H20: 2773 | I20: 350 | J20: 0 | K20: =H20-I20-J20 -> 2423
E21: February | G21: 23 | H21: 1791 | I21: 600 | J21: 0 | K21: =H21-I21-J21 -> 1191
E22: October | G22: 18 | H22: 0 | I22: 0 | J22: 0 | K22: =H22-I22 -> 0
E23: October | G23: 19 | H23: 0 | I23: 0 | J23: 0 | K23: =H23-I23 -> 0
E24: October | G24: 20 | H24: 0 | I24: 0 | J24: 0 | K24: =H24-I24 -> 0
E25: October | G25: 27 | H25: 0 | I25: 0 | J25: 0 | K25: =H25-I25 -> 0 | O25: No mass
E27: Total | H27: =SUM(H18:H25) -> 8148 | I27: =SUM(I18:I25) -> 1350 | J27: =SUM(J18:J25) -> 0 | K27: =SUM(K18:K25) -> 6798 | O27: 7954 | P27: =K27-O27 -> -1156
C31: Donations from Mass Intentions /Pledges: (see Schedule A)
E33: Donations ( net of Stipend ) | K33: ='Feb-2025-Sched A'!I68 -> 6156 | M33: =K33+K27 -> 12954 | O33: 12450
C35: Add: Cash withdrawal
E36: 27 January 2025 | K36: 0
E37: 30 January 2025 | K37: 0 | M37: =SUM(K36:K37) -> 0
C38: Total Cash Available | L38: P | M38: =+M33+M10+M37 -> 60535.22
C41: Less: Expenses for the month of February 2025
C43: Date | E43: PCV # | G43: Particulars | K43: Amount
C45: February 1 | G45: Labor and Materials for Repainting of Chapel Roof | K45: =8170+9030 -> 17200
H46: Labor= 8170.00 + Materials=9030.00
C47: February 1 | G47: Labor and Materials for Repainting of Chapel Roof | K47: =13500+8506 -> 22006
H48: Labor= 13,500.00 + Materials=8,506.00
C49: February 2 | G49: Purchase of Jubilee Parol | K49: 2100
C50: February 10 | G50: Candles for Chapel | K50: 211.65
C51: February 15 | G51: Purcahse of Varnish used for Sto. Entierro Carosa | K51: 4000
C52: February 16 | G52: Purchase of Spotlights at the Altar | K52: 2588.05
C53: February 16 | G53: Labor expenses - installation of spotlights, removal of old signage | K53: 550
C54: February 17 | G54: Labor expenses - replaced damaged faucet and installation of jubilee parol | K54: 500
C55: February 18 | G55: Water Expenses ( Billing period - Dec 11 2024 to Feb 11 2025) ) | K55: 802.16
C56: February 18 | G56: Electricity Expenses ( Meralco Bill - Dec 21 to Jan 21 ) | K56: 862
C57: February 19 | G57: Dry Cleaning expenses | K57: 600
C58: February 21 | G58: Flower Sponsor | K58: 750
C59: February 27 | G59: Food expenses for Father Von's Anniversary | K59: 1187 | M59: =SUM(K45:K59) -> 53356.86
C61: Net of Expenses | M61: =M38-M59 -> 7178.36
C63: Less: Deposits for the month of February 2025 | M63: 0
E64: 06 January 2025 | K64: 0
E65: 06 January 2025 | K65: 0 | M65: =SUM(K64:K65) -> 0 | O65: 12450 | P65: =K65-O65 -> -12450
C67: Cash Balance as of February 28, 2025 | L67: P | M67: =M61-M63 -> 7178.36 | O67: 675.68 | P67: =M67+O67 -> 7854.04 | Q67: =1156+5000 -> 6156 | R67: =P67-Q67 -> 1698.04
C70: Cash in Bank as of January 31, 2025 | L70: P | M70: 22929.54
C72: Add: Deposits | M72: 0
C73: Interest ( Net of witholding tax ) | M73: =2.23-0.45 -> 1.78
C74: Less: Withdrawals ( Jan 27 & 30 ) | M74: 0
C75: Cash in Bank as of February 28, 2025 | L75: P | M75: =SUM(M70:M73)-M74 -> 22931.32
O76: 22929.54 | P76: =M75-O76 -> 1.78
C80: Prepared by: | G80: Checked by: | I80: Audited by: | M80: Noted by:
C82: Elvira Grafil | G82: Fely Rabano | I82: Tina Murla | M82: Lucky Tiu
C83: Asst. Treasurer | G83: Treasurer | I83: Auditor | M83: President

Sheet Feb-2025-Sched A
B2: Schedule A
B7: Our Lady of the Most Holy Rosary (Sub-Parish)
G8: Control File - Receipts
F9: For the month of February 2025
G11: DONATIONS (Mass Intentions:Thanksgiving, Souls, others) | H11: DONATIONS | I11: Net of Donations | J11: STIPEND from | L11: Total Stipend
B12: Date | D12: OR Number | F12: Donor | J12: Donations | K12: Mass Collections
B13: February
B14: 02 | D14: 2915 | F14: Lucy | G14: 100
B15: 02 | D15: =1+D14 -> 2916 | F15: Art De Leon | G15: 200
B16: 02 | D16: =1+D15 -> 2917 | F16: Jane Pasamba | G16: 100
B17: 02 | D17: =1+D15 -> 2917 | F17: Eloisa | G17: 100
F18: No Official Receipt | G18: =500+1156 -> 1656
B19: Sub-Total | G19: =SUM(G14:G18) -> 2156 | I19: =G19-J19 -> 1156 | J19: 1000 | K19: 0 | L19: =J19+K19 -> 1000
B20: 09 | D20: 2919 | F20: Lucy | G20: 100
B21: 09 | D21: =1+D20 -> 2920 | F21: Mary Ann | G21: 200
B22: 09 | D22: =1+D21 -> 2921 | F22: Elmer Buere | G22: 100
B23: 09 | D23: =1+D22 -> 2922 | F23: Nani Domingo | G23: 100
B24: 09 | D24: =1+D23 -> 2923 | F24: Emily | G24: 100
B25: Sub-Total | G25: =SUM(G20:G24) -> 600 | I25: =G25-J25 -> 0 | J25: 600 | K25: 400 | L25: =J25+K25 -> 1000
B26: 16 | D26: 2924 | F26: Jane Pasamba | G26: 100
B27: 16 | D27: =1+D26 -> 2925 | F27: Lucy | G27: 100
B28: 16 | D28: =1+D27 -> 2926 | F28: Elmer Buere | G28: 100
B29: 16 | D29: =1+D28 -> 2927 | F29: Beng Grafil | G29: 100
B30: 16 | D30: =1+D29 -> 2928 | F30: Juvy | G30: 100
B31: 16 | D31: =1+D30 -> 2929 | F31: Susan | G31: 50
B32: 16 | D32: =1+D31 -> 2930 | F32: Mary Ann | G32: 100
B33: Sub-Total | G33: =SUM(G26:G32) -> 650 | I33: =G33-J33 -> 0 | J33: 650 | K33: 350 | L33: =J33+K33 -> 1000
B34: 17 | D34: 2931 | F34: Doc Edwin | G34: 5000
B35: Sub-Total | G35: =G34 -> 5000 | I35: =G35 -> 5000
B36: 24 | D36: 2932 | F36: Elmer Buere | G36: 100
B37: 24 | D37: =1+D36 -> 2933 | F37: Beng Grafil | G37: 100
B38: 24 | D38: =1+D37 -> 2934 | F38: Irene Masong | G38: 100
B39: 24 | D39: =1+D38 -> 2935 | F39: Aveles | G39: 100
B40: Sub-Total | G40: =SUM(G36:G39) -> 400 | I40: =G40-J40 -> 0 | J40: 400 | K40: 600 | L40: =J40+K40 -> 1000
L41: =J41+K41 -> 0
L42: =J42+K42 -> 0
L46: =J46+K46 -> 0
B47: Sub-Total | G47: =SUM(G41:G46) -> 0 | I47: =G47-J47 -> -800 | J47: 800 | K47: 200 | L47: =J47+K47 -> 1000
B48: 19 | D48: 2792 | F48: Regine Estrada
B49: 19 | D49: =1+D48 -> 2793 | F49: Elmer Buere
B50: Sub-Total | G50: =SUM(G48:G49) -> 0 | I50: =G50-J50 -> 0
B51: 20 | D51: 2794 | F51: Imelda Torres
B52: 20 | D52: =1+D51 -> 2795 | F52: Gary Mariano
B53: 20 | D53: =1+D52 -> 2796 | F53: Damian Family
B54: 20 | D54: =1+D53 -> 2797 | F54: Jane Pasamba
B55: 20 | D55: =1+D54 -> 2798 | F55: Basilia Family
B56: 20 | D56: =1+D55 -> 2799 | F56: blank | G56: 0
B57: 20 | D57: =1+D56 -> 2800 | F57: Rose Riambon
B58: Sub-Total | G58: =SUM(G51:G57) -> 0 | I58: =G58-J58 -> 0 | J58: 0 | L58: =J58+K58 -> 0
B59: 12 | D59: 2801 | F59: Art De Leon
B60: 13 | D60: =1+D59 -> 2802 | F60: Nida Albato
B61: 14 | D61: =1+D60 -> 2803 | F61: Hilda Villena
B62: 15 | D62: =1+D61 -> 2804 | F62: Melanie Tabuena
B63: 17 | D63: =1+D62 -> 2805 | F63: Fely Rabano
B64: 20 | D64: =1+D63 -> 2806 | F64: Grace Villaresco
B65: 25 | D65: =1+D64 -> 2807 | F65: Rad Saringan
B66: Sub-Total | G66: =SUM(G59:G65) -> 0 | I66: =G66-J66 -> 0 | J66: 0 | L66: =J66+K66 -> 0
B67: Sub-Total | F67: No Official Receipt/Donations from envelopes | I67: =G67-J67 -> 0
B68: TOTAL | G68: =G19+G25+G33+G35+G40 -> 8806 | I68: =I19+I25+I33+I35+I40 -> 6156 | J68: =J19+J25+J33+J35+J40 -> 2650 | K68: =K19+K25+K33+K35+K40 -> 1350 | L68: =L19+L25+L33+L35+L40 -> 4000
B77: Stipend for the month of February 2025
B79: Period covered | F79: Amount
B80: February | C80: 02 | F80: 1000
B81: February | C81: 09 | F81: 1000
B82: February | C82: 16 | F82: 1000
B83: February | C83: 24 | F83: 1000
B86: Total Stipend | F86: =SUM(F80:F84) -> 4000

Sheet March-2025-FR
C4: Our Lady of the Most Holy Rosary (Sub-Parish)
C5: Diamond Crest Village ,Brgy, San Manuel, San Jose DelMonte City, Bulacan
C7: FINANCIAL REPORT
C8: As of March 31, 2025
C10: Cash Balance as of March 01, 2025 | L10: P | M10: 7178.36
C12: Add: Receipts for the month of March 2025
C14: Mass Collections: | G14: (Net of Stipend)
H16: Collections | I16: Stipend | J16: Others | K16: Net Amount
E18: March | G18: 02 | H18: 1945 | I18: 0 | J18: 0 | K18: =H18-I18-J18 -> 1945
E19: March | G19: 09 | H19: 2421 | I19: 400 | J19: 0 | K19: =H19-I19-J19 -> 2021
E20: March | G20: 16 | H20: 2330 | I20: 400 | J20: 0 | K20: =H20-I20-J20 -> 1930
E26: March | G26: 23 | H26: 1398 | I26: 400 | J26: 0 | K26: =H26-I26-J26 -> 998
E27: March | G27: 30 | H27: 1815 | I27: 550 | J27: 0 | K27: =H27-I27-J27 -> 1265
E28: October | G28: 18 | H28: 0 | I28: 0 | J28: 0 | K28: =H28-I28 -> 0
E29: October | G29: 19 | H29: 0 | I29: 0 | J29: 0 | K29: =H29-I29 -> 0
E30: October | G30: 20 | H30: 0 | I30: 0 | J30: 0 | K30: =H30-I30 -> 0
E31: October | G31: 27 | H31: 0 | I31: 0 | J31: 0 | K31: =H31-I31 -> 0 | O31: No mass
E33: Total | H33: =SUM(H18:H31) -> 9909 | I33: =SUM(I18:I31) -> 1750 | J33: =SUM(J18:J31) -> 0 | K33: =SUM(K18:K31) -> 8159
C37: Donations from Mass Intentions /Pledges: (see Schedule A)
E39: Donations ( net of Stipend ) | K39: 0 | M39: =K39+K33 -> 8159
C41: Add: Cash withdrawal
E42: 27 January 2025 | K42: 0
E43: 30 January 2025 | K43: 0 | M43: =SUM(K42:K43) -> 0
C44: Total Cash Available | L44: P | M44: =+M39+M10+M43 -> 15337.36
C47: Less: Expenses for the month of March 2025
C49: Date | E49: PCV # | G49: Particulars | K49: Amount
C51: March 8 | G51: Purchase of big Jubilee Parol | K51: 500
H52: Labor= 8170.00 + Materials=9030.00
C53: March 8 | G53: Candles for Chapel | K53: 281.2
C54: March 8 | H54: Labor= 13,500.00 + Materials=8,506.00
C55: March 8 | G55: Food expenses ( Snacks for Daan ng Krus ) | K55: 275
C56: March 19 | G56: Water Expenses ( Billing period - Feb11 to March 11 2025) ) | K56: 419.12
C57: March 20 | G57: Food expenses ( Snacks for Daan ng Krus ) | K57: 1347.7
C58: March 21 | G58: Donation for Basic Bible Seminar held at Casa | K58: 1500
C59: March 28 | G59: Labor expenses - replaced damaged faucet and installation of jubilee parol | K59: 0
C60: March 8 | G60: Water Expenses ( Billing period - Dec 11 2024 to Feb 11 2025) ) | K60: 0
C61: February 18 | G61: Electricity Expenses ( Meralco Bill - Dec 21 to Jan 21 ) | K61: 0
C62: February 19 | G62: Dry Cleaning expenses | K62: 0
C63: February 21 | G63: Flower Sponsor | K63: 0
C64: March 28 | G64: Electricity Expenses ( Meralco Bill Share - Jan 19 to Feb 19 2025 ) | K64: 807.3 | M64: =SUM(K51:K64) -> 5130.32
C66: Net of Expenses | M66: =M44-M64 -> 10207.04
C68: Less: Deposits for the month of March 2025 | M68: 7178.36
E69: 06 January 2025 | K69: 0
E70: 06 January 2025 | K70: 0 | M70: =SUM(K69:K70) -> 0 | O70: 12450 | P70: =K70-O70 -> -12450
C72: Cash Balance as of March 31, 2025 | L72: P | M72: =M66-M68 -> 3028.68 | O72: 3028.68 | P72: =M72-O72 -> 8.6401997e-12
C75: Cash in Bank as of February 28, 2025 | L75: P | M75: 22931.32
C77: Add: Deposits | M77: 7178.36
C78: Interest ( Net of witholding tax ) | M78: =2.56-0.51 -> 2.05
C79: Less: Withdrawals ( Jan 27 & 30 ) | M79: 0
C80: Cash in Bank as of March 31, 2025 | L80: P | M80: =SUM(M75:M78)-M79 -> 30111.73
C85: Prepared by: | G85: Checked by: | I85: Audited by: | M85: Noted by:
C87: Elvira Grafil | G87: Fely Rabano | I87: Tina Murla | M87: Lucky Tiu
C88: Asst. Treasurer | G88: Treasurer | I88: Auditor | M88: President

Sheet Mar 2025 Sched A
B2: Schedule A
B7: Our Lady of the Most Holy Rosary (Sub-Parish)
G8: Control File - Receipts
F9: For the month of March 2025
G11: DONATIONS (Mass Intentions:Thanksgiving, Souls, others) | H11: DONATIONS | I11: Net of Donations | J11: STIPEND from | L11: Total Stipend
B12: Date | D12: OR Number | F12: Donor | J12: Donations | K12: Mass Collections
B13: March
B14: 02 | D14: 2936 | F14: Lucy Saramosing | G14: 100
B15: 02 | D15: =1+D14 -> 2937 | F15: Gina Albarido | G15: 100
B16: 02 | D16: =1+D15 -> 2938 | F16: Beng Grafil | G16: 100
B17: 02 | D17: =1+D16 -> 2939 | F17: Jane Pasamba | G17: 100
B18: 02 | D18: =1+D17 -> 2940 | F18: Susan Chua | G18: 50
B19: 02 | D19: =1+D18 -> 2941 | F19: Alyssa Aviles | G19: 100
B20: 02 | D20: =1+D19 -> 2942 | F20: Irene Masong | G20: 100
B21: 02 | D21: =1+D20 -> 2943 | F21: Tina Murla | G21: 350
B22: Sub-Total | G22: =SUM(G14:G21) -> 1000 | I22: =G22-J22 -> 0 | J22: 1000 | K22: 0 | L22: =J22+K22 -> 1000
B23: 09 | D23: 2944 | F23: Cancelled | G23: 0
B24: 09 | D24: =1+D23 -> 2945 | F24: Lara Family | G24: 100
B25: 09 | D25: =1+D24 -> 2946 | F25: Elmer Buere | G25: 100
B26: 09 | D26: =1+D25 -> 2947 | F26: Lucy Saramosing | G26: 100
B27: 09 | D27: =1+D26 -> 2948 | F27: Beng Grafil | G27: 100
B28: 09 | D28: =1+D27 -> 2949 | F28: Calonge Family | G28: 100
B29: 09 | D29: =1+D28 -> 2950 | F29: Aviles Family | G29: 100
B30: Sub-Total | G30: =SUM(G23:G29) -> 600 | I30: =G30-J30 -> 0 | J30: 600 | K30: 400 | L30: =J30+K30 -> 1000
B31: 16 | D31: 2951 | F31: Beng Grafil | G31: 100
B32: 16 | D32: =1+D31 -> 2952 | F32: Jane Pasamba | G32: 100
B33: 16 | D33: =1+D32 -> 2953 | F33: Gina Albarido | G33: 100
B34: 16 | D34: =1+D33 -> 2954 | F34: Thelma Lara | G34: 50
B35: 16 | D35: =1+D34 -> 2955 | F35: Elmer Buere | G35: 100
B36: 16 | D36: =1+D35 -> 2956 | F36: Mary Ann Padua | G36: 50
B37: 16 | F37: No Official Receipt | G37: 100
B38: Sub-Total | G38: =SUM(G31:G37) -> 600 | I38: =G38-J38 -> 0 | J38: 600 | K38: 400 | L38: =J38+K38 -> 1000
B39: 23 | D39: 2957 | F39: Lucy Saramosing | G39: 100
B40: 23 | D40: =1+D39 -> 2958 | F40: Irene Masong | G40: 100
B41: 23 | D41: =1+D40 -> 2959 | F41: Elmer Buere | G41: 100
B42: 23 | D42: =1+D41 -> 2960 | F42: Lorie | G42: 100
B43: 23 | D43: =1+D42 -> 2961 | F43: Gina Albarido | G43: 100
B44: 23 | D44: =1+D43 -> 2962 | F44: Aviles Family | G44: 100
B45: Sub-Total | G45: =SUM(G39:G44) -> 600 | I45: =G45-J45 -> 0 | J45: 600 | K45: 400 | L45: =J45+K45 -> 1000
B46: 30 | D46: 2963 | F46: Ebon | G46: 100 | L46: =J46+K46 -> 0
B47: 30 | D47: =1+D46 -> 2964 | F47: Elmer Buere | G47: 100 | L47: =J47+K47 -> 0
B48: 30 | D48: =1+D47 -> 2965 | F48: Aviles Family | G48: 100
B49: 30 | D49: =1+D48 -> 2966 | F49: Relyn Calonge | G49: 100
B50: 30 | D50: =1+D49 -> 2967 | F50: Mary Ann Padua | G50: 50
B51: Sub-Total | G51: =SUM(G46:G50) -> 450 | J51: 450 | K51: 550 | L51: =J51+K51 -> 1000
B52: TOTAL | G52: =G51+G45+G38+G30+G22 -> 3250 | I52: =I51+I45+I38+I30+I22 -> 0 | J52: =J51+J45+J38+J30+J22 -> 3250 | K52: =K51+K45+K38+K30+K22 -> 1750 | L52: =L51+L45+L38+L30+L22 -> 5000
B61: Stipend for the month of March 2025
B63: Period covered | F63: Amount
B64: March | C64: 02 | F64: 1000
B65: March | C65: 09 | F65: 1000
B66: March | C66: 16 | F66: 1000
B67: March | C67: 23 | F67: 1000
B68: March | C68: 30 | F68: 1000
B70: Total Stipend | F70: =SUM(F64:F68) -> 5000

Sheet Apr-2025-FR
C4: Our Lady of the Most Holy Rosary (Sub-Parish)
C5: Diamond Crest Village ,Brgy, San Manuel, San Jose DelMonte City, Bulacan
C7: FINANCIAL REPORT
C8: As of April 30, 2025
C10: Cash Balance as of April 01, 2025 | L10: P | M10: 3028.68
C12: Add: Receipts for the month of April 2025
C14: Mass Collections: | G14: (Net of Stipend)
H16: Collections | I16: Stipend | J16: Others | K16: Net Amount
E18: April | G18: 06 | H18: 1808 | I18: 300 | J18: 0 | K18: =H18-I18-J18 -> 1508
E19: April | G19: 20 | H19: 55 | I19: 0 | J19: 0 | K19: =H19-I19-J19 -> 55
E20: April | G20: 27 | H20: 1433 | I20: 350 | J20: 0 | K20: =H20-I20-J20 -> 1083
H26: 0 | I26: 0 | J26: 0 | K26: =H26-I26-J26 -> 0
H27: 0 | I27: 0 | J27: 0 | K27: =H27-I27-J27 -> 0
E28: October | G28: 18 | H28: 0 | I28: 0 | J28: 0 | K28: =H28-I28 -> 0
E29: October | G29: 19 | H29: 0 | I29: 0 | J29: 0 | K29: =H29-I29 -> 0
E30: October | G30: 20 | H30: 0 | I30: 0 | J30: 0 | K30: =H30-I30 -> 0
E31: October | G31: 27 | H31: 0 | I31: 0 | J31: 0 | K31: =H31-I31 -> 0 | O31: No mass
E33: Total | H33: =SUM(H18:H31) -> 3296 | I33: =SUM(I18:I31) -> 650 | J33: =SUM(J18:J31) -> 0 | K33: =SUM(K18:K31) -> 2646
C37: Donations from Mass Intentions /Pledges: (see Schedule A)
E39: Donations ( net of Stipend ) | K39: ='Apr 2025 Sched A'!I49 -> 0
C41: Donations ( Alay Kapwa Envelopes ) | K41: 15400 | M41: =SUM(K33:K41) -> 18046
C44: Total Cash Available | L44: P | M44: =M10+M41 -> 21074.68
C47: Less: Expenses for the month of April 2025
C49: Date | E49: PCV # | G49: Particulars | K49: Amount
C51: April 4 | G51: Plumbing Repairs/Materials | K51: 693
H52: Labor= 8170.00 + Materials=9030.00
C53: April 13 | G53: DCV-SPPC Sponsor at SLRP( Ibon & Wine ) | K53: 1400
C54: April 4 | H54: Labor= 13,500.00 + Materials=8,506.00
C55: April 14 | G55: Expenses for Chrism Mass at Malolos by DCV-SPPC representative | K55: 1300
C56: April 14 | G56: Pabasa & Vigil Expenses ( Coffee, etc.) | K56: 430.55
C57: April 16 | G57: Water Expenses ( Billing period - March 11 to April 11 2025) ) | K57: 400
C58: April 19 | G58: DCV-SPPC Sponsor at SLRP Sabado De Gloria ( Pancit Bilao ) | K58: 1500
C59: April 16 | G59: Labor expenses - replaced damaged faucet and installation of jubilee parol | K59: 0
C60: April 16 | G60: Water Expenses ( Billing period - Dec 11 2024 to Feb 11 2025) ) | K60: 0
C61: April 16 | G61: Electricity Expenses ( Meralco Bill - Dec 21 to Jan 21 ) | K61: 0
C62: April 16 | G62: Dry Cleaning expenses | K62: 0
C63: April 16 | G63: Flower Sponsor | K63: 0
C64: April 24 | G64: Electricity Expenses ( Meralco Bill Share - Feb 20 to March 19 2025 ) | K64: 625
G65: Altar Table ( worth 5000 less 2000 - (donation from Ate Tina )) | K65: 3000
C66: April 24 | G66: Financial Assistance (for Lucky's hospitalization) | K66: 2000 | M66: =SUM(K51:K66) -> 11348.55
C68: Net of Expenses | M68: =M44-M66 -> 9726.13
C70: Less: Deposits for the month of April 2025 | M70: 0
E71: 06 January 2025 | K71: 0
E72: 06 January 2025 | K72: 0 | M72: =SUM(K71:K72) -> 0 | O72: 12450 | P72: =K72-O72 -> -12450
C74: Cash Balance as of April 30, 2025 | L74: P | M74: =M68-M70 -> 9726.13 | O74: 3028.68 | P74: =M74-6697.45 -> 3028.68 | Q74: =O74-P74 -> -8.6401997e-12
C77: Cash in Bank as of March 31, 2025 | L77: P | M77: 30111.73
C79: Add: Deposits | M79: 0
C80: Interest ( Net of witholding tax ) | M80: =3.14-0.63 -> 2.51
C81: Less: Withdrawals ( Jan 27 & 30 ) | M81: 0
C82: Cash in Bank as of April 30, 2025 | L82: P | M82: =SUM(M77:M80)-M81 -> 30114.24
C87: Prepared by: | G87: Checked by: | I87: Audited by: | M87: Noted by:
C89: Elvira Grafil | G89: Fely Rabano | I89: Tina Murla | M89: Lucky Tiu
C90: Asst. Treasurer | G90: Treasurer | I90: Auditor | M90: President

Sheet Apr 2025 Sched A
B2: Schedule A
B7: Our Lady of the Most Holy Rosary (Sub-Parish)
G8: Control File - Receipts
F9: For the month of April 2025
G11: DONATIONS (Mass Intentions:Thanksgiving, Souls, others) | H11: DONATIONS | I11: Net of Donations | J11: STIPEND from | L11: Total Stipend
B12: Date | D12: OR Number | F12: Donor | J12: Donations | K12: Mass Collections
B13: April
B14: 06 | D14: 2968 | F14: Lucy Saramosing | G14: 150
B15: 06 | D15: =1+D14 -> 2969 | F15: Elmer Buere & family | G15: 100
B16: 06 | D16: =1+D15 -> 2970 | F16: Gina Albarido & family | G16: 100
B17: 06 | D17: =1+D15 -> 2970 | F17: Mary Ann Padua | G17: 100
B18: 06 | F18: No Official Receipt | G18: 250
B19: Sub-Total | G19: =SUM(G14:G18) -> 700 | I19: =G19-J19 -> 0 | J19: 700 | K19: 300 | L19: =J19+K19 -> 1000
B20: 20 | D20: 2972 | F20: Beng Grafil | G20: 100
B21: 20 | D21: =1+D20 -> 2973 | F21: Gina Albarido | G21: 100
B22: 20 | D22: =1+D21 -> 2974 | F22: Lucy Saramosing | G22: 100
B23: 20 | D23: =1+D22 -> 2975 | F23: Elmer Buere | G23: 100
B24: 20 | F24: No Official Receipt | G24: 600
G25: 0
G26: 0
G27: 0
B28: Sub-Total | G28: =SUM(G20:G27) -> 1000 | I28: =G28-J28 -> 0 | J28: 1000 | K28: 0 | L28: =J28+K28 -> 1000
B29: 27 | D29: 2976 | F29: Elmer Buere | G29: 100
B30: 27 | D30: =1+D29 -> 2977 | F30: Lucy Saramosing | G30: 100
B31: 27 | D31: =1+D30 -> 2978 | F31: Aviles Family | G31: 100
B32: 27 | D32: =1+D31 -> 2979 | F32: Victor Palan | G32: 100
B33: 27 | D33: =1+D32 -> 2980 | F33: Mary Ann Padua | G33: 200
B34: 27 | D34: =1+D33 -> 2981 | F34: Ris Centeno | G34: 50
B35: Sub-Total | G35: =SUM(G29:G34) -> 650 | I35: =G35-J35 -> 0 | J35: 650 | K35: 350 | L35: =J35+K35 -> 1000
B36: 23 | D36: 2957 | F36: Lucy Saramosing
B37: 23 | D37: =1+D36 -> 2958 | F37: Irene Masong
B38: 23 | D38: =1+D37 -> 2959 | F38: Elmer Buere
B39: 23 | D39: =1+D38 -> 2960 | F39: Lorie
B40: 23 | D40: =1+D39 -> 2961 | F40: Gina Albarido
B41: 23 | D41: =1+D40 -> 2962 | F41: Aviles Family
B42: Sub-Total | G42: =SUM(G36:G41) -> 0 | I42: =G42-J42 -> 0 | J42: 0 | K42: 0 | L42: =J42+K42 -> 0
B43: 30 | D43: 2963 | F43: Ebon | L43: =J43+K43 -> 0
B44: 30 | D44: =1+D43 -> 2964 | F44: Elmer Buere | L44: =J44+K44 -> 0
B45: 30 | D45: =1+D44 -> 2965 | F45: Aviles Family
B46: 30 | D46: =1+D45 -> 2966 | F46: Relyn Calonge
B47: 30 | D47: =1+D46 -> 2967 | F47: Mary Ann Padua
B48: Sub-Total | G48: =SUM(G43:G47) -> 0 | J48: 0 | K48: 0 | L48: =J48+K48 -> 0
B49: TOTAL | G49: =G48+G42+G35+G28+G19 -> 2350 | I49: =I48+I42+I35+I28+I19 -> 0 | J49: =J48+J42+J35+J28+J19 -> 2350 | K49: =K48+K42+K35+K28+K19 -> 650 | L49: =L48+L42+L35+L28+L19 -> 3000
B58: Stipend for the month of April 2025
B60: Period covered | F60: Amount
B61: April | C61: 06 | F61: 1000
B62: April | C62: 20 | F62: 1000
B63: April | C63: 27 | F63: 1000
B67: Total Stipend | F67: =SUM(F61:F65) -> 3000

Sheet May-2025-FR
C4: Our Lady of the Most Holy Rosary (Sub-Parish)
C5: Diamond Crest Village ,Brgy, San Manuel, San Jose DelMonte City, Bulacan
C7: FINANCIAL REPORT
C8: As of May 31, 2025
C10: Cash Balance as of May 01, 2025 | L10: P | M10: 9726.13
C12: Add: Receipts for the month of May 2025
C14: Mass Collections: | G14: (Net of Stipend)
H16: Collections | I16: Stipend | J16: Others | K16: Net Amount
E18: May | G18: 04 | H18: 1294 | I18: 200 | J18: 0 | K18: =H18-I18-J18 -> 1094
E19: May | G19: 11 | H19: =1841-71-100 -> 1670 | I19: 200 | J19: 100 | K19: =H19-I19-J19 -> 1370 | O19: =3522-3693 -> -171 | P19: uncollected
E20: May | G20: 25 | H20: 1558 | I20: 500 | J20: 0 | K20: =H20-I20-J20 -> 1058
H26: 0 | I26: 0 | J26: 0 | K26: =H26-I26-J26 -> 0
H27: 0 | I27: 0 | J27: 0 | K27: =H27-I27-J27 -> 0
E28: October | G28: 18 | H28: 0 | I28: 0 | J28: 0 | K28: =H28-I28 -> 0
E29: October | G29: 19 | H29: 0 | I29: 0 | J29: 0 | K29: =H29-I29 -> 0
E30: October | G30: 20 | H30: 0 | I30: 0 | J30: 0 | K30: =H30-I30 -> 0
E31: October | G31: 27 | H31: 0 | I31: 0 | J31: 0 | K31: =H31-I31 -> 0 | O31: No mass
E33: Total | H33: =SUM(H18:H31) -> 4522 | I33: =SUM(I18:I31) -> 900 | J33: =SUM(J18:J31) -> 100 | K33: =SUM(K18:K31) -> 3522 | O33: 3522 | P33: =K33-O33 -> 0
C37: Donations from Mass Intentions /Pledges: (see Schedule A)
E39: Donations ( net of Stipend ) | K39: ='May 2025 Sched A'!I54 -> 0
C41: Donations ( Alay Kapwa Envelopes ) | K41: 0 | M41: =SUM(K33:K41) -> 3522
C44: Total Cash Available | L44: P | M44: =M10+M41 -> 13248.13
C47: Less: Expenses for the month of May 2025
C49: Date | E49: PCV # | G49: Particulars | K49: Amount
C51: May 14 | G51: Food Sponsor ( Estasyon ng Muling Pagkabuhay) | K51: 3197.45
H52: Labor= 8170.00 + Materials=9030.00
C53: May 19 | G53: Electricity Expenses ( Meralco Bill Share - March 21 20 to April 20 2025 ) | K53: 1071.35
C54: May 14 | H54: Labor= 13,500.00 + Materials=8,506.00
C55: May 20 | G55: Water Expenses ( Billing period - April 11 to May 11 2025) ) | K55: 300
C56: May 20 | G56: DCV - SPPC Mass Sponsor - Novenario at SLRP | K56: 1500 | M56: =SUM(K51:K56) -> 6068.8
K57: 0
K58: 0
K59: 0
K60: 0
K61: 0
K62: 0
K63: 0
K64: 0
K65: 0
C68: Net of Expenses | M68: =M44-M56 -> 7179.33
C70: Less: Deposits for the month of May 2025 | M70: 3028.68
E71: 06 January 2025 | K71: 0
E72: 06 January 2025 | K72: 0 | M72: =SUM(K71:K72) -> 0 | O72: 12450 | P72: =K72-O72 -> -12450
C74: Cash Balance as of May 31, 2025 | L74: P | M74: =M68-M70 -> 4150.65 | O74: 4150.65 | P74: =M74-O74 -> 9.094947e-12
P75: 171 | Q75: excess ( collections )
P76: 100 | Q76: excess ( donations )
C77: Cash in Bank as of April 30, 2025 | L77: P | M77: 30114.24
C79: Add: Deposits | M79: 3028.68
C80: Interest ( Net of witholding tax ) | M80: =3.48-0.7 -> 2.78
C81: Less: Withdrawals ( Jan 27 & 30 ) | M81: 0
C82: Cash in Bank as of May 31, 2025 | L82: P | M82: =SUM(M77:M80)-M81 -> 33145.7
C87: Prepared by: | G87: Checked by: | I87: Audited by: | M87: Noted by:
C89: Elvira Grafil | G89: Fely Rabano | I89: Tina Murla | M89: Lucky Tiu
C90: Asst. Treasurer | G90: Treasurer | I90: Auditor | M90: President

Sheet May 2025 Sched A
B2: Schedule A
B7: Our Lady of the Most Holy Rosary (Sub-Parish)
G8: Control File - Receipts
F9: For the month of May 2025
G11: DONATIONS (Mass Intentions:Thanksgiving, Souls, others) | H11: DONATIONS | I11: Net of Donations | J11: STIPEND from | L11: Total Stipend
B12: Date | D12: OR Number | F12: Donor | J12: Donations | K12: Mass Collections
B13: May
B14: 04 | D14: 2982 | F14: Gina Albarido | G14: 100
B15: 04 | D15: =1+D14 -> 2983 | F15: Jane Pasamba | G15: 100
B16: 04 | D16: =1+D15 -> 2984 | F16: Elmer Buere | G16: 100
B17: 04 | D17: =1+D16 -> 2985 | F17: Calonge Family | G17: 100
B18: 04 | D18: =1+D17 -> 2986 | F18: Beng Grafil | G18: 100
B19: 04 | D19: =1+D18 -> 2987 | F19: Mary Ann | G19: 100
B20: 04 | D20: =1+D19 -> 2988 | F20: Irene Masong | G20: 100
B21: 04 | D21: =1+D20 -> 2989 | F21: Aviles Family | G21: 100
B22: Sub-Total | G22: =SUM(G14:G21) -> 800 | I22: =G22-J22 -> 0 | J22: 800 | K22: 200 | L22: =J22+K22 -> 1000
B23: 11 | D23: 2990 | F23: Lucy Saramosing | G23: 100
B24: 11 | D24: =1+D23 -> 2991 | F24: Gina Albarido | G24: 100
B25: 11 | D25: =1+D24 -> 2992 | F25: Lorie | G25: 100
B26: 11 | D26: =1+D25 -> 2993 | F26: Regie Estrada | G26: 100
B27: 11 | D27: =1+D26 -> 2994 | F27: Aviles Family | G27: 100
B28: 11 | D28: =1+D27 -> 2995 | F28: Irene Masong | G28: 100
B29: 11 | D29: =1+D28 -> 2996 | F29: Elmer Buere | G29: 100
B30: 11 | D30: =1+D29 -> 2997 | F30: Baby | G30: 100
G31: 0
G32: 0
G33: 0
B34: Sub-Total | G34: =SUM(G23:G33) -> 800 | I34: =G34-J34 -> 0 | J34: 800 | K34: 200 | L34: =J34+K34 -> 1000
B35: 25 | D35: 2998 | F35: Gina Albarido | G35: 100
B36: 25 | D36: =1+D35 -> 2999 | F36: Beng Grafil | G36: 100
B37: 25 | D37: =1+D36 -> 3000 | F37: Elmer Buere | G37: 100
B38: 25 | D38: =1+D37 -> 3001 | F38: Jane Pasamba | G38: 100
B39: 25 | D39: =1+D38 -> 3002 | F39: Baby | G39: 100
B40: Sub-Total | G40: =SUM(G35:G39) -> 500 | I40: =G40-J40 -> 0 | J40: 500 | K40: 500 | L40: =J40+K40 -> 1000
B47: Sub-Total | G47: =SUM(G41:G46) -> 0 | I47: =G47-J47 -> 0 | J47: 0 | K47: 0 | L47: =J47+K47 -> 0
B48: 30 | D48: 2963 | F48: Ebon | L48: =J48+K48 -> 0
B49: 30 | D49: =1+D48 -> 2964 | F49: Elmer Buere | L49: =J49+K49 -> 0
B50: 30 | D50: =1+D49 -> 2965 | F50: Aviles Family
B51: 30 | D51: =1+D50 -> 2966 | F51: Relyn Calonge
B52: 30 | D52: =1+D51 -> 2967 | F52: Mary Ann Padua
B53: Sub-Total | G53: =SUM(G48:G52) -> 0 | J53: 0 | K53: 0 | L53: =J53+K53 -> 0
B54: TOTAL | G54: =G53+G47+G40+G34+G22 -> 2100 | I54: =I53+I47+I40+I34+I22 -> 0 | J54: =J53+J47+J40+J34+J22 -> 2100 | K54: =K53+K47+K40+K34+K22 -> 900 | L54: =L53+L47+L40+L34+L22 -> 3000
B63: Stipend for the month of April 2025
B65: Period covered | F65: Amount
B66: May | C66: 04 | F66: 1000
B67: May | C67: 11 | F67: 1000
B68: May | C68: 25 | F68: 1000
B72: Total Stipend | F72: =SUM(F66:F70) -> 3000

Sheet Jun 2025 FR
C4: Our Lady of the Most Holy Rosary (Sub-Parish)
C5: Diamond Crest Village ,Brgy, San Manuel, San Jose DelMonte City, Bulacan
C7: FINANCIAL REPORT
C8: As of June 30, 2025
C10: Cash Balance as of June 01, 2025 | L10: P | M10: 4150.65
C12: Add: Receipts for the month of June 2025
C14: Mass Collections: | G14: (Net of Stipend)
H16: Collections | I16: Stipend | J16: Others | K16: Net Amount
E18: June | G18: 01 | H18: 1603 | I18: 600 | J18: 0 | K18: =H18-I18-J18 -> 1003
E19: June | G19: 08 | H19: 1316 | I19: 400 | K19: =H19-I19-J19 -> 916
E20: June | G20: 15 | H20: 1530 | I20: 300 | K20: =H20-I20-J20 -> 1230
E21: June | G21: 22 | H21: 1162 | I21: 150 | J21: 0 | K21: =H21-I21-J21 -> 1012
E22: June | G22: 29 | H22: 1758 | I22: 0 | J22: 0 | K22: =H22-I22-J22 -> 1758
H28: 0 | I28: 0 | J28: 0 | K28: =H28-I28-J28 -> 0
H29: 0 | I29: 0 | J29: 0 | K29: =H29-I29-J29 -> 0
E30: October | G30: 18 | H30: 0 | I30: 0 | J30: 0 | K30: =H30-I30 -> 0
E31: October | G31: 19 | H31: 0 | I31: 0 | J31: 0 | K31: =H31-I31 -> 0
E32: October | G32: 20 | H32: 0 | I32: 0 | J32: 0 | K32: =H32-I32 -> 0
E33: October | G33: 27 | H33: 0 | I33: 0 | J33: 0 | K33: =H33-I33 -> 0 | O33: No mass
E35: Total | H35: =SUM(H18:H33) -> 7369 | I35: =SUM(I18:I33) -> 1450 | J35: =SUM(J18:J33) -> 0 | K35: =SUM(K18:K33) -> 5919 | O35: =K35-M57 -> 3257.1
C38: Donations from Mass Intentions /Pledges: (see Schedule A)
E40: Donations ( net of Stipend ) | K40: 0 | M40: =SUM(K33:K40) -> 5919
C42: Donations ( Alay Kapwa Envelopes ) | K42: 0 | M42: =SUM(K35:K42) -> 5919
C44: Total Cash Available | L44: P | M44: =M10+M40 -> 10069.65
C47: Less: Expenses for the month of June 2025
C49: Date | E49: PCV # | G49: Particulars | K49: Amount
C51: June 15 | G51: Flower Sponsor ( DCV-SPPC) | K51: 750
H52: Labor= 8170.00 + Materials=9030.00
C53: June 17 | G53: Water Expenses ( Billing period - May 11 to June 11 2025) ) | K53: 303.6
C54: June 14 | H54: Labor= 13,500.00 + Materials=8,506.00
C55: June 22 | G55: Flower Sponsor for the Feast of Corpus Christi | K55: 1000
C56: June 24 | G56: Electricity Expenses ( Meralco Bill Share - April 21 20 to May 20 2025 ) | K56: 484.3
C57: June 27 | G57: Purchase of battery for wireless microphones | K57: 124 | M57: =SUM(K51:K57) -> 2661.9
K58: 0
K59: 0
K60: 0
K61: 0
K62: 0
K63: 0
K64: 0
K65: 0
K66: 0
C68: Net of Expenses | M68: =M44-M57 -> 7407.75
C70: Less: Deposits for the month of June 2025 | M70: 0
E71: 06 January 2025 | K71: 0
E72: 06 January 2025 | K72: 0 | M72: =SUM(K71:K72) -> 0 | O72: 12450 | P72: =K72-O72 -> -12450
C74: Cash Balance as of June 30, 2025 | L74: P | M74: =M68-M70 -> 7407.75 | O74: 0
C77: Cash in Bank as of May 31, 2025 | L77: P | M77: 33145.7
C79: Add: Deposits | M79: 0
C80: Interest ( Net of witholding tax ) | M80: 2.75
C81: Less: Withdrawals ( Jan 27 & 30 ) | M81: 0
C82: Cash in Bank as of June 30, 2025 | L82: P | M82: =SUM(M77:M80)-M81 -> 33148.45
C87: Prepared by: | G87: Checked by: | I87: Audited by: | M87: Noted by:
C89: Elvira Grafil | G89: Fely Rabano | I89: Tina Murla | M89: Lucky Tiu
C90: Asst. Treasurer | G90: Treasurer | I90: Auditor | M90: President

Sheet June 2025 Sched A
B1: Schedule A
B3: Our Lady of the Most Holy Rosary (Sub-Parish)
G4: Control File - Receipts
F5: For the month of June 2025
G7: DONATIONS (Mass Intentions:Thanksgiving, Souls, others) | H7: DONATIONS | I7: Net of Donations | J7: STIPEND from | L7: Total Stipend
B8: Date | D8: OR Number | F8: Donor | J8: Donations | K8: Mass Collections
B9: June
B10: 01 | D10: 3003 | F10: Mrs. Molina | G10: 100
B11: 01 | D11: =1+D10 -> 3004 | F11: Beng Grafil | G11: 100
B12: 01 | D12: =1+D11 -> 3005 | F12: Irene Masong | G12: 100
B13: 01 | D13: =1+D12 -> 3006 | F13: Baby | G13: 100
B14: Sub-Total | G14: =SUM(G10:G13) -> 400 | I14: =G14-J14 -> 0 | J14: 400 | K14: 600 | L14: =J14+K14 -> 1000
B15: 08 | D15: 3007 | F15: Lucy Saramosing | G15: 100
B16: 08 | D16: =1+D15 -> 3008 | F16: Beng Grafil | G16: 100
B17: 08 | D17: =1+D16 -> 3009 | F17: Jane Pasamba | G17: 100
B18: 08 | D18: =1+D17 -> 3010 | F18: Elmer Buere | G18: 100
B19: 08 | D19: =1+D18 -> 3011 | F19: Mrs. Molina | G19: 100
B20: 08 | D20: =1+D19 -> 3012 | F20: Irene Masong | G20: 100
B21: 08 | D21: =1+D20 -> 3013 | F21: Relyn Calonge | G21: 100
G22: 0
G23: 0
G24: 0
B25: Sub-Total | G25: =SUM(G15:G24) -> 700 | I25: =G25-J25 -> 100 | J25: 600 | K25: 400 | L25: =J25+K25 -> 1000
B26: 15 | D26: 3014 | F26: Lucy Saramosing | G26: 100
B27: 15 | D27: =1+D26 -> 3015 | F27: Beng Grafil | G27: 100
B28: 15 | D28: =1+D27 -> 3016 | F28: Elmer Buere | G28: 100
B29: 15 | D29: =1+D28 -> 3017 | F29: Mrs. Molina | G29: 100
B30: 15 | D30: =1+D29 -> 3018 | F30: Gina Albarido | G30: 100
B31: 15 | D31: =1+D30 -> 3019 | F31: Mrs. Molina | G31: 100
B32: 15 | D32: =1+D31 -> 3020 | F32: Aviles Family | G32: 100
B33: Sub-Total | G33: =SUM(G26:G32) -> 700 | I33: =G33-J33 -> 0 | J33: 700 | K33: 300 | L33: =J33+K33 -> 1000
B34: 22 | D34: 3021 | F34: Edna | G34: 100
B35: 22 | D35: =1+D34 -> 3022 | F35: Beng Grafil | G35: 100
B36: 22 | D36: =1+D35 -> 3023 | F36: Susan | G36: 100
B37: 22 | D37: =1+D36 -> 3024 | F37: Susan | G37: 50
B38: 22 | D38: =1+D37 -> 3025 | F38: Elmer Buere | G38: 100
B39: 22 | D39: =1+D38 -> 3026 | F39: Gina Albarido | G39: 100
B40: 22 | D40: =1+D39 -> 3027 | F40: Aviles Family | G40: 100
B41: 22 | D41: =1+D40 -> 3028 | F41: Baby | G41: 100
B42: 22 | D42: =1+D41 -> 3029 | F42: Jane | G42: 100
B43: Sub-Total | G43: =SUM(G34:G42) -> 850 | I43: =G43-J43 -> 0 | J43: 850 | K43: 150 | L43: =J43+K43 -> 1000
B44: 29 | D44: 3030 | F44: Eloi Banog | G44: 100 | L44: =J44+K44 -> 0
B45: 29 | D45: =1+D44 -> 3031 | F45: Beng Grafil | G45: 100 | L45: =J45+K45 -> 0
B46: 29 | D46: =1+D45 -> 3032 | F46: Lucy Saramosing | G46: 100
B47: 29 | D47: =1+D46 -> 3033 | F47: Aviles Family | G47: 100
B48: 29 | D48: =1+D47 -> 3034 | F48: Abad Family | G48: 100
B49: 29 | D49: =1+D48 -> 3035 | F49: Jane Pasamba | G49: 100
B50: 29 | D50: =1+D49 -> 3036 | F50: Elmer Buere | G50: 100
B51: 29 | D51: 0 | F51: No Receipt | G51: 200
B52: Sub-Total | G52: =SUM(G44:G51) -> 900 | I52: =G52-J52 -> -100 | J52: 1000 | K52: 0 | L52: =J52+K52 -> 1000
B53: TOTAL | G53: =G52+G43+G33+G25+G14 -> 3550 | I53: =I52+I43+I33+I25+I14 -> 0 | J53: =J52+J43+J33+J25+J14 -> 3550 | K53: =K52+K43+K33+K25+K14 -> 1450 | L53: =L52+L43+L33+L25+L14 -> 5000
B56: Stipend for the month of June 2025
B58: Period covered | F58: Amount
B59: June | C59: 01 | F59: 1000
B60: June | C60: 08 | F60: 1000
B61: June | C61: 15 | F61: 1000
B62: May | C62: 22 | F62: 1000
B63: June | C63: 29 | F63: 1000
B67: Total Stipend | F67: =SUM(F59:F65) -> 5000

Sheet July 2025 FR
C3: Our Lady of the Most Holy Rosary (Sub-Parish)
C4: Diamond Crest Village , Brgy, San Manuel, San Jose DelMonte City, Bulacan
C6: FINANCIAL REPORT
C7: As of July 31, 2025
C9: Cash Balance as of July01 , 2025 | L9: P | M9: 7407.75
C11: Add: Receipts for the month of July 2025
C13: Mass Collections: | G13: (Net of Stipend)
H15: Collections | I15: Stipend | J15: Others | K15: Net Amount
E17: July | G17: 06 | H17: 1783 | I17: 200 | J17: 0 | K17: =H17-I17-J17 -> 1583
E18: July | G18: 13 | H18: 1952 | I18: 400 | K18: =H18-I18-J18 -> 1552
E19: July | G19: 20 | H19: 1713 | I19: 400 | K19: =H19-I19-J19 -> 1313
E20: July | G20: 27 | H20: 1819 | I20: 400 | J20: 0 | K20: =H20-I20-J20 -> 1419
H26: 0 | I26: 0 | J26: 0 | K26: =H26-I26-J26 -> 0
H27: 0 | I27: 0 | J27: 0 | K27: =H27-I27-J27 -> 0
E28: October | G28: 18 | H28: 0 | I28: 0 | J28: 0 | K28: =H28-I28 -> 0
E29: October | G29: 19 | H29: 0 | I29: 0 | J29: 0 | K29: =H29-I29 -> 0
E30: October | G30: 20 | H30: 0 | I30: 0 | J30: 0 | K30: =H30-I30 -> 0
E31: October | G31: 27 | H31: 0 | I31: 0 | J31: 0 | K31: =H31-I31 -> 0 | O31: No mass
E33: Total | H33: =SUM(H17:H31) -> 7267 | I33: =SUM(I17:I31) -> 1400 | J33: =SUM(J17:J31) -> 0 | K33: =SUM(K17:K31) -> 5867 | O33: =K33-P33 -> 86 | P33: 5781
C36: Donations from Mass Intentions /Pledges: (see Schedule A)
E38: Donations ( net of Stipend ) | K38: 0 | M38: =SUM(K31:K38) -> 5867
C40: Donations ( Alay Kapwa Envelopes ) | K40: 0 | M40: =SUM(K33:K40) -> 5867
C42: Total Cash Available | L42: P | M42: =M9+M38 -> 13274.75
C45: Less: Expenses for the month of July 2025
C47: Date | E47: PCV # | G47: Particulars | K47: Amount
C49: July 08 | G49: Candles for Chapel | K49: 282.4
H50: Labor= 8170.00 + Materials=9030.00
C51: July 08 | G51: Labor Expenses (cleaning roof and cutting/trimming trees ) | K51: 408
C52: June 14 | H52: Labor= 13,500.00 + Materials=8,506.00
C53: July 16 | G53: Water Expenses ( Billing period - June 11 to July 11 2025) ) | K53: 151.5
C54: July 16 | G54: Electricity Expenses ( Meralco Bill Share - May 21 to June 20 ) | K54: 601
C55: July 31 | G55: Labor & Meal Expenses ( Bioman - cleaning/cutting mango tree ) | K55: 237.15 | M55: =SUM(K49:K55) -> 1680.05
K56: 0
K57: 0
K58: 0
K59: 0
K60: 0
K61: 0
K62: 0
K63: 0
K64: 0
C66: Net of Expenses | M66: =M42-M55 -> 11594.7
C68: Less: Deposits for the month of July2025 | M68: 4150.65
E69: 06 January 2025 | K69: 0
E70: 06 January 2025 | K70: 0 | M70: =SUM(K69:K70) -> 0 | O70: 12450 | P70: =K70-O70 -> -12450
C72: Cash Balance as of July 31, 2025 | L72: P | M72: =M66-M68 -> 7444.05 | O72: 0
C75: Cash in Bank as of June 30, 2025 | L75: P | M75: 33148.45
C77: Add: Deposits | M77: 4150.65
C78: Interest ( Net of witholding tax ) | M78: =3.79-0.76 -> 3.03
C79: Less: Withdrawals ( Jan 27 & 30 ) | M79: 0
C80: Cash in Bank as of July 31, 2025 | L80: P | M80: =SUM(M75:M78) -> 37302.13
C84: Prepared by: | G84: Checked by: | I84: Audited by: | J84: Noted by:
C86: Elvira Grafil | G86: Fely Rabano | I86: Tina Murla | J86: Lucky Tiu
C87: Asst. Treasurer | G87: Treasurer | I87: Auditor | J87: President

Sheet July 2025 Sched A
B2: Schedule A
B5: Our Lady of the Most Holy Rosary (Sub-Parish)
G6: Control File - Receipts
F7: For the month of July 2025
G9: DONATIONS (Mass Intentions:Thanksgiving, Souls, others) | H9: DONATIONS | I9: Net of Donations | J9: STIPEND from | L9: Total Stipend
B10: Date | D10: OR Number | F10: Donor | J10: Donations | K10: Mass Collections
B11: July
B12: 06 | D12: 3037 | F12: Lucy Saramosing | G12: 100
B13: 06 | D13: =1+D12 -> 3038 | F13: Irene Masong | G13: 100
B14: 06 | D14: =1+D13 -> 3039 | F14: Eloisa Banog | G14: 100
B15: 06 | D15: =1+D14 -> 3040 | F15: Mrs. Molina | G15: 100
B16: 06 | D16: =1+D15 -> 3041 | F16: Elmer Buere | G16: 100
B17: 06 | D17: =1+D16 -> 3042 | F17: Beng Grafil | G17: 100
B18: 06 | D18: =1+D17 -> 3043 | F18: Aviles Family | G18: 100
B19: 06 | D19: =1+D18 -> 3044 | F19: Juvy Mateo | G19: 100
B20: Sub-Total | G20: =SUM(G12:G19) -> 800 | I20: =G20-J20 -> 0 | J20: 800 | K20: 200 | L20: =J20+K20 -> 1000
B21: 13 | D21: 3051 | F21: Eloisa Banog | G21: 100
B22: 13 | D22: =1+D21 -> 3052 | F22: Gina Albarido | G22: 100
B23: 13 | D23: =1+D22 -> 3053 | F23: Beng Grafil | G23: 100
B24: 13 | D24: =1+D23 -> 3054 | F24: Jane Pasamba | G24: 100
B25: 13 | D25: =1+D24 -> 3055 | F25: Baby Boris | G25: 100
B26: 13 | D26: =1+D25 -> 3056 | F26: Thesa | G26: 100
G27: 0
G28: 0
G29: 0
B30: Sub-Total | G30: =SUM(G21:G29) -> 600 | I30: =G30-J30 -> 0 | J30: 600 | K30: 400 | L30: =J30+K30 -> 1000
B31: 20 | D31: 3057 | F31: Beng Grafil | G31: 100
B32: 20 | D32: =1+D31 -> 3058 | F32: Reylyn Calonge | G32: 100
B33: 20 | D33: =1+D32 -> 3059 | F33: Jane Pasamba | G33: 100
B34: 20 | D34: =1+D33 -> 3060 | F34: Elmer Buere | G34: 100
B35: 20 | D35: =1+D34 -> 3061 | F35: Lucy Saramosing | G35: 100
B36: 20 | D36: =1+D35 -> 3062 | F36: Tina Mur;a | G36: 100
B37: Sub-Total | G37: =SUM(G31:G36) -> 600 | I37: =G37-J37 -> 0 | J37: 600 | K37: 400 | L37: =J37+K37 -> 1000
B38: 27 | D38: 3045 | F38: Maria Luisa | G38: 100
B39: 27 | D39: =1+D38 -> 3046 | F39: Geraldine | G39: 100
B40: 27 | D40: =1+D39 -> 3047 | F40: Baby Boris | G40: 100
B41: 27 | D41: =1+D40 -> 3048 | F41: Eloisa Banog | G41: 100
B42: 27 | D42: =1+D40 -> 3048 | F42: Gina Albarido | G42: 100
B43: 27 | D43: - | F43: No Official Receipt | G43: 100
B44: Sub-Total | G44: =SUM(G38:G43) -> 600 | I44: =G44-J44 -> 0 | J44: 600 | K44: 400 | L44: =J44+K44 -> 1000
L45: =J45+K45 -> 0
L46: =J46+K46 -> 0
B53: Sub-Total | G53: =SUM(G45:G52) -> 0 | I53: =G53-J53 -> 0 | J53: 0 | K53: 0 | L53: =J53+K53 -> 0
B54: TOTAL | G54: =G53+G44+G37+G30+G20 -> 2600 | I54: =I53+I44+I37+I30+I20 -> 0 | J54: =J53+J44+J37+J30+J20 -> 2600 | K54: =K53+K44+K37+K30+K20 -> 1400 | L54: =L53+L44+L37+L30+L20 -> 4000
B58: Stipend for the month of July 2025
B60: Period covered | F60: Amount
B61: July | C61: 06 | F61: 1000
B62: July | C62: 13 | F62: 1000
B63: July | C63: 20 | F63: 1000
B64: July | C64: 27 | F64: 1000
B65: July | C65: 29 | F65: 0
B69: Total Stipend | F69: =SUM(F61:F67) -> 4000

Sheet April 2021
D1: Our Lady of the Most Holy Rosary (Sub-Parish)
D2: Control File - Receipts | E2: Control File - Receipts
E3: Month of April 2021
F5: Pamisa &
A6: Date | C6: Rcpt. # | E6: Donor | F6: Thanksgiving | H6: Soul | I6: Stipend | K6: Street
A8: 04 | C8: 1863 | E8: Helen Caballero | I8: 200
A9: 04 | C9: 1864 | E9: Tina Murla | I9: 200
A10: 11 | C10: 1865 | E10: Art de Leon | I10: 500
A11: 11 | C11: 1866 | E11: Edna Mejia | H11: 200 | I11: 200
A12: 11 | C12: 1867 | E12: Lucy Saramosing | H12: 50 | I12: 100
A13: 18 | C13: 1868 | E13: Kenneth Tiu | I13: 1000
A14: 25 | C14: 1869 | E14: Opcinar Fam. | I14: 100
A15: 25 | C15: 1870 | E15: Lucy Saramosing | H15: 60 | I15: 100
A16: 25 | C16: 1871 | E16: Edna Mejia | I16: 100
A17: 25 | C17: 1872 | E17: Irene Masong | I17: 500
I19: =SUM(I8:I17) -> 3000
C20: Prepared by:
E22: Fely Rabano
E23: Treasurer
A25: STIPEND:
A26: April | C26: 04
C27: 11
C28: 18
C29: 25 | E29: 4 Sundays @ 800 ea. …………………. | I29: 3200

Sheet May 2021
D1: Our Lady of the Most Holy Rosary (Sub-Parish)
D2: Control File - Receipts | E2: Control File - Receipts
E3: Month of May 2021
F5: Pamisa &
A6: Date | C6: Rcpt. # | E6: Donor | F6: Thanksgiving | H6: Soul | I6: Stipend | K6: Donation
A8: 02 | C8: 1873 | E8: Irene Masong | I8: 100
A9: 08 | C9: 1874 | E9: Baby Hernando | I9: 1000
A10: 08 | C10: 1875 | E10: Nida Alberto | I10: 500
A11: 16 | C11: 1876 | E11: Art de Leon | I11: 500
A12: 16 | C12: 1877 | E12: Hernando Family | I12: 100
A13: 16 | C13: 1878 | E13: Lucy Saramosing | I13: 100
A14: 16 | C14: 1879 | E14: J. Mateo | I14: 100
A15: 16 | C15: 1880 | E15: Helen Caballero | H15: 200 | I15: 1000
A16: 23 | C16: 1881 | E16: Art de Leon | I16: 200
A17: 23 | C17: 1882 | E17: Lerma Marabut | I17: 100
A18: 30 | C18: 1883 | E18: Elmer Buere | I18: 100
I20: =SUM(I8:I18) -> 3800
C22: Prepared by:
E24: Fely Rabano
E25: Treasurer
A28: STIPEND:
A29: May | C29: 02
C30: 09
C31: 16
C32: 23
C33: 30 | E33: 5 Sundays @ 800 ea. …………………. | I33: 4000

Sheet June 2022
D1: Our Lady of the Most Holy Rosary (Sub-Parish)
D2: Control File - Receipts | E2: Control File - Receipts
E3: Month of June 2022 | H3: PAMISA
F5: Pamisa & | I5: from | K5: from mass | M5: Total
A6: Date | C6: Rcpt. # | E6: Donor | F6: Thanksgiving | H6: Soul | I6: Pamisa | K6: collection | M6: Stipend
A8: 05 | C8: 2113 | E8: Lucy Saramosing | F8: 100
A9: 05 | C9: 2114 | E9: Gina Albarido | F9: 50
A10: 05 | C10: 2115 | E10: Lucy Saramosing | H10: 50
A11: 05 | C11: 2116 | E11: Jane Pasamba | F11: 100
A12: 05 | C12: 2117 | E12: Elmer Buere | F12: 100
F13: 100 | I13: 450 | K13: 550 | M13: 1000
A14: 12 | C14: 2118 | E14: Gina Albarido | F14: 100
A15: 12 | C15: 2119 | E15: Lucy Saramosing | F15: 100
A16: 12 | C16: 2120 | E16: Reylyn Calonge | F16: 100
A17: 12 | C17: 2121 | E17: Elmer Buere | F17: 100
A18: 12 | C18: 2122 | E18: Ana Grafil & Fam. | F18: 500
A19: 12 | E19: Tina M. | F19: 100 | I19: 1000 | M19: 1000
A20: 16 | C20: 2123 | E20: Art de Leon | F20: 1000 | H20: (donation for roof painting)
A21: 18 | C21: 2124 | E21: Fely Rabano | F21: 1000 | H21: (donation for roof painting)
A22: 19 | C22: 2125 | E22: Billy Lara | H22: 100
A23: 19 | C23: 2126 | E23: Irene Masong | F23: 1000 | H23: (donation for roof painting)
A24: 19 | C24: 2127 | E24: Reylyn Calonge | F24: 100
A25: 19 | C25: 2128 | E25: Gina Albarido | F25: 500 | H25: (donation for roof painting)
A26: 19 | C26: 2129 | E26: Ebon Andres | F26: 110
A27: 19 | C27: 2130 | E27: Belma Veloria | F27: 100
A28: 19 | C28: 2131 | E28: Elmer Buere | F28: 100
A29: 19 | C29: 2132 | E29: Euben Conseja | F29: 150 | I29: 560 | K29: 440 | M29: 1000
A30: 26 | C30: 2133 | E30: Thin Tapaoan | F30: 1000 | H30: (donation for roof painting)
A31: 26 | C31: 2134 | E31: Gina Albarido | F31: 100
A32: 26 | C32: 2135 | E32: Jane Pasamba | F32: 100 | I32: 200 | K32: 800 | M32: 1000
I34: =SUM(I9:I32) -> 2210 | K34: =SUM(K8:K32) -> 1790 | M34: =SUM(I34:K34) -> 4000
C35: Total mass collection …… | F35: =SUM(F8:F32) -> 6710
E37: For mass stipend | F37: 2210
E38: Donation | F38: 4500
E39: for deposit | F39: 0
F40: =SUM(F37:F38) -> 6710
C42: Checked by:
A45: STIPEND:
A46: June | C46: 05 | F46: 1000
C47: 12 | F47: 1000
C48: 19 | F48: 1000
C49: 26 | F49: 1000
E50: 4 Sundays @ 1000 ea. …………………. | I50: 4000

Sheet July 2022
D1: Our Lady of the Most Holy Rosary (Sub-Parish)
D2: Control File - Receipts | E2: Control File - Receipts
E3: Month of July 2022
F5: Pamisa & | I5: from | K5: from mass | M5: Total
A6: Date | C6: Rcpt. # | E6: Donor | F6: Thanksgiving | H6: Soul | I6: Pamisa | K6: collection | M6: Stipend
A8: 03 | C8: 2136 | E8: Lucky Tiu | F8: 50
A9: 03 | C9: 2137 | E9: Lucy Saramosing | F9: 90 | H9: 90
A10: 03 | C10: 2138 | E10: Annie Alejandria | F10: 50
A11: 03 | C11: 2139 | E11: Tess Sabado | F11: 300
A12: 10 | C12: 2140 | E12: Reylyn Calonge | F12: 100 | I12: 500 | K12: 500 | M12: 1000
A13: 10 | C13: 2141 | E13: Lucky Tiu | F13: 100
A14: 10 | C14: 2142 | E14: Gina Albarido | F14: 100
A15: 10 | C15: 2143 | E15: Reylyn Calonge | F15: 100
A16: 10 | C16: 2145 | E16: Helen Caballero | F16: 100
F17: 100
A18: 10 | C18: 2146 | E18: Ramil Montera | F18: 500 | I18: 1000 | M18: 1000
A19: 17 | C19: 2144 | E19: Grace Ilioferer | F19: 100
A20: 17 | C20: 2147 | E20: Elmer Buere | F20: 100
A21: 17 | C21: 2148 | E21: Lucy Saramosing | F21: 100
A22: 17 | C22: 2149 | E22: Love Love | F22: 100
A23: 17 | C23: 2150 | E23: Tessie Castillo | F23: 100 | I23: 500 | K23: 500 | M23: 1000
A24: 24 | C24: 2151 | E24: Jane Pasamba | F24: 100
A25: 24 | C25: 2152 | E25: Reylyn Calonge | F25: 100
A26: 24 | C26: 2153 | E26: Elmer Buere | F26: 100
A27: 24 | C27: 2154 | E27: Avila Fam. | F27: 50
A28: 24 | C28: 2155 | E28: Leo & Elvira Grafil | F28: 500 | I28: 850 | K28: 150 | M28: 1000
A29: 31 | C29: 2156 | E29: Jane Pasamba | F29: 500
A30: 31 | C30: 2157 | E30: Elmer Buere | F30: 100
F31: 200
F32: 100
I33: 900 | K33: 100 | M33: 1000
I34: =SUM(I7:I33) -> 3750 | K34: =SUM(K8:K33) -> 1250 | M34: =SUM(M10:M33) -> 5000
C35: Prepared by:
E37: Treasurer
A39: July 2022
A40: STIPEND: | I40: Stipend
A41: July | C41: 03
C42: 10
C43: 17
C44: 24
C45: 31
E46: 5 Sundays @ 1000 ea. …………………. | I46: 5000

Sheet Aug. 2022
D1: Our Lady of the Most Holy Rosary (Sub-Parish)
D2: Control File - Receipts | E2: Control File - Receipts
E3: Month of August 2022
F5: Pamisa & | J5: from | L5: from mass | N5: Total
A6: Date | C6: Rcpt. # | E6: Donor | F6: Thanksgiving | H6: Soul | J6: Pamisa | L6: collection | N6: Stipend
A8: 07 | C8: 2158 | E8: Irene Masong | F8: 100
A9: 07 | C9: 2159 | E9: Reylen Calonge | F9: 100
A10: 07 | C10: 2160 | E10: Hilda Villena | F10: 1000 | J10: 1000 | N10: 1000
A11: 14 | C11: 2161 | E11: Lucy Saramosing | F11: 100
A12: 14 | C12: 2162 | E12: Edith Galeria | F12: 200
A13: 14 | C13: 2163 | E13: Elmer Buere | F13: 100 | J13: 600 | L13: 400 | N13: 1000
A14: 21 | C14: 2164 | E14: Jesus Lara | F14: 100
A15: 21 | C15: 2165 | E15: Reylen Calonge | F15: 100
A16: 21 | C16: 2166 | E16: Ely Tapaoan | F16: 100
A17: 21 | C17: 2167 | E17: Lorena Bianzon | F17: 500 | J17: 800 | L17: 200 | N17: 1000
A18: 28 | C18: 2168 | E18: Thin Tapaoan | F18: 100
A19: 28 | C19: 2169 | E19: Luz Damian | F19: 100
A20: 28 | C20: 2170 | E20: Palar Fam. | F20: 100
A21: 28 | C21: 2171 | E21: Palar Fam. | F21: 100
A22: 28 | C22: 2172 | E22: Marabut Fam. | F22: 500 | J22: 900 | L22: 100 | N22: 1000
J23: =SUM(J9:J22) -> 3300 | L23: =SUM(L12:L22) -> 700 | N23: =SUM(N10:N22) -> 4000
C25: Prepared by:
E27: Treasurer
A29: STIPEND:
A30: August | C30: 07
C31: 14
C32: 21
C33: 28
E34: 4 Sundays @ 1000 ea. …………………. | J34: 4000

Sheet Sept. 2022
D1: Our Lady of the Most Holy Rosary (Sub-Parish)
D2: Control File - Receipts | E2: Control File - Receipts
E3: Month of September 2022
F5: Pamisa & | I5: from | K5: from mass | M5: Total
A6: Date | C6: Rcpt. # | E6: Donor | F6: Thanksgiving | H6: Soul | I6: pamisa | K6: collection | M6: Stipend
A8: 04 | C8: 2172 | E8: Lucy Saramosing | F8: 100
A9: 04 | C9: 2173 | E9: Lucky Tiu | F9: 100
A10: 04 | C10: 2175 | E10: Irene Masong | F10: 100
A11: 04 | C11: 2176 | E11: Erbon Andres | F11: 300 | I11: 600 | K11: 400 | M11: 1000
A12: 11 | C12: 2177 | E12: Lucy Saramosing | F12: 100
A13: 11 | C13: 2178 | E13: Gina Albarido | F13: 120
A14: 11 | C14: 2179 | E14: Reylyn Calonge | F14: 100
A15: 11 | C15: 2180 | E15: Jane Pasamba | F15: 100
A16: 11 | C16: 2181 | E16: Elmer Buere | F16: 100 | I16: =SUM(F12:F16) -> 520 | K16: 480 | M16: =SUM(I16:K16) -> 1000
A17: 18 | C17: 2182 | E17: Gina Albarido | F17: 150
A18: 18 | C18: 2183 | E18: Elmer Buere | F18: 100 | I18: 250 | K18: 750 | M18: 1000
A19: 25 | C19: 2184 | E19: Gina Albarido | F19: 100
A20: 25 | C20: 2185 | E20: Reylyn Calonge | F20: 100
A21: 25 | C21: 2186 | E21: Jane Pasamba | F21: 100
A22: 25 | C22: 2187 | E22: Tess Sabado | F22: 200 | I22: 500 | K22: 500 | M22: 1000
C23: 2188 | E23: cancelled
I24: =SUM(I8:I22) -> 1870 | K24: =SUM(K10:K22) -> 2130 | M24: =SUM(I24:K24) -> 4000
C27: Prepared by:
A31: STIPEND: | I31: Stipend
A32: September | C32: 04
C33: 11
C34: 18
C35: 25
E36: 4 Sundays @ 1000.00 ea. | I36: 4000

Sheet Oct. 2023
D1: Our Lady of the Most Holy Rosary (Sub-Parish)
D2: Control File - Receipts | E2: Control File - Receipts
E3: Month of October 2023
F4: Pamisa & | I4: from | K4: from mass | L4: Total
A5: Date | C5: Rcpt. # | E5: Donor | F5: Thanksgiving | H5: Donation | I5: pamisa | K5: collection | L5: Stipend
A7: 01 | C7: 2439 | E7: J. Pasamba | F7: 100
A8: 01 | C8: 2440 | E8: Tina P. | F8: 100
A9: 01 | C9: 2441 | E9: Regine Estrada | F9: 100
A10: 01 | C10: 2442 | E10: Gina Albarido | F10: 100
A11: 01 | C11: 2443 | E11: Leo Grafil | F11: 500
A12: 01 | C12: 2444 | E12: Elmer Buere | F12: 100 | I12: =SUM(F7:F12) -> 1000 | L12: 1000 | M12: (10/01)
A13: 01 | C13: 2445 | E13: Irene M. | F13: 100 | H13: 100
A14: 01 | C14: 2446 | E14: Hilda Villena | F14: 100 | H14: 100
A15: 08 | C15: 2447 | E15: Elmer Buere | F15: 100
A16: 08 | C16: 2448 | E16: Thin Tapaoan | F16: 100
A17: 08 | C17: 2449 | E17: Gina Albarido | F17: 100 | I17: 300 | K17: 700 | L17: 1000 | M17: (10/08)
A18: 15 | C18: 2450 | E18: Doc Edwin | H18: 2000
A19: 18 | C19: 2451 | E19: Grace Villarisco | H19: 3000
A20: 19 | C20: 2452 | E20: M. Padua | F20: 50
A21: 19 | C21: 2453 | E21: F. Rabano | F21: 100
A22: 20 | C22: 2454 | E22: F. Rabano | F22: 100
A23: 21 | C23: 2455 | E23: M. Padua | F23: 100
A24: 21 | C24: 2456 | E24: Rose Riambon | L24: 1500 | M24: (10/21)
A25: 21 | C25: 2457 | E25: Ebon Andres | F25: 100
A26: 21 | C26: 2458 | E26: Teresa Pesalbon | H26: 1000
A27: 21 | C27: 2459 | E27: Madel Belino | H27: 1500
A28: 22 | C28: 2460 | E28: Gina Albarido | F28: 100
A29: 22 | C29: 2461 | E29: Thin Tapaoan | F29: 100
A30: 22 | C30: 2462 | E30: Regine Estrada | F30: 100
A31: 22 | C31: 2463 | E31: cancelled
A32: 22 | C32: 2464 | E32: M. Padua | F32: 50
A33: 22 | C33: 2465 | E33: Eloisa | F33: 100
A34: 22 | C34: 2466 | E34: L. Bianzon | F34: 100
A35: 22 | C35: 2467 | E35: Jane P. | F35: 100
A36: 22 | C36: 2468 | E36: DCV HOA | H36: Sunday Mass | L36: 1500 | M36: (10/22)
A37: 22 | C37: 2469 | E37: Belma | F37: 100
A38: 22 | C38: 2470 | E38: Helen | F38: 100
A39: 22 | C39: 2471 | E39: Reylyn | F39: 100
A40: 22 | C40: 2472 | E40: Elmer Buere | F40: 100
A41: 22 | C41: 2473 | E41: Zenaida | F41: 100
A42: 22 | C42: 2474 | E42: Irene M. | F42: 100
A43: 22 | C43: 2475 | E43: Belma | F43: 200
F44: =SUM(F19:F43) -> 1900
A45: 29 | C45: 2476 | E45: Rachelle | F45: 200
A46: 29 | C46: 2477 | E46: Lucy | F46: 100
A47: 29 | C47: 2478 | E47: Art de Leon | F47: 200
A48: 29 | C48: 2479 | E48: Regine Estrada | F48: 100
A49: 29 | C49: 2480 | E49: Elmer Buere | F49: 100 | I49: 700 | K49: 200 | L49: 1000 | M49: (10/29)
E50: donation | H50: =SUM(H16:H47) -> 7500
C52: Prepared by:
A55: STIPEND: | F55: Sponsor | I55: Amount
A56: October | C56: 01 | I56: 1000
C57: 08 | I57: 1000
C58: 15 | E58: no mass
A59: Thursday | C59: 19 | E59: Triduum Mass | F59: Triumph & Laurel St. | I59: 1500 | K59: (no receipt)
A60: Friday | C60: 20 | E60: Triduum Mass | F60: Yuletide & Glory St. | I60: 1500 | K60: (no receipt)
A61: Saturday | C61: 22 | E61: Triduum Mass | F61: Rose Riambon | I61: 1500
A62: Sunday | C62: 23 | E62: Fiesta | F62: DCV HOA | I62: 1500

Sheet Nov. 2023
D1: Our Lady of the Most Holy Rosary (Sub-Parish)
D2: Control File - Receipts | E2: Control File - Receipts
E3: Month of November 2023
F5: Pamisa & | J5: from mass | L5: from mass | M5: Total
A6: Date | C6: Rcpt. # | E6: Donor | F6: Thanksgiving | H6: Soul | J6: pamisa | L6: collection | M6: Stipend
A8: 11-06-22 | C8: 2216 | E8: Lucky Tiu | F8: 100
A9: 11-06-22 | C9: 2217 | E9: Elmer Buere | F9: 100
A10: 11-06-22 | C10: 2218 | E10: Reylyn Calonge | F10: 100
A11: 11-06-22 | C11: 2219 | E11: Lucy Saramosing | F11: 100 | J11: 400 | L11: 600 | M11: 1000 | N11: 44871
A12: 11-13-22 | C12: 2220 | E12: Reylyn Calonge | F12: 100
A13: 11-13-22 | C13: 2221 | E13: Elmer Buere | F13: 100
A14: 11-18-22 | C14: 2222 | E14: Siony Tugado | F14: 250 | J14: 450 | L14: 550 | M14: 1000 | N14: 44878
A15: 11-17-22 | C15: 2223 | E15: Belma Veloria | F15: 1000 | J15: 1000 | M15: 1000 | N15: 44882
A16: 11-18-22 | C16: 2224 | E16: Albarido | F16: 100
A17: 11-19-22 | C17: 2225 | E17: Elmer Buere | F17: 100
A18: 11-19-22 | C18: 2226 | E18: Fely Rabano | F18: 100
A19: 11-19-22 | C19: 2227 | E19: Siony Tugado | F19: 50
A20: 11-19-22 | C20: 2228 | E20: Luz Damian | F20: 50
A21: 11-19-22 | C21: 2229 | F21: 50
A22: 11-19-22 | C22: 2230 | E22: Jane Pasamba | F22: 100 | J22: =SUM(F16:F22) -> 550 | L22: 450 | M22: 1000 | N22: 44883
A23: 11-19-22 | C23: 2231 | E23: Labog Family | F23: 500
A24: 11-19-22 | C24: 2232 | E24: Helen Caballero | F24: 500 | J24: 1000 | M24: 1000 | N24: 44884
A25: 10-16-22 | C25: 2251
A26: 11-27-22 | C26: 2252 | E26: Irene Masong | F26: 100
A27: 11-27-22 | C27: 2253 | E27: Gina Albarido | F27: 100
A28: 11-27-22 | C28: 2254 | E28: Reylyn Calonge | F28: 100
A29: 11-27-22 | C29: 2255 | E29: N. Grafil | F29: 200
A30: 11-27-22 | F30: 90 | J30: =SUM(F26:F30) -> 590 | L30: 410 | M30: 1000 | N30: 44892
J31: =SUM(J10:J30) -> 3990 | L31: =SUM(L11:L30) -> 2010 | M31: =SUM(M11:M30) -> 6000
C33: Prepared by:
E35: Treasurer
A36: STIPEND:
A37: Nov. 2023 | J37: Stipend
C38: 06 | J38: 1000
C39: 13 | J39: 1000
C40: 17 | E40: Triduum Mass | J40: 1000
C41: 18 | E41: Triduum Mass | J41: 1000
C42: 19 | E42: Triduum Mass | J42: 1000
C43: 20 | E43: No Mass at DCV - Feast of Christ the King
C44: 27 | J44: 1000

Sheet Dec. 2023
D1: Our Lady of the Most Holy Rosary (Sub-Parish)
D2: Control File - Receipts | E2: Control File - Receipts
E3: Month of December 2023
F5: Pamisa & | K5: from
A6: Date | C6: Rcpt. # | E6: Donor | F6: Thanksgiving | H6: Donation | I6: Stipend | K6: collection | L6: Stipend | M6: Date
A7: December
A8: 03 | C8: 2493 | E8: Thin Tapaoan | F8: 100
A9: 03 | C9: 2494 | E9: Lucky Tiu | F9: 100
A10: 03 | C10: 2495 | E10: Thelma Lara | F10: 50
A11: 03 | C11: 2496 | E11: Dehlie | F11: 100
A12: 03 | C12: 2497 | E12: Art de Leon | F12: 200
A13: 03 | C13: 2498 | E13: Annie | F13: 20
A14: 03 | C14: 2499 | E14: Lucy Saramosing | F14: 100
E15: (no receipt) | F15: 100 | I15: =SUM(F8:F15) -> 770 | K15: 230 | L15: 1000 | M15: Dec. 03
A16: 10 | C16: 2500 | E16: Annie | F16: 50
A17: 10 | C17: 2501 | E17: Reylyn | F17: 100
A18: 10 | C18: 2502 | E18: Art de Leon | F18: 200
A19: 10 | C19: 2503 | F19: 100
A20: 10 | C20: 2504 | E20: Elmer | F20: 200 | I20: =SUM(F16:F20) -> 650 | K20: 350 | L20: 1000 | M20: Dec. 10
A21: 15 | C21: 2505 | E21: Freddie D. | F21: 50
A22: 15 | C22: 2506 | E22: Annie | F22: 100
A23: 15 | C23: 2507 | E23: Salas Fam. | F23: 100
A24: 15 | C24: 2508 | E24: Elmer /b, | F24: 100
A25: 15 | C25: 2509 | E25: Ebon Andres | F25: 400
A26: 15 | C26: 2510 | E26: Myrna Barcena | F26: 500 | I26: =SUM(F21:F26) -> 1250 | K26: 250 | L26: 1500 | M26: Dec. 15
A27: 16 | C27: 2511 | E27: Annie | F27: 50
A28: 16 | C28: 2512 | E28: Art de Leon | F28: 200
A29: 16 | C29: 2513 | E29: Elmer Buere | F29: 100
A30: 16 | C30: 2514 | E30: Reylyn | F30: 100
A31: 16 | C31: 2515 | E31: Diamante Fam. | F31: 200 | I31: =SUM(F27:F31) -> 650 | K31: 850 | L31: 1500 | M31: Dec. 16
A32: 17 | C32: 2516 | E32: Rose Riambon | F32: 1500 | L32: 1500 | M32: Dec. 17
A33: 17 | C33: 2517 | E33: Elmer | F33: 100
A34: 17 | C34: 2518 | E34: Hilda | F34: 100
A35: 18 | C35: 2519 | E35: Reylyn | F35: 100
A36: 18 | C36: 2520 | E36: Art de Leon | F36: 200
A37: 18 | C37: 2521 | E37: Thin | F37: 100
A38: 18 | C38: 2522 | E38: Lerma | F38: 500
A39: 18 | C39: 2523 | E39: Nanie Domingo | F39: 100
A40: 18 | C40: 2524 | E40: Elmer | F40: 100
A41: 18 | C41: 2525 | E41: Emily | F41: 100 | H41: =SUM(F33:F41) -> 1400
A42: 18 | C42: 2526 | E42: Linda Sarmiento | F42: 1500 | L42: 1500 | M42: Dec. 18
A43: 19 | C43: 2527 | E43: Thin | F43: 100
A44: 19 | C44: 2528 | E44: Henry | F44: 100
A45: 19 | C45: 2529 | E45: Annie | F45: 50
A46: 19 | C46: 2530 | E46: Buelva | F46: 100
A47: 19 | C47: 2531 | E47: Emma | F47: 100
A48: 19 | C48: 2532 | E48: Baby P. | F48: 500 | H48: =SUM(F43:F48) -> 950
A49: 19 | C49: 2533 | E49: Teresa Pesalbon | F49: 1500 | L49: 1500 | M49: Dec. 19
A58: 19 | C58: 2534 | E58: Anne Senanin | F58: 500 | H58: 500
A59: 20 | C59: 2535 | E59: Gina A. | F59: 100 | H59: 100
A60: 20 | C60: 2536 | E60: Art de Leon | F60: 750
A61: 20 | C61: 2537 | E61: Annie | F61: 20
A62: 20 | C62: 2538 | E62: Jane P. | F62: 100 | H62: 100
A63: 20 | C63: 2539 | E63: Nanie Domingo | F63: 300 | H63: 300
A64: 20 | C64: 2540 | E64: Elmer | F64: 100
A65: 20 | C65: 2541 | E65: Mhonique Polison | F65: 500
A66: 20 | C66: 2542 | E66: Sagun Fam. | F66: 110
A67: 20 | E67: (no receipt) | F67: 20 | I67: 1500 | L67: 1500 | M67: Dec. 20
A68: 21 | C68: 2543 | E68: Gina A. | F68: 100
A69: 21 | C69: 2544 | E69: Elmer | F69: 100
A70: 21 | C70: 2545 | E70: Teresa Pesalbon | F70: 1000
A71: 22 | C71: 2546 | E71: Elmer | F71: 100
A72: 23 | C72: 2547 | E72: Reylyn | F72: 100
A73: 23 | C73: 2548 | E73: Fely R. | F73: 100 | I73: =SUM(F68:F73) -> 1500 | L73: 1500 | M73: Dec. 21
A74: 23 | C74: 2549 | E74: Nanie Domingo | F74: 50
A75: 23 | C75: 2550 | E75: Belma | F75: 100
A76: 25 | C76: 2551 | E76: Rabano | F76: 100
A77: 25 | C77: 2552 | E77: Elmer | F77: 100
A78: 25 | C78: 2553 | E78: Irene M. | F78: 100
A79: 25 | C79: 2554 | E79: Atienza Fam. | F79: 100
A80: 25 | C80: 2555 | E80: Baby P. | F80: 300
A81: 25 | C81: 2556 | E81: Leonie Aviles | F81: 200 | I81: =SUM(F74:F81) -> 1050 | K81: 450 | L81: 1500 | M81: Dec. 22
E82: Fely & Luz D. | F82: 1500 | L82: 1500 | M82: Dec. 23
A83: 25 | C83: 2557 | E83: Madel Belino | F83: 1500 | L83: 1500 | M83: Dec. 25
A84: 31 | C84: 2558 | E84: Elmer | F84: 100 | H84: 100
A85: 31 | C85: 2559 | E85: Linda Sarmiento | F85: 1500 | L85: 1500 | M85: Dec. 31
A86: 31 | C86: 2560 | E86: Lucy Saramosing | F86: 100 | H86: 100
C87: 2561 | E87: (cancelled)
A88: 26 | C88: 2562 | E88: Grace Villarisco | F88: 3000 | H88: 3000
E91: Net collection …………….. | H91: =SUM(H10:H88) -> 6550
C93: Prepared by:
A109: STIPEND | H109: Add'l | I109: Total
A110: Date | E110: Mass Sponsor: | H110: Stipend | I110: Stipend
A111: DECEMBER
A112: 03 | F112: 770 | H112: 230 | I112: 1000
A113: 10 | F113: 650 | H113: 350 | I113: 1000
A114: 15 | C114: S.Gabi | F114: 1250 | G114: 1000 | H114: 250 | I114: 1500
A115: 16 | C115: S.Gabi | F115: 650 | G115: 1000 | H115: 850 | I115: 1500
A116: 17 | C116: S.Gabi | E116: Rose Riambon | F116: 1500 | G116: 1000 | I116: 1500
A117: 18 | C117: S.Gabi | E117: Linda Sarmiento | F117: 1500 | G117: 1000 | I117: 1500
A118: 19 | C118: S.Gabi | E118: Teresa Pesalbon | F118: 1500 | G118: 1000 | I118: 1500
A119: 20 | C119: S.Gabi | E119: Art de Leon | F119: 750 | G119: 1000 | H119: 750 | I119: 1500
A120: 21 | C120: S.Gabi | F120: 1500 | G120: 1000 | I120: 1500
A121: 22 | C121: S.Gabi | F121: 1050 | G121: 1000 | H121: 450 | I121: 1500
A122: 23 | C122: S.Gabi | E122: Fely R.. & Luz D. | F122: 1500 | G122: 1000 | I122: 1500
A123: 25 | C123: Xmas | E123: Madel Belino | F123: 1500 | I123: 1500
A124: 31 | E124: Linda Sarmiento | F124: 1500 | G124: 1000 | I124: 1500

Sheet Sheet1
